Workbook

Sheet Dashboard
A1: TCO Nissan Tiida — baseline atual para decisão de troca por EV
A3: Atualizado até | B3: 46278 | C3: Km/ano | D3: 21438 | E3: TCO central / mês | F3: 2304.55 | G3: TCO econômico / mês | H3: 2397.16
A5: 1. Histórico real — 12 meses móveis | F5: 2. Baseline para frente — cenário CENTRAL
A6: Componente | B6: Anual | C6: Mensal | D6: R$/km | F6: Componente | G6: Anual | H6: Mensal | I6: Lógica
A7: Combustível real | B7: 13267.21 | C7: =ROUND(B7/12,2) -> 1105.6 | D7: =ROUND(B7/$D$3,3) -> 0.619 | F7: Combustível otimizado | G7: 10858.57 | H7: =ROUND(G7/12,2) -> 904.88 | I7: Etanol: km/ano ÷ km/L × R$/L
A8: Serviços reais | B8: 17782.46 | C8: =ROUND(B8/12,2) -> 1481.87 | D8: =ROUND(B8/$D$3,3) -> 0.829 | F8: Manutenção central | G8: 11700.83 | H8: =ROUND(G8/12,2) -> 975.07 | I8: Histórico longo R$/km × uso atual
A9: Seguro | B9: 3516.24 | C9: =ROUND(B9/12,2) -> 293.02 | D9: =ROUND(B9/$D$3,3) -> 0.164 | F9: Seguro | G9: 3516.24 | H9: =ROUND(G9/12,2) -> 293.02 | I9: Custo atual
A10: IPVA estimado | B10: 1404.88 | C10: =ROUND(B10/12,2) -> 117.07 | D10: =ROUND(B10/$D$3,3) -> 0.066 | F10: IPVA | G10: 1404.88 | H10: =ROUND(G10/12,2) -> 117.07 | I10: Estimativa 2026
A11: Licenciamento | B11: 174.08 | C11: =ROUND(B11/12,2) -> 14.51 | D11: =ROUND(B11/$D$3,3) -> 0.008 | F11: Licenciamento | G11: 174.08 | H11: =ROUND(G11/12,2) -> 14.51 | I11: 2026
A12: TCO histórico real | B12: =ROUND(SUM(B7:B11),2) -> 36144.87 | C12: =ROUND(B12/12,2) -> 3012.07 | D12: =ROUND(B12/$D$3,3) -> 1.686 | F12: TCO de caixa CENTRAL | G12: =ROUND(SUM(G7:G11),2) -> 27654.6 | H12: =ROUND(G12/12,2) -> 2304.55 | I12: Base principal para comparar parcela
F13: Depreciação econômica | G13: 1111.32 | H13: =ROUND(G13/12,2) -> 92.61 | I13: 3% a.a. sobre FIPE atual
F14: TCO econômico CENTRAL | G14: =ROUND(G12+G13,2) -> 28765.92 | H14: =ROUND(G14/12,2) -> 2397.16 | I14: Caixa + depreciação
A16: 3. Sensibilidade da manutenção e do TCO
A17: Cenário | B17: Manutenção/ano | C17: TCO caixa/ano | D17: TCO caixa/mês | E17: TCO econômico/mês | F17: R$/km | G17: Uso | H17: Base | I17: Leitura
A18: Otimista | B18: 8739.46 | C18: =ROUND($G$7+B18+$G$9+$G$10+$G$11,2) -> 24693.23 | D18: =ROUND(C18/12,2) -> 2057.77 | E18: =ROUND((C18+$G$13)/12,2) -> 2150.38 | F18: =ROUND(C18/$D$3,3) -> 1.152 | G18: Piso | H18: 12m + corretivas/3 | I18: Grandes corretivas recentes não se repetem cedo
A19: CENTRAL — histórico longo | B19: 11700.83 | C19: =ROUND($G$7+B19+$G$9+$G$10+$G$11,2) -> 27654.6 | D19: =ROUND(C19/12,2) -> 2304.55 | E19: =ROUND((C19+$G$13)/12,2) -> 2397.16 | F19: =ROUND(C19/$D$3,3) -> 1.29 | G19: PRINCIPAL | H19: 2021–2026 | I19: Melhor caso-base para comparar EV
A20: Central+ — proxy externas | B20: 12881.2 | C20: =ROUND($G$7+B20+$G$9+$G$10+$G$11,2) -> 28834.97 | D20: =ROUND(C20/12,2) -> 2402.91 | E20: =ROUND((C20+$G$13)/12,2) -> 2495.52 | F20: =ROUND(C20/$D$3,3) -> 1.345 | G20: Sensibilidade | H20: Histórico + proxy | I20: Inclui referência de peças externas da OS 11032
A21: Stress — sua posse recente | B21: 15295.73 | C21: =ROUND($G$7+B21+$G$9+$G$10+$G$11,2) -> 31249.5 | D21: =ROUND(C21/12,2) -> 2604.13 | E21: =ROUND((C21+$G$13)/12,2) -> 2696.74 | F21: =ROUND(C21/$D$3,3) -> 1.458 | G21: Teto | H21: Jun/25–set/26 | I21: Mantém o ritmo recente de envelhecimento
A22: Histórico real 12m | B22: 17782.46 | C22: 36144.87 | D22: 3012.07 | E22: 3104.68 | F22: 1.686 | G22: Referência | H22: 12m móveis | I22: Fluxo real recente, não forecast
A24: 4. Manutenção — 12 meses móveis | F24: 5. Combustível — premissas atuais
A25: Categoria | B25: Valor | C25: % | D25: Tratamento | F25: Métrica | G25: Valor | H25: Unidade | I25: Leitura
A26: Preventiva / desgaste | B26: 4498.46 | C26: =B26/$B$29 -> 0.25297175 | D26: Recorrente / desgaste | F26: Etanol | G26: 3.89 | H26: R$/L | I26: Preço mais recente
A27: Corretiva / recuperação | B27: 12723 | C27: =B27/$B$29 -> 0.71548031 | D27: Usada em sensibilidade | F27: Gasolina | G27: 6.29 | H27: R$/L | I27: Preço mais recente
A28: Incidente / carroceria | B28: 561 | C28: =B28/$B$29 -> 0.031547941 | D28: Não recorrente | F28: Relação etanol/gasolina | G28: 0.6184 | H28: % | I28: Ainda favorável ao etanol
A29: Total serviços | B29: 17782.46 | D29: Histórico real | F29: Consumo etanol | G29: 7.68 | H29: km/L | I29: Referência histórica
F30: Custo projetado etanol | G30: 0.507 | H30: R$/km | I30: Usado no TCO para frente
A49: Leitura para decisão: use R$ 2,304.55/mês como baseline de caixa do Tiida e R$ 2,397.16/mês como baseline econômica. O histórico real dos últimos 12 meses foi R$ 3,012.07/mês. No Comparador_EV, a economia operacional deve ser confrontada com parcela, seguro, impostos, energia, manutenção e depreciação do elétrico.

Sheet Comparador_EV
A1: Comparador EV — compra, financiamento e custo real da troca
A2: Preencha as células amarelas. O número-chave é a PARCELA LÍQUIDA DA TROCA: financiamento + operação do EV − TCO de caixa do Tiida.
A4: 1. COMPRA DO ELÉTRICO | E4: 2. CONDIÇÕES DO FINANCIAMENTO | I4: 3. CUSTO OPERACIONAL DO EV
A5: Modelo / versão do EV | D5: Identificação do cenário | E5: Taxa de juros | F5: 0.017 | G5: % a.m. | H5: Taxa mensal da proposta | I5: Consumo elétrico | J5: 12 | K5: kWh/100 km | L5: Real ou homologado ajustado
A6: Preço do EV | B6: 120000 | C6: R$ | D6: Preço efetivo negociado | E6: Prazo original | F6: 48 | G6: meses | H6: Prazo contratado | I6: Tarifa elétrica | J6: 2 | K6: R$/kWh | L6: Tarifa efetiva de recarga
A7: FIPE atual do Tiida | B7: =Premissas!B11 -> 37044 | C7: R$ | D7: Referência automática | E7: Data da 1ª parcela | F7: 46266 | G7: data | H7: Atualize para cada proposta | I7: Perdas de recarga | J7: 0.1 | K7: % | L7: Wall-to-battery
A8: Valor líquido do Tiida na troca | B8: 40000 | C8: R$ | D8: Edite pelo valor real da proposta | E8: Correção monetária | F8: 0 | G8: % a.m. | H8: Mantida da sua calculadora | I8: Energia anual | J8: =IF(OR(J5="",J6=""),"",Dashboard!D3*J5/100*J6*(1+J7)) -> 5659.632 | K8: R$/ano | L8: Automático
A9: Entrada adicional em dinheiro | C9: R$ | D9: Além do Tiida | E9: Aporte extra padrão | F9: 0 | G9: R$/mês | H9: Amortização extra planejada | I9: Seguro EV | J9: 5600 | K9: R$/ano | L9: Cotação real
A10: Custos incorporados ao financiamento | C10: R$ | D10: Taxas/acessórios financiados | E10: Início do aporte | F10: 2 | G10: mês | H10: 1 = primeira parcela | I10: IPVA EV | J10: 4400 | K10: R$/ano | L10: Use 0 se aplicável
A11: Valor a financiar calculado | B11: =IF(B6="","",MAX(0,B6-B8-B9+B10)) -> 80000 | C11: R$ | D11: Preço - Tiida - entrada + custos | E11: Reinvestir redução da parcela? | F11: Sim | G11: Sim / Não | H11: Mantém o esforço financeiro mais alto | I11: Licenciamento | J11: =Premissas!B14 -> 174.08 | K11: R$/ano | L11: Base atual
A12: Valor financiado manual (opcional) | C12: R$ | D12: Usado enquanto o preço do EV estiver vazio | E12: Estratégia ativa | F12: =IF(B13<=0,"-",IF(AND(F9=0,COUNT(Financiamento_EV!I17:I136)=0),"BASELINE",IF(F11="Sim","POTENCIALIZADA","NORMAL"))) -> BASELINE | H12: Automático | I12: Manutenção EV | J12: 770 | K12: R$/ano | L12: Revisões + pneus + consumíveis
A13: VALOR FINANCIADO USADO | B13: =IF(B11<>"",B11,B12) -> 80000 | C13: R$ | D13: Base efetiva do simulador | E13: Orçamento financeiro após aporte | F13: =IF(Financiamento_EV!F5="","",Financiamento_EV!H5) -> 2451.511 | G13: R$/mês | H13: Parcela inicial + aporte padrão | I13: Depreciação EV | J13: 0.035 | K13: % a.a. | L13: Premissa econômica
I14: Depreciação anual | J14: =IF(OR(B6="",J13=""),"",B6*J13) -> 4200 | K14: R$/ano | L14: Automático
A15: 4. O QUE A TROCA SIGNIFICA NO SEU BOLSO | I15: TCO caixa EV | J15: =IF(COUNT(J8:J12)<5,"",SUM(J8:J12)) -> 16603.712 | K15: R$/ano | L15: Sem financiamento
A16: PAGAMENTO DO FINANCIAMENTO — MÊS 1 | C16: ECONOMIA OPERACIONAL VS TIIDA / MÊS | E16: PARCELA FINAL — CUSTO LÍQUIDO DA TROCA / MÊS 1 | I16: TCO caixa EV | J16: =IF(J15="","",J15/12) -> 1383.6427 | K16: R$/mês | L16: Sem financiamento
A17: =IF(Financiamento_EV!N17=0,"",Financiamento_EV!N17) -> 2451.511 | C17: =IF(J16="","",Dashboard!H12-J16) -> 920.90733 | E17: =IF(OR(A17="",C17=""),"",A17-C17) -> 1530.6036 | I17: TCO econômico EV | J17: =IF(OR(J15="",J14=""),"",(J15+J14)/12) -> 1733.6427 | K17: R$/mês | L17: Caixa + depreciação
A19: MÉDIA LÍQUIDA ATÉ A QUITAÇÃO | C19: DEPOIS DA QUITAÇÃO / MÊS | E19: QUITAÇÃO ESTIMADA
A20: =Fluxo_EV!D4 -> 1530.6036 | C20: =Fluxo_EV!F4 -> -920.90733 | E20: =Financiamento_EV!F7 -> 47696
A22: 5. TRÊS ESTRATÉGIAS DE FINANCIAMENTO
A23: BASELINE — SEM AMORTIZAÇÃO | C23: AMORTIZAÇÃO NORMAL | E23: POTENCIALIZADA
A24: Prazo efetivo | B24: =Cenarios_Fin!B5 -> 48 | C24: Prazo efetivo | D24: =Cenarios_Fin!D5 -> 48 | E24: Prazo efetivo | F24: =Cenarios_Fin!F5 -> 48
A25: Quitação | B25: =Cenarios_Fin!B6 -> 47696 | C25: Quitação | D25: =Cenarios_Fin!D6 -> 47696 | E25: Quitação | F25: =Cenarios_Fin!F6 -> 47696
A26: Juros totais | B26: =Cenarios_Fin!B7 -> 37672.526 | C26: Juros totais | D26: =Cenarios_Fin!D7 -> 37672.526 | E26: Juros totais | F26: =Cenarios_Fin!F7 -> 37672.526
A27: Total pago | B27: =Cenarios_Fin!B8 -> 117672.53 | C27: Total pago | D27: =Cenarios_Fin!D8 -> 117672.53 | E27: Total pago | F27: =Cenarios_Fin!F8 -> 117672.53
A28: Economia de juros | B28: =Cenarios_Fin!B9 -> 0 | C28: Economia de juros | D28: =Cenarios_Fin!D9 -> 0 | E28: Economia de juros | F28: =Cenarios_Fin!F9 -> 8.0035534e-11
A29: Meses antecipados | B29: =Cenarios_Fin!B10 -> 0 | C29: Meses antecipados | D29: =Cenarios_Fin!D10 -> 0 | E29: Meses antecipados | F29: =Cenarios_Fin!F10 -> 0
A31: 6. TCO E LEITURA ECONÔMICA
A32: Métrica | B32: Tiida | C32: EV | D32: Delta EV - Tiida
A33: TCO de caixa / mês | B33: =Dashboard!H12 -> 2304.55 | C33: =IF(J16="","",J16) -> 1383.6427 | D33: =IF(C33="","",C33-B33) -> -920.90733
A34: TCO econômico / mês | B34: =Dashboard!H14 -> 2397.16 | C34: =IF(J17="","",J17) -> 1733.6427 | D34: =IF(C34="","",C34-B34) -> -663.51733
A35: Juros médios / mês no financiamento | B35: 0 | C35: =IF(OR(Financiamento_EV!F8="",Financiamento_EV!F6=0),"",Financiamento_EV!F8/Financiamento_EV!F6) -> 784.84428 | D35: =IF(C35="","",C35) -> 784.84428
A36: Custo econômico EV + juros médios | B36: =Dashboard!H14 -> 2397.16 | C36: =IF(OR(J17="",C35=""),"",J17+C35) -> 2518.487 | D36: =IF(C36="","",C36-B36) -> 121.32695
A37: Total de juros do cenário ativo | B37: 0 | C37: =IF(Financiamento_EV!F8="","",Financiamento_EV!F8) -> 37672.526 | D37: =IF(C37="","",C37) -> 37672.526
A39: Parcela líquida = pagamento do financiamento + custo operacional do EV − TCO mensal do Tiida. Positivo é dinheiro novo por mês; negativo é economia.

Sheet Financiamento_EV
A1: Financiamento EV — amortização detalhada do cenário ativo
A2: Premissas em verde vêm do Comparador_EV. A coluna amarela 'Extra manual' substitui o aporte padrão em meses específicos. O modelo recalcula a parcela para o prazo remanescente após amortizações.
A4: PREMISSAS VINCULADAS | E4: RESUMO DO CENÁRIO ATIVO
A5: Valor financiado | C5: =Comparador_EV!$B$13 -> 80000 | E5: Parcela contratual inicial | F5: =IF($C$5<=0,"",IF($C$6=0,$C$5/$C$7,$C$5*$C$6/(1-(1+$C$6)^(-$C$7)))) -> 2451.511 | G5: Orçamento após aporte | H5: =IF(F5="","",F5+$C$10) -> 2451.511
A6: Taxa de juros a.m. | C6: =Comparador_EV!$F$5 -> 0.017 | E6: Prazo efetivo | F6: =IF($C$5<=0,"",IFERROR(MATCH(0,$O$17:$O$136,0),$C$7)) -> 48 | G6: Meses antecipados | H6: =IF(F6="","",$C$7-F6) -> 0
A7: Prazo original (meses) | C7: =Comparador_EV!F6 -> 48 | E7: Quitação estimada | F7: =IF($C$5<=0,"",IFERROR(INDEX($B$17:$B$136,MATCH(0,$O$17:$O$136,0)),"")) -> 47696 | G7: Economia de juros | H7: =IF(F8="","",Cenarios_Fin!$B$7-F8) -> 8.0035534e-11
A8: Data da 1ª parcela | C8: =Comparador_EV!$F$7 -> 46266 | E8: Juros totais | F8: =IF($C$5<=0,"",SUM($F$17:$F$136)) -> 37672.526 | G8: Economia de juros (%) | H8: =IF(OR(H7="",Cenarios_Fin!$B$7=0),"",H7/Cenarios_Fin!$B$7) -> 2.1245067e-15
A9: Correção monetária a.m. | C9: =Comparador_EV!$F$8 -> 0
A10: Aporte extra padrão | C10: =Comparador_EV!F9 -> 0 | E10: Aporte novo efetivo | F10: =IF($C$5<=0,"",SUM($L$17:$L$136)) -> 0 | G10: Total pago | H10: =IF($C$5<=0,"",SUM($N$17:$N$136)) -> 117672.53
A11: Início do aporte (mês) | C11: =Comparador_EV!$F$10 -> 2 | E11: Reinvestimento | F11: =IF($C$5<=0,"",SUM($M$17:$M$136)) -> 1.2773853e-09 | G11: Parcela contratual final | H11: =IF($C$5<=0,"",IFERROR(INDEX($G$17:$G$136,MATCH(0,$O$17:$O$136,0)),0)) -> 2451.511
A12: Reinvestir redução da parcela? | C12: =Comparador_EV!$F$11 -> Sim | E12: Amortização extra total | F12: =IF($C$5<=0,"",SUM($L$17:$M$136)) -> 1.2773853e-09 | G12: Redução da parcela final | H12: =IF(OR(F5="",H11=""),"",MAX(0,F5-H11)) -> 5.6525096e-10
A14: CRONOGRAMA DO CENÁRIO ATIVO
A15: Mês | B15: Referência | C15: Saldo inicial | D15: Correção | E15: Saldo corrigido | F15: Juros | G15: Parcela contratual | H15: Amortização da parcela | I15: Extra manual | J15: Aporte base | K15: Reinvestimento | L15: Aporte base efetivo | M15: Reinvest. efetivo | N15: Pagamento total | O15: Saldo final | P15: Juros acumulados | Q15: Extras acumulados
A17: =1 -> 1 | B17: =C8 -> 46266 | C17: =C5 -> 80000 | D17: =IF(OR(C17<=0,A17>$C$7),0,C17*$C$9) -> 0 | E17: =MAX(0,C17+D17) -> 80000 | F17: =IF(E17<=0,0,E17*$C$6) -> 1360 | G17: =IF(E17<=0,0,IF($C$6=0,E17/($C$7-A17+1),E17*$C$6/(1-(1+$C$6)^(-($C$7-A17+1))))) -> 2451.511 | H17: =MAX(0,MIN(E17,G17-F17)) -> 1091.511 | J17: =IF(E17<=0,0,IF(ISNUMBER(I17),MAX(0,I17),IF(A17>=$C$11,$C$10,0))) -> 0 | K17: =IF(OR(E17<=0,$C$12<>"Sim",A17<$C$11),0,MAX(0,$F$5-G17)) -> 0 | L17: =IF(E17<=0,0,MIN(J17,MAX(0,E17-H17))) -> 0 | M17: =IF(E17<=0,0,MIN(K17,MAX(0,E17-H17-L17))) -> 0 | N17: =IF(E17<=0,0,G17+L17+M17) -> 2451.511 | O17: =MAX(0,E17-H17-L17-M17) -> 78908.489 | P17: =F17 -> 1360 | Q17: =L17+M17 -> 0
A18: =A17+1 -> 2 | B18: =DATE(YEAR(B17),MONTH(B17)+1,1) -> 46296 | C18: =O17 -> 78908.489 | D18: =IF(OR(C18<=0,A18>$C$7),0,C18*$C$9) -> 0 | E18: =MAX(0,C18+D18) -> 78908.489 | F18: =IF(E18<=0,0,E18*$C$6) -> 1341.4443 | G18: =IF(E18<=0,0,IF($C$6=0,E18/($C$7-A18+1),E18*$C$6/(1-(1+$C$6)^(-($C$7-A18+1))))) -> 2451.511 | H18: =MAX(0,MIN(E18,G18-F18)) -> 1110.0666 | J18: =IF(E18<=0,0,IF(ISNUMBER(I18),MAX(0,I18),IF(A18>=$C$11,$C$10,0))) -> 0 | K18: =IF(OR(E18<=0,$C$12<>"Sim",A18<$C$11),0,MAX(0,$F$5-G18)) -> 0 | L18: =IF(E18<=0,0,MIN(J18,MAX(0,E18-H18))) -> 0 | M18: =IF(E18<=0,0,MIN(K18,MAX(0,E18-H18-L18))) -> 0 | N18: =IF(E18<=0,0,G18+L18+M18) -> 2451.511 | O18: =MAX(0,E18-H18-L18-M18) -> 77798.422 | P18: =P17+F18 -> 2701.4443 | Q18: =Q17+L18+M18 -> 0
A19: =A18+1 -> 3 | B19: =DATE(YEAR(B18),MONTH(B18)+1,1) -> 46327 | C19: =O18 -> 77798.422 | D19: =IF(OR(C19<=0,A19>$C$7),0,C19*$C$9) -> 0 | E19: =MAX(0,C19+D19) -> 77798.422 | F19: =IF(E19<=0,0,E19*$C$6) -> 1322.5732 | G19: =IF(E19<=0,0,IF($C$6=0,E19/($C$7-A19+1),E19*$C$6/(1-(1+$C$6)^(-($C$7-A19+1))))) -> 2451.511 | H19: =MAX(0,MIN(E19,G19-F19)) -> 1128.9378 | J19: =IF(E19<=0,0,IF(ISNUMBER(I19),MAX(0,I19),IF(A19>=$C$11,$C$10,0))) -> 0 | K19: =IF(OR(E19<=0,$C$12<>"Sim",A19<$C$11),0,MAX(0,$F$5-G19)) -> 9.094947e-13 | L19: =IF(E19<=0,0,MIN(J19,MAX(0,E19-H19))) -> 0 | M19: =IF(E19<=0,0,MIN(K19,MAX(0,E19-H19-L19))) -> 9.094947e-13 | N19: =IF(E19<=0,0,G19+L19+M19) -> 2451.511 | O19: =MAX(0,E19-H19-L19-M19) -> 76669.485 | P19: =P18+F19 -> 4024.0175 | Q19: =Q18+L19+M19 -> 9.094947e-13
A20: =A19+1 -> 4 | B20: =DATE(YEAR(B19),MONTH(B19)+1,1) -> 46357 | C20: =O19 -> 76669.485 | D20: =IF(OR(C20<=0,A20>$C$7),0,C20*$C$9) -> 0 | E20: =MAX(0,C20+D20) -> 76669.485 | F20: =IF(E20<=0,0,E20*$C$6) -> 1303.3812 | G20: =IF(E20<=0,0,IF($C$6=0,E20/($C$7-A20+1),E20*$C$6/(1-(1+$C$6)^(-($C$7-A20+1))))) -> 2451.511 | H20: =MAX(0,MIN(E20,G20-F20)) -> 1148.1297 | J20: =IF(E20<=0,0,IF(ISNUMBER(I20),MAX(0,I20),IF(A20>=$C$11,$C$10,0))) -> 0 | K20: =IF(OR(E20<=0,$C$12<>"Sim",A20<$C$11),0,MAX(0,$F$5-G20)) -> 4.5474735e-13 | L20: =IF(E20<=0,0,MIN(J20,MAX(0,E20-H20))) -> 0 | M20: =IF(E20<=0,0,MIN(K20,MAX(0,E20-H20-L20))) -> 4.5474735e-13 | N20: =IF(E20<=0,0,G20+L20+M20) -> 2451.511 | O20: =MAX(0,E20-H20-L20-M20) -> 75521.355 | P20: =P19+F20 -> 5327.3987 | Q20: =Q19+L20+M20 -> 1.3642421e-12
A21: =A20+1 -> 5 | B21: =DATE(YEAR(B20),MONTH(B20)+1,1) -> 46388 | C21: =O20 -> 75521.355 | D21: =IF(OR(C21<=0,A21>$C$7),0,C21*$C$9) -> 0 | E21: =MAX(0,C21+D21) -> 75521.355 | F21: =IF(E21<=0,0,E21*$C$6) -> 1283.863 | G21: =IF(E21<=0,0,IF($C$6=0,E21/($C$7-A21+1),E21*$C$6/(1-(1+$C$6)^(-($C$7-A21+1))))) -> 2451.511 | H21: =MAX(0,MIN(E21,G21-F21)) -> 1167.6479 | J21: =IF(E21<=0,0,IF(ISNUMBER(I21),MAX(0,I21),IF(A21>=$C$11,$C$10,0))) -> 0 | K21: =IF(OR(E21<=0,$C$12<>"Sim",A21<$C$11),0,MAX(0,$F$5-G21)) -> 9.094947e-13 | L21: =IF(E21<=0,0,MIN(J21,MAX(0,E21-H21))) -> 0 | M21: =IF(E21<=0,0,MIN(K21,MAX(0,E21-H21-L21))) -> 9.094947e-13 | N21: =IF(E21<=0,0,G21+L21+M21) -> 2451.511 | O21: =MAX(0,E21-H21-L21-M21) -> 74353.707 | P21: =P20+F21 -> 6611.2618 | Q21: =Q20+L21+M21 -> 2.2737368e-12
A22: =A21+1 -> 6 | B22: =DATE(YEAR(B21),MONTH(B21)+1,1) -> 46419 | C22: =O21 -> 74353.707 | D22: =IF(OR(C22<=0,A22>$C$7),0,C22*$C$9) -> 0 | E22: =MAX(0,C22+D22) -> 74353.707 | F22: =IF(E22<=0,0,E22*$C$6) -> 1264.013 | G22: =IF(E22<=0,0,IF($C$6=0,E22/($C$7-A22+1),E22*$C$6/(1-(1+$C$6)^(-($C$7-A22+1))))) -> 2451.511 | H22: =MAX(0,MIN(E22,G22-F22)) -> 1187.4979 | J22: =IF(E22<=0,0,IF(ISNUMBER(I22),MAX(0,I22),IF(A22>=$C$11,$C$10,0))) -> 0 | K22: =IF(OR(E22<=0,$C$12<>"Sim",A22<$C$11),0,MAX(0,$F$5-G22)) -> 9.094947e-13 | L22: =IF(E22<=0,0,MIN(J22,MAX(0,E22-H22))) -> 0 | M22: =IF(E22<=0,0,MIN(K22,MAX(0,E22-H22-L22))) -> 9.094947e-13 | N22: =IF(E22<=0,0,G22+L22+M22) -> 2451.511 | O22: =MAX(0,E22-H22-L22-M22) -> 73166.209 | P22: =P21+F22 -> 7875.2748 | Q22: =Q21+L22+M22 -> 3.1832315e-12
A23: =A22+1 -> 7 | B23: =DATE(YEAR(B22),MONTH(B22)+1,1) -> 46447 | C23: =O22 -> 73166.209 | D23: =IF(OR(C23<=0,A23>$C$7),0,C23*$C$9) -> 0 | E23: =MAX(0,C23+D23) -> 73166.209 | F23: =IF(E23<=0,0,E23*$C$6) -> 1243.8256 | G23: =IF(E23<=0,0,IF($C$6=0,E23/($C$7-A23+1),E23*$C$6/(1-(1+$C$6)^(-($C$7-A23+1))))) -> 2451.511 | H23: =MAX(0,MIN(E23,G23-F23)) -> 1207.6854 | J23: =IF(E23<=0,0,IF(ISNUMBER(I23),MAX(0,I23),IF(A23>=$C$11,$C$10,0))) -> 0 | K23: =IF(OR(E23<=0,$C$12<>"Sim",A23<$C$11),0,MAX(0,$F$5-G23)) -> 9.094947e-13 | L23: =IF(E23<=0,0,MIN(J23,MAX(0,E23-H23))) -> 0 | M23: =IF(E23<=0,0,MIN(K23,MAX(0,E23-H23-L23))) -> 9.094947e-13 | N23: =IF(E23<=0,0,G23+L23+M23) -> 2451.511 | O23: =MAX(0,E23-H23-L23-M23) -> 71958.524 | P23: =P22+F23 -> 9119.1003 | Q23: =Q22+L23+M23 -> 4.0927262e-12
A24: =A23+1 -> 8 | B24: =DATE(YEAR(B23),MONTH(B23)+1,1) -> 46478 | C24: =O23 -> 71958.524 | D24: =IF(OR(C24<=0,A24>$C$7),0,C24*$C$9) -> 0 | E24: =MAX(0,C24+D24) -> 71958.524 | F24: =IF(E24<=0,0,E24*$C$6) -> 1223.2949 | G24: =IF(E24<=0,0,IF($C$6=0,E24/($C$7-A24+1),E24*$C$6/(1-(1+$C$6)^(-($C$7-A24+1))))) -> 2451.511 | H24: =MAX(0,MIN(E24,G24-F24)) -> 1228.216 | J24: =IF(E24<=0,0,IF(ISNUMBER(I24),MAX(0,I24),IF(A24>=$C$11,$C$10,0))) -> 0 | K24: =IF(OR(E24<=0,$C$12<>"Sim",A24<$C$11),0,MAX(0,$F$5-G24)) -> 9.094947e-13 | L24: =IF(E24<=0,0,MIN(J24,MAX(0,E24-H24))) -> 0 | M24: =IF(E24<=0,0,MIN(K24,MAX(0,E24-H24-L24))) -> 9.094947e-13 | N24: =IF(E24<=0,0,G24+L24+M24) -> 2451.511 | O24: =MAX(0,E24-H24-L24-M24) -> 70730.308 | P24: =P23+F24 -> 10342.395 | Q24: =Q23+L24+M24 -> 5.0022209e-12
A25: =A24+1 -> 9 | B25: =DATE(YEAR(B24),MONTH(B24)+1,1) -> 46508 | C25: =O24 -> 70730.308 | D25: =IF(OR(C25<=0,A25>$C$7),0,C25*$C$9) -> 0 | E25: =MAX(0,C25+D25) -> 70730.308 | F25: =IF(E25<=0,0,E25*$C$6) -> 1202.4152 | G25: =IF(E25<=0,0,IF($C$6=0,E25/($C$7-A25+1),E25*$C$6/(1-(1+$C$6)^(-($C$7-A25+1))))) -> 2451.511 | H25: =MAX(0,MIN(E25,G25-F25)) -> 1249.0957 | J25: =IF(E25<=0,0,IF(ISNUMBER(I25),MAX(0,I25),IF(A25>=$C$11,$C$10,0))) -> 0 | K25: =IF(OR(E25<=0,$C$12<>"Sim",A25<$C$11),0,MAX(0,$F$5-G25)) -> 1.3642421e-12 | L25: =IF(E25<=0,0,MIN(J25,MAX(0,E25-H25))) -> 0 | M25: =IF(E25<=0,0,MIN(K25,MAX(0,E25-H25-L25))) -> 1.3642421e-12 | N25: =IF(E25<=0,0,G25+L25+M25) -> 2451.511 | O25: =MAX(0,E25-H25-L25-M25) -> 69481.212 | P25: =P24+F25 -> 11544.81 | Q25: =Q24+L25+M25 -> 6.3664629e-12
A26: =A25+1 -> 10 | B26: =DATE(YEAR(B25),MONTH(B25)+1,1) -> 46539 | C26: =O25 -> 69481.212 | D26: =IF(OR(C26<=0,A26>$C$7),0,C26*$C$9) -> 0 | E26: =MAX(0,C26+D26) -> 69481.212 | F26: =IF(E26<=0,0,E26*$C$6) -> 1181.1806 | G26: =IF(E26<=0,0,IF($C$6=0,E26/($C$7-A26+1),E26*$C$6/(1-(1+$C$6)^(-($C$7-A26+1))))) -> 2451.511 | H26: =MAX(0,MIN(E26,G26-F26)) -> 1270.3303 | J26: =IF(E26<=0,0,IF(ISNUMBER(I26),MAX(0,I26),IF(A26>=$C$11,$C$10,0))) -> 0 | K26: =IF(OR(E26<=0,$C$12<>"Sim",A26<$C$11),0,MAX(0,$F$5-G26)) -> 1.3642421e-12 | L26: =IF(E26<=0,0,MIN(J26,MAX(0,E26-H26))) -> 0 | M26: =IF(E26<=0,0,MIN(K26,MAX(0,E26-H26-L26))) -> 1.3642421e-12 | N26: =IF(E26<=0,0,G26+L26+M26) -> 2451.511 | O26: =MAX(0,E26-H26-L26-M26) -> 68210.882 | P26: =P25+F26 -> 12725.991 | Q26: =Q25+L26+M26 -> 7.730705e-12
A27: =A26+1 -> 11 | B27: =DATE(YEAR(B26),MONTH(B26)+1,1) -> 46569 | C27: =O26 -> 68210.882 | D27: =IF(OR(C27<=0,A27>$C$7),0,C27*$C$9) -> 0 | E27: =MAX(0,C27+D27) -> 68210.882 | F27: =IF(E27<=0,0,E27*$C$6) -> 1159.585 | G27: =IF(E27<=0,0,IF($C$6=0,E27/($C$7-A27+1),E27*$C$6/(1-(1+$C$6)^(-($C$7-A27+1))))) -> 2451.511 | H27: =MAX(0,MIN(E27,G27-F27)) -> 1291.926 | J27: =IF(E27<=0,0,IF(ISNUMBER(I27),MAX(0,I27),IF(A27>=$C$11,$C$10,0))) -> 0 | K27: =IF(OR(E27<=0,$C$12<>"Sim",A27<$C$11),0,MAX(0,$F$5-G27)) -> 2.2737368e-12 | L27: =IF(E27<=0,0,MIN(J27,MAX(0,E27-H27))) -> 0 | M27: =IF(E27<=0,0,MIN(K27,MAX(0,E27-H27-L27))) -> 2.2737368e-12 | N27: =IF(E27<=0,0,G27+L27+M27) -> 2451.511 | O27: =MAX(0,E27-H27-L27-M27) -> 66918.956 | P27: =P26+F27 -> 13885.576 | Q27: =Q26+L27+M27 -> 1.0004442e-11
A28: =A27+1 -> 12 | B28: =DATE(YEAR(B27),MONTH(B27)+1,1) -> 46600 | C28: =O27 -> 66918.956 | D28: =IF(OR(C28<=0,A28>$C$7),0,C28*$C$9) -> 0 | E28: =MAX(0,C28+D28) -> 66918.956 | F28: =IF(E28<=0,0,E28*$C$6) -> 1137.6222 | G28: =IF(E28<=0,0,IF($C$6=0,E28/($C$7-A28+1),E28*$C$6/(1-(1+$C$6)^(-($C$7-A28+1))))) -> 2451.511 | H28: =MAX(0,MIN(E28,G28-F28)) -> 1313.8887 | J28: =IF(E28<=0,0,IF(ISNUMBER(I28),MAX(0,I28),IF(A28>=$C$11,$C$10,0))) -> 0 | K28: =IF(OR(E28<=0,$C$12<>"Sim",A28<$C$11),0,MAX(0,$F$5-G28)) -> 1.8189894e-12 | L28: =IF(E28<=0,0,MIN(J28,MAX(0,E28-H28))) -> 0 | M28: =IF(E28<=0,0,MIN(K28,MAX(0,E28-H28-L28))) -> 1.8189894e-12 | N28: =IF(E28<=0,0,G28+L28+M28) -> 2451.511 | O28: =MAX(0,E28-H28-L28-M28) -> 65605.067 | P28: =P27+F28 -> 15023.198 | Q28: =Q27+L28+M28 -> 1.1823431e-11
A29: =A28+1 -> 13 | B29: =DATE(YEAR(B28),MONTH(B28)+1,1) -> 46631 | C29: =O28 -> 65605.067 | D29: =IF(OR(C29<=0,A29>$C$7),0,C29*$C$9) -> 0 | E29: =MAX(0,C29+D29) -> 65605.067 | F29: =IF(E29<=0,0,E29*$C$6) -> 1115.2861 | G29: =IF(E29<=0,0,IF($C$6=0,E29/($C$7-A29+1),E29*$C$6/(1-(1+$C$6)^(-($C$7-A29+1))))) -> 2451.511 | H29: =MAX(0,MIN(E29,G29-F29)) -> 1336.2248 | J29: =IF(E29<=0,0,IF(ISNUMBER(I29),MAX(0,I29),IF(A29>=$C$11,$C$10,0))) -> 0 | K29: =IF(OR(E29<=0,$C$12<>"Sim",A29<$C$11),0,MAX(0,$F$5-G29)) -> 2.7284841e-12 | L29: =IF(E29<=0,0,MIN(J29,MAX(0,E29-H29))) -> 0 | M29: =IF(E29<=0,0,MIN(K29,MAX(0,E29-H29-L29))) -> 2.7284841e-12 | N29: =IF(E29<=0,0,G29+L29+M29) -> 2451.511 | O29: =MAX(0,E29-H29-L29-M29) -> 64268.842 | P29: =P28+F29 -> 16138.484 | Q29: =Q28+L29+M29 -> 1.4551915e-11
... A136: =A135+1 -> 120 | B136: =DATE(YEAR(B135),MONTH(B135)+1,1) -> 49888 | C136: =O135 -> 0 | D136: =IF(OR(C136<=0,A136>$C$7),0,C136*$C$9) -> 0 | E136: =MAX(0,C136+D136) -> 0 | F136: =IF(E136<=0,0,E136*$C$6) -> 0 | G136: =IF(E136<=0,0,IF($C$6=0,E136/($C$7-A136+1),E136*$C$6/(1-(1+$C$6)^(-($C$7-A136+1))))) -> 0 | H136: =MAX(0,MIN(E136,G136-F136)) -> 0 | J136: =IF(E136<=0,0,IF(ISNUMBER(I136),MAX(0,I136),IF(A136>=$C$11,$C$10,0))) -> 0 | K136: =IF(OR(E136<=0,$C$12<>"Sim",A136<$C$11),0,MAX(0,$F$5-G136)) -> 0 | L136: =IF(E136<=0,0,MIN(J136,MAX(0,E136-H136))) -> 0 | M136: =IF(E136<=0,0,MIN(K136,MAX(0,E136-H136-L136))) -> 0 | N136: =IF(E136<=0,0,G136+L136+M136) -> 0 | O136: =MAX(0,E136-H136-L136-M136) -> 0 | P136: =P135+F136 -> 37672.526 | Q136: =Q135+L136+M136 -> 1.2773853e-09

Sheet Cenarios_Fin
A1: Financiamento — comparação de estratégias de amortização
A2: Baseline = sem amortização. Normal = aporte fixo. Potencializada = aporte fixo + reinvestimento da redução da parcela.
A4: BASELINE — SEM AMORTIZAÇÃO | C4: AMORTIZAÇÃO NORMAL | E4: POTENCIALIZADA
A5: Prazo efetivo | B5: =IF(Financiamento_EV!$C$5<=0,"",IFERROR(MATCH(0,$H$35:$H$154,0),Financiamento_EV!$C$7)) -> 48 | C5: Prazo efetivo | D5: =IF(Financiamento_EV!$C$5<=0,"",IFERROR(MATCH(0,$S$35:$S$154,0),Financiamento_EV!$C$7)) -> 48 | E5: Prazo efetivo | F5: =IF(Financiamento_EV!$C$5<=0,"",IFERROR(MATCH(0,$AF$35:$AF$154,0),Financiamento_EV!$C$7)) -> 48
A6: Quitação | B6: =IF(B5="","",DATE(YEAR(Financiamento_EV!$C$8),MONTH(Financiamento_EV!$C$8)+B5-1,1)) -> 47696 | C6: Quitação | D6: =IF(D5="","",DATE(YEAR(Financiamento_EV!$C$8),MONTH(Financiamento_EV!$C$8)+D5-1,1)) -> 47696 | E6: Quitação | F6: =IF(F5="","",DATE(YEAR(Financiamento_EV!$C$8),MONTH(Financiamento_EV!$C$8)+F5-1,1)) -> 47696
A7: Juros totais | B7: =IF(B5="","",SUM($E$35:$E$154)) -> 37672.526 | C7: Juros totais | D7: =IF(D5="","",SUM($O$35:$O$154)) -> 37672.526 | E7: Juros totais | F7: =IF(F5="","",SUM($Z$35:$Z$154)) -> 37672.526
A8: Total pago | B8: =IF(B5="","",SUM($I$35:$I$154)) -> 117672.53 | C8: Total pago | D8: =IF(D5="","",SUM($T$35:$T$154)) -> 117672.53 | E8: Total pago | F8: =IF(F5="","",SUM($AE$35:$AE$154)) -> 117672.53
A9: Economia de juros | B9: 0 | C9: Economia de juros | D9: =IF(D7="","",$B$7-D7) -> 0 | E9: Economia de juros | F9: =IF(F7="","",$B$7-F7) -> 8.0035534e-11
A10: Meses antecipados | B10: 0 | C10: Meses antecipados | D10: =IF(D5="","",Financiamento_EV!$C$7-D5) -> 0 | E10: Meses antecipados | F10: =IF(F5="","",Financiamento_EV!$C$7-F5) -> 0
A11: Extra total | B11: 0 | C11: Extra total | D11: =IF(D5="","",SUM($R$35:$R$154)) -> 0 | E11: Extra total | F11: =IF(F5="","",SUM($AG$35:$AG$154)) -> 1.2773853e-09
A34: Mês | B34: Saldo inicial | C34: Correção | D34: Saldo corrigido | E34: Juros | F34: Parcela | G34: Amort. | H34: Saldo final | I34: Pagamento | K34: Mês | L34: Saldo inicial | M34: Correção | N34: Saldo corrigido | O34: Juros | P34: Parcela | Q34: Amort. | R34: Aporte | S34: Saldo final | T34: Pagamento | V34: Mês | W34: Saldo inicial | X34: Correção | Y34: Saldo corrigido | Z34: Juros | AA34: Parcela | AB34: Amort. | AC34: Aporte | AD34: Reinvest. | AE34: Pagamento | AF34: Saldo final | AG34: Extra total | AI34: Mês | AJ34: Baseline | AK34: Normal | AL34: Potencializada | AM34: Mês | AN34: Baseline | AO34: Normal | AP34: Potencializada
A35: =1 -> 1 | B35: =Financiamento_EV!$C$5 -> 80000 | C35: =IF(OR(B35<=0,A35>Financiamento_EV!$C$7),0,B35*Financiamento_EV!$C$9) -> 0 | D35: =MAX(0,B35+C35) -> 80000 | E35: =IF(D35<=0,0,D35*Financiamento_EV!$C$6) -> 1360 | F35: =IF(D35<=0,0,IF(Financiamento_EV!$C$6=0,D35/(Financiamento_EV!$C$7-A35+1),D35*Financiamento_EV!$C$6/(1-(1+Financiamento_EV!$C$6)^(-(Financiamento_EV!$C$7-A35+1))))) -> 2451.511 | G35: =MAX(0,MIN(D35,F35-E35)) -> 1091.511 | H35: =MAX(0,D35-G35) -> 78908.489 | I35: =IF(D35<=0,0,F35) -> 2451.511 | K35: =1 -> 1 | L35: =Financiamento_EV!$C$5 -> 80000 | M35: =IF(OR(L35<=0,K35>Financiamento_EV!$C$7),0,L35*Financiamento_EV!$C$9) -> 0 | N35: =MAX(0,L35+M35) -> 80000 | O35: =IF(N35<=0,0,N35*Financiamento_EV!$C$6) -> 1360 | P35: =IF(N35<=0,0,IF(Financiamento_EV!$C$6=0,N35/(Financiamento_EV!$C$7-K35+1),N35*Financiamento_EV!$C$6/(1-(1+Financiamento_EV!$C$6)^(-(Financiamento_EV!$C$7-K35+1))))) -> 2451.511 | Q35: =MAX(0,MIN(N35,P35-O35)) -> 1091.511 | R35: =IF(N35<=0,0,MIN(IF(ISNUMBER(INDEX(Financiamento_EV!$I$17:$I$136,K35)),MAX(0,INDEX(Financiamento_EV!$I$17:$I$136,K35)),IF(K35>=Financiamento_EV!$C$11,Financiamento_EV!$C$10,0)),MAX(0,N35-Q35))) -> 0 | S35: =MAX(0,N35-Q35-R35) -> 78908.489 | T35: =IF(N35<=0,0,P35+R35) -> 2451.511 | V35: =1 -> 1 | W35: =Financiamento_EV!$C$5 -> 80000 | X35: =IF(OR(W35<=0,V35>Financiamento_EV!$C$7),0,W35*Financiamento_EV!$C$9) -> 0 | Y35: =MAX(0,W35+X35) -> 80000 | Z35: =IF(Y35<=0,0,Y35*Financiamento_EV!$C$6) -> 1360 | AA35: =IF(Y35<=0,0,IF(Financiamento_EV!$C$6=0,Y35/(Financiamento_EV!$C$7-V35+1),Y35*Financiamento_EV!$C$6/(1-(1+Financiamento_EV!$C$6)^(-(Financiamento_EV!$C$7-V35+1))))) -> 2451.511 | AB35: =MAX(0,MIN(Y35,AA35-Z35)) -> 1091.511 | AC35: =IF(Y35<=0,0,MIN(IF(ISNUMBER(INDEX(Financiamento_EV!$I$17:$I$136,V35)),MAX(0,INDEX(Financiamento_EV!$I$17:$I$136,V35)),IF(V35>=Financiamento_EV!$C$11,Financiamento_EV!$C$10,0)),MAX(0,Y35-AB35))) -> 0 | AD35: =IF(OR(Y35<=0,V35<Financiamento_EV!$C$11),0,MIN(MAX(0,Financiamento_EV!$F$5-AA35),MAX(0,Y35-AB35-AC35))) -> 0 | AE35: =IF(Y35<=0,0,AA35+AC35+AD35) -> 2451.511 | AF35: =MAX(0,Y35-AB35-AC35-AD35) -> 78908.489 | AG35: =AC35+AD35 -> 0 | AI35: =A35 -> 1 | AJ35: =H35 -> 78908.489 | AK35: =S35 -> 78908.489 | AL35: =AF35 -> 78908.489 | AM35: =A35 -> 1 | AN35: =I35 -> 2451.511 | AO35: =T35 -> 2451.511 | AP35: =AE35 -> 2451.511
A36: =A35+1 -> 2 | B36: =H35 -> 78908.489 | C36: =IF(OR(B36<=0,A36>Financiamento_EV!$C$7),0,B36*Financiamento_EV!$C$9) -> 0 | D36: =MAX(0,B36+C36) -> 78908.489 | E36: =IF(D36<=0,0,D36*Financiamento_EV!$C$6) -> 1341.4443 | F36: =IF(D36<=0,0,IF(Financiamento_EV!$C$6=0,D36/(Financiamento_EV!$C$7-A36+1),D36*Financiamento_EV!$C$6/(1-(1+Financiamento_EV!$C$6)^(-(Financiamento_EV!$C$7-A36+1))))) -> 2451.511 | G36: =MAX(0,MIN(D36,F36-E36)) -> 1110.0666 | H36: =MAX(0,D36-G36) -> 77798.422 | I36: =IF(D36<=0,0,F36) -> 2451.511 | K36: =K35+1 -> 2 | L36: =S35 -> 78908.489 | M36: =IF(OR(L36<=0,K36>Financiamento_EV!$C$7),0,L36*Financiamento_EV!$C$9) -> 0 | N36: =MAX(0,L36+M36) -> 78908.489 | O36: =IF(N36<=0,0,N36*Financiamento_EV!$C$6) -> 1341.4443 | P36: =IF(N36<=0,0,IF(Financiamento_EV!$C$6=0,N36/(Financiamento_EV!$C$7-K36+1),N36*Financiamento_EV!$C$6/(1-(1+Financiamento_EV!$C$6)^(-(Financiamento_EV!$C$7-K36+1))))) -> 2451.511 | Q36: =MAX(0,MIN(N36,P36-O36)) -> 1110.0666 | R36: =IF(N36<=0,0,MIN(IF(ISNUMBER(INDEX(Financiamento_EV!$I$17:$I$136,K36)),MAX(0,INDEX(Financiamento_EV!$I$17:$I$136,K36)),IF(K36>=Financiamento_EV!$C$11,Financiamento_EV!$C$10,0)),MAX(0,N36-Q36))) -> 0 | S36: =MAX(0,N36-Q36-R36) -> 77798.422 | T36: =IF(N36<=0,0,P36+R36) -> 2451.511 | V36: =V35+1 -> 2 | W36: =AF35 -> 78908.489 | X36: =IF(OR(W36<=0,V36>Financiamento_EV!$C$7),0,W36*Financiamento_EV!$C$9) -> 0 | Y36: =MAX(0,W36+X36) -> 78908.489 | Z36: =IF(Y36<=0,0,Y36*Financiamento_EV!$C$6) -> 1341.4443 | AA36: =IF(Y36<=0,0,IF(Financiamento_EV!$C$6=0,Y36/(Financiamento_EV!$C$7-V36+1),Y36*Financiamento_EV!$C$6/(1-(1+Financiamento_EV!$C$6)^(-(Financiamento_EV!$C$7-V36+1))))) -> 2451.511 | AB36: =MAX(0,MIN(Y36,AA36-Z36)) -> 1110.0666 | AC36: =IF(Y36<=0,0,MIN(IF(ISNUMBER(INDEX(Financiamento_EV!$I$17:$I$136,V36)),MAX(0,INDEX(Financiamento_EV!$I$17:$I$136,V36)),IF(V36>=Financiamento_EV!$C$11,Financiamento_EV!$C$10,0)),MAX(0,Y36-AB36))) -> 0 | AD36: =IF(OR(Y36<=0,V36<Financiamento_EV!$C$11),0,MIN(MAX(0,Financiamento_EV!$F$5-AA36),MAX(0,Y36-AB36-AC36))) -> 0 | AE36: =IF(Y36<=0,0,AA36+AC36+AD36) -> 2451.511 | AF36: =MAX(0,Y36-AB36-AC36-AD36) -> 77798.422 | AG36: =AC36+AD36 -> 0 | AI36: =A36 -> 2 | AJ36: =H36 -> 77798.422 | AK36: =S36 -> 77798.422 | AL36: =AF36 -> 77798.422 | AM36: =A36 -> 2 | AN36: =I36 -> 2451.511 | AO36: =T36 -> 2451.511 | AP36: =AE36 -> 2451.511
A37: =A36+1 -> 3 | B37: =H36 -> 77798.422 | C37: =IF(OR(B37<=0,A37>Financiamento_EV!$C$7),0,B37*Financiamento_EV!$C$9) -> 0 | D37: =MAX(0,B37+C37) -> 77798.422 | E37: =IF(D37<=0,0,D37*Financiamento_EV!$C$6) -> 1322.5732 | F37: =IF(D37<=0,0,IF(Financiamento_EV!$C$6=0,D37/(Financiamento_EV!$C$7-A37+1),D37*Financiamento_EV!$C$6/(1-(1+Financiamento_EV!$C$6)^(-(Financiamento_EV!$C$7-A37+1))))) -> 2451.511 | G37: =MAX(0,MIN(D37,F37-E37)) -> 1128.9378 | H37: =MAX(0,D37-G37) -> 76669.485 | I37: =IF(D37<=0,0,F37) -> 2451.511 | K37: =K36+1 -> 3 | L37: =S36 -> 77798.422 | M37: =IF(OR(L37<=0,K37>Financiamento_EV!$C$7),0,L37*Financiamento_EV!$C$9) -> 0 | N37: =MAX(0,L37+M37) -> 77798.422 | O37: =IF(N37<=0,0,N37*Financiamento_EV!$C$6) -> 1322.5732 | P37: =IF(N37<=0,0,IF(Financiamento_EV!$C$6=0,N37/(Financiamento_EV!$C$7-K37+1),N37*Financiamento_EV!$C$6/(1-(1+Financiamento_EV!$C$6)^(-(Financiamento_EV!$C$7-K37+1))))) -> 2451.511 | Q37: =MAX(0,MIN(N37,P37-O37)) -> 1128.9378 | R37: =IF(N37<=0,0,MIN(IF(ISNUMBER(INDEX(Financiamento_EV!$I$17:$I$136,K37)),MAX(0,INDEX(Financiamento_EV!$I$17:$I$136,K37)),IF(K37>=Financiamento_EV!$C$11,Financiamento_EV!$C$10,0)),MAX(0,N37-Q37))) -> 0 | S37: =MAX(0,N37-Q37-R37) -> 76669.485 | T37: =IF(N37<=0,0,P37+R37) -> 2451.511 | V37: =V36+1 -> 3 | W37: =AF36 -> 77798.422 | X37: =IF(OR(W37<=0,V37>Financiamento_EV!$C$7),0,W37*Financiamento_EV!$C$9) -> 0 | Y37: =MAX(0,W37+X37) -> 77798.422 | Z37: =IF(Y37<=0,0,Y37*Financiamento_EV!$C$6) -> 1322.5732 | AA37: =IF(Y37<=0,0,IF(Financiamento_EV!$C$6=0,Y37/(Financiamento_EV!$C$7-V37+1),Y37*Financiamento_EV!$C$6/(1-(1+Financiamento_EV!$C$6)^(-(Financiamento_EV!$C$7-V37+1))))) -> 2451.511 | AB37: =MAX(0,MIN(Y37,AA37-Z37)) -> 1128.9378 | AC37: =IF(Y37<=0,0,MIN(IF(ISNUMBER(INDEX(Financiamento_EV!$I$17:$I$136,V37)),MAX(0,INDEX(Financiamento_EV!$I$17:$I$136,V37)),IF(V37>=Financiamento_EV!$C$11,Financiamento_EV!$C$10,0)),MAX(0,Y37-AB37))) -> 0 | AD37: =IF(OR(Y37<=0,V37<Financiamento_EV!$C$11),0,MIN(MAX(0,Financiamento_EV!$F$5-AA37),MAX(0,Y37-AB37-AC37))) -> 9.094947e-13 | AE37: =IF(Y37<=0,0,AA37+AC37+AD37) -> 2451.511 | AF37: =MAX(0,Y37-AB37-AC37-AD37) -> 76669.485 | AG37: =AC37+AD37 -> 9.094947e-13 | AI37: =A37 -> 3 | AJ37: =H37 -> 76669.485 | AK37: =S37 -> 76669.485 | AL37: =AF37 -> 76669.485 | AM37: =A37 -> 3 | AN37: =I37 -> 2451.511 | AO37: =T37 -> 2451.511 | AP37: =AE37 -> 2451.511
A38: =A37+1 -> 4 | B38: =H37 -> 76669.485 | C38: =IF(OR(B38<=0,A38>Financiamento_EV!$C$7),0,B38*Financiamento_EV!$C$9) -> 0 | D38: =MAX(0,B38+C38) -> 76669.485 | E38: =IF(D38<=0,0,D38*Financiamento_EV!$C$6) -> 1303.3812 | F38: =IF(D38<=0,0,IF(Financiamento_EV!$C$6=0,D38/(Financiamento_EV!$C$7-A38+1),D38*Financiamento_EV!$C$6/(1-(1+Financiamento_EV!$C$6)^(-(Financiamento_EV!$C$7-A38+1))))) -> 2451.511 | G38: =MAX(0,MIN(D38,F38-E38)) -> 1148.1297 | H38: =MAX(0,D38-G38) -> 75521.355 | I38: =IF(D38<=0,0,F38) -> 2451.511 | K38: =K37+1 -> 4 | L38: =S37 -> 76669.485 | M38: =IF(OR(L38<=0,K38>Financiamento_EV!$C$7),0,L38*Financiamento_EV!$C$9) -> 0 | N38: =MAX(0,L38+M38) -> 76669.485 | O38: =IF(N38<=0,0,N38*Financiamento_EV!$C$6) -> 1303.3812 | P38: =IF(N38<=0,0,IF(Financiamento_EV!$C$6=0,N38/(Financiamento_EV!$C$7-K38+1),N38*Financiamento_EV!$C$6/(1-(1+Financiamento_EV!$C$6)^(-(Financiamento_EV!$C$7-K38+1))))) -> 2451.511 | Q38: =MAX(0,MIN(N38,P38-O38)) -> 1148.1297 | R38: =IF(N38<=0,0,MIN(IF(ISNUMBER(INDEX(Financiamento_EV!$I$17:$I$136,K38)),MAX(0,INDEX(Financiamento_EV!$I$17:$I$136,K38)),IF(K38>=Financiamento_EV!$C$11,Financiamento_EV!$C$10,0)),MAX(0,N38-Q38))) -> 0 | S38: =MAX(0,N38-Q38-R38) -> 75521.355 | T38: =IF(N38<=0,0,P38+R38) -> 2451.511 | V38: =V37+1 -> 4 | W38: =AF37 -> 76669.485 | X38: =IF(OR(W38<=0,V38>Financiamento_EV!$C$7),0,W38*Financiamento_EV!$C$9) -> 0 | Y38: =MAX(0,W38+X38) -> 76669.485 | Z38: =IF(Y38<=0,0,Y38*Financiamento_EV!$C$6) -> 1303.3812 | AA38: =IF(Y38<=0,0,IF(Financiamento_EV!$C$6=0,Y38/(Financiamento_EV!$C$7-V38+1),Y38*Financiamento_EV!$C$6/(1-(1+Financiamento_EV!$C$6)^(-(Financiamento_EV!$C$7-V38+1))))) -> 2451.511 | AB38: =MAX(0,MIN(Y38,AA38-Z38)) -> 1148.1297 | AC38: =IF(Y38<=0,0,MIN(IF(ISNUMBER(INDEX(Financiamento_EV!$I$17:$I$136,V38)),MAX(0,INDEX(Financiamento_EV!$I$17:$I$136,V38)),IF(V38>=Financiamento_EV!$C$11,Financiamento_EV!$C$10,0)),MAX(0,Y38-AB38))) -> 0 | AD38: =IF(OR(Y38<=0,V38<Financiamento_EV!$C$11),0,MIN(MAX(0,Financiamento_EV!$F$5-AA38),MAX(0,Y38-AB38-AC38))) -> 4.5474735e-13 | AE38: =IF(Y38<=0,0,AA38+AC38+AD38) -> 2451.511 | AF38: =MAX(0,Y38-AB38-AC38-AD38) -> 75521.355 | AG38: =AC38+AD38 -> 4.5474735e-13 | AI38: =A38 -> 4 | AJ38: =H38 -> 75521.355 | AK38: =S38 -> 75521.355 | AL38: =AF38 -> 75521.355 | AM38: =A38 -> 4 | AN38: =I38 -> 2451.511 | AO38: =T38 -> 2451.511 | AP38: =AE38 -> 2451.511
A39: =A38+1 -> 5 | B39: =H38 -> 75521.355 | C39: =IF(OR(B39<=0,A39>Financiamento_EV!$C$7),0,B39*Financiamento_EV!$C$9) -> 0 | D39: =MAX(0,B39+C39) -> 75521.355 | E39: =IF(D39<=0,0,D39*Financiamento_EV!$C$6) -> 1283.863 | F39: =IF(D39<=0,0,IF(Financiamento_EV!$C$6=0,D39/(Financiamento_EV!$C$7-A39+1),D39*Financiamento_EV!$C$6/(1-(1+Financiamento_EV!$C$6)^(-(Financiamento_EV!$C$7-A39+1))))) -> 2451.511 | G39: =MAX(0,MIN(D39,F39-E39)) -> 1167.6479 | H39: =MAX(0,D39-G39) -> 74353.707 | I39: =IF(D39<=0,0,F39) -> 2451.511 | K39: =K38+1 -> 5 | L39: =S38 -> 75521.355 | M39: =IF(OR(L39<=0,K39>Financiamento_EV!$C$7),0,L39*Financiamento_EV!$C$9) -> 0 | N39: =MAX(0,L39+M39) -> 75521.355 | O39: =IF(N39<=0,0,N39*Financiamento_EV!$C$6) -> 1283.863 | P39: =IF(N39<=0,0,IF(Financiamento_EV!$C$6=0,N39/(Financiamento_EV!$C$7-K39+1),N39*Financiamento_EV!$C$6/(1-(1+Financiamento_EV!$C$6)^(-(Financiamento_EV!$C$7-K39+1))))) -> 2451.511 | Q39: =MAX(0,MIN(N39,P39-O39)) -> 1167.6479 | R39: =IF(N39<=0,0,MIN(IF(ISNUMBER(INDEX(Financiamento_EV!$I$17:$I$136,K39)),MAX(0,INDEX(Financiamento_EV!$I$17:$I$136,K39)),IF(K39>=Financiamento_EV!$C$11,Financiamento_EV!$C$10,0)),MAX(0,N39-Q39))) -> 0 | S39: =MAX(0,N39-Q39-R39) -> 74353.707 | T39: =IF(N39<=0,0,P39+R39) -> 2451.511 | V39: =V38+1 -> 5 | W39: =AF38 -> 75521.355 | X39: =IF(OR(W39<=0,V39>Financiamento_EV!$C$7),0,W39*Financiamento_EV!$C$9) -> 0 | Y39: =MAX(0,W39+X39) -> 75521.355 | Z39: =IF(Y39<=0,0,Y39*Financiamento_EV!$C$6) -> 1283.863 | AA39: =IF(Y39<=0,0,IF(Financiamento_EV!$C$6=0,Y39/(Financiamento_EV!$C$7-V39+1),Y39*Financiamento_EV!$C$6/(1-(1+Financiamento_EV!$C$6)^(-(Financiamento_EV!$C$7-V39+1))))) -> 2451.511 | AB39: =MAX(0,MIN(Y39,AA39-Z39)) -> 1167.6479 | AC39: =IF(Y39<=0,0,MIN(IF(ISNUMBER(INDEX(Financiamento_EV!$I$17:$I$136,V39)),MAX(0,INDEX(Financiamento_EV!$I$17:$I$136,V39)),IF(V39>=Financiamento_EV!$C$11,Financiamento_EV!$C$10,0)),MAX(0,Y39-AB39))) -> 0 | AD39: =IF(OR(Y39<=0,V39<Financiamento_EV!$C$11),0,MIN(MAX(0,Financiamento_EV!$F$5-AA39),MAX(0,Y39-AB39-AC39))) -> 9.094947e-13 | AE39: =IF(Y39<=0,0,AA39+AC39+AD39) -> 2451.511 | AF39: =MAX(0,Y39-AB39-AC39-AD39) -> 74353.707 | AG39: =AC39+AD39 -> 9.094947e-13 | AI39: =A39 -> 5 | AJ39: =H39 -> 74353.707 | AK39: =S39 -> 74353.707 | AL39: =AF39 -> 74353.707 | AM39: =A39 -> 5 | AN39: =I39 -> 2451.511 | AO39: =T39 -> 2451.511 | AP39: =AE39 -> 2451.511
A40: =A39+1 -> 6 | B40: =H39 -> 74353.707 | C40: =IF(OR(B40<=0,A40>Financiamento_EV!$C$7),0,B40*Financiamento_EV!$C$9) -> 0 | D40: =MAX(0,B40+C40) -> 74353.707 | E40: =IF(D40<=0,0,D40*Financiamento_EV!$C$6) -> 1264.013 | F40: =IF(D40<=0,0,IF(Financiamento_EV!$C$6=0,D40/(Financiamento_EV!$C$7-A40+1),D40*Financiamento_EV!$C$6/(1-(1+Financiamento_EV!$C$6)^(-(Financiamento_EV!$C$7-A40+1))))) -> 2451.511 | G40: =MAX(0,MIN(D40,F40-E40)) -> 1187.4979 | H40: =MAX(0,D40-G40) -> 73166.209 | I40: =IF(D40<=0,0,F40) -> 2451.511 | K40: =K39+1 -> 6 | L40: =S39 -> 74353.707 | M40: =IF(OR(L40<=0,K40>Financiamento_EV!$C$7),0,L40*Financiamento_EV!$C$9) -> 0 | N40: =MAX(0,L40+M40) -> 74353.707 | O40: =IF(N40<=0,0,N40*Financiamento_EV!$C$6) -> 1264.013 | P40: =IF(N40<=0,0,IF(Financiamento_EV!$C$6=0,N40/(Financiamento_EV!$C$7-K40+1),N40*Financiamento_EV!$C$6/(1-(1+Financiamento_EV!$C$6)^(-(Financiamento_EV!$C$7-K40+1))))) -> 2451.511 | Q40: =MAX(0,MIN(N40,P40-O40)) -> 1187.4979 | R40: =IF(N40<=0,0,MIN(IF(ISNUMBER(INDEX(Financiamento_EV!$I$17:$I$136,K40)),MAX(0,INDEX(Financiamento_EV!$I$17:$I$136,K40)),IF(K40>=Financiamento_EV!$C$11,Financiamento_EV!$C$10,0)),MAX(0,N40-Q40))) -> 0 | S40: =MAX(0,N40-Q40-R40) -> 73166.209 | T40: =IF(N40<=0,0,P40+R40) -> 2451.511 | V40: =V39+1 -> 6 | W40: =AF39 -> 74353.707 | X40: =IF(OR(W40<=0,V40>Financiamento_EV!$C$7),0,W40*Financiamento_EV!$C$9) -> 0 | Y40: =MAX(0,W40+X40) -> 74353.707 | Z40: =IF(Y40<=0,0,Y40*Financiamento_EV!$C$6) -> 1264.013 | AA40: =IF(Y40<=0,0,IF(Financiamento_EV!$C$6=0,Y40/(Financiamento_EV!$C$7-V40+1),Y40*Financiamento_EV!$C$6/(1-(1+Financiamento_EV!$C$6)^(-(Financiamento_EV!$C$7-V40+1))))) -> 2451.511 | AB40: =MAX(0,MIN(Y40,AA40-Z40)) -> 1187.4979 | AC40: =IF(Y40<=0,0,MIN(IF(ISNUMBER(INDEX(Financiamento_EV!$I$17:$I$136,V40)),MAX(0,INDEX(Financiamento_EV!$I$17:$I$136,V40)),IF(V40>=Financiamento_EV!$C$11,Financiamento_EV!$C$10,0)),MAX(0,Y40-AB40))) -> 0 | AD40: =IF(OR(Y40<=0,V40<Financiamento_EV!$C$11),0,MIN(MAX(0,Financiamento_EV!$F$5-AA40),MAX(0,Y40-AB40-AC40))) -> 9.094947e-13 | AE40: =IF(Y40<=0,0,AA40+AC40+AD40) -> 2451.511 | AF40: =MAX(0,Y40-AB40-AC40-AD40) -> 73166.209 | AG40: =AC40+AD40 -> 9.094947e-13 | AI40: =A40 -> 6 | AJ40: =H40 -> 73166.209 | AK40: =S40 -> 73166.209 | AL40: =AF40 -> 73166.209 | AM40: =A40 -> 6 | AN40: =I40 -> 2451.511 | AO40: =T40 -> 2451.511 | AP40: =AE40 -> 2451.511
A41: =A40+1 -> 7 | B41: =H40 -> 73166.209 | C41: =IF(OR(B41<=0,A41>Financiamento_EV!$C$7),0,B41*Financiamento_EV!$C$9) -> 0 | D41: =MAX(0,B41+C41) -> 73166.209 | E41: =IF(D41<=0,0,D41*Financiamento_EV!$C$6) -> 1243.8256 | F41: =IF(D41<=0,0,IF(Financiamento_EV!$C$6=0,D41/(Financiamento_EV!$C$7-A41+1),D41*Financiamento_EV!$C$6/(1-(1+Financiamento_EV!$C$6)^(-(Financiamento_EV!$C$7-A41+1))))) -> 2451.511 | G41: =MAX(0,MIN(D41,F41-E41)) -> 1207.6854 | H41: =MAX(0,D41-G41) -> 71958.524 | I41: =IF(D41<=0,0,F41) -> 2451.511 | K41: =K40+1 -> 7 | L41: =S40 -> 73166.209 | M41: =IF(OR(L41<=0,K41>Financiamento_EV!$C$7),0,L41*Financiamento_EV!$C$9) -> 0 | N41: =MAX(0,L41+M41) -> 73166.209 | O41: =IF(N41<=0,0,N41*Financiamento_EV!$C$6) -> 1243.8256 | P41: =IF(N41<=0,0,IF(Financiamento_EV!$C$6=0,N41/(Financiamento_EV!$C$7-K41+1),N41*Financiamento_EV!$C$6/(1-(1+Financiamento_EV!$C$6)^(-(Financiamento_EV!$C$7-K41+1))))) -> 2451.511 | Q41: =MAX(0,MIN(N41,P41-O41)) -> 1207.6854 | R41: =IF(N41<=0,0,MIN(IF(ISNUMBER(INDEX(Financiamento_EV!$I$17:$I$136,K41)),MAX(0,INDEX(Financiamento_EV!$I$17:$I$136,K41)),IF(K41>=Financiamento_EV!$C$11,Financiamento_EV!$C$10,0)),MAX(0,N41-Q41))) -> 0 | S41: =MAX(0,N41-Q41-R41) -> 71958.524 | T41: =IF(N41<=0,0,P41+R41) -> 2451.511 | V41: =V40+1 -> 7 | W41: =AF40 -> 73166.209 | X41: =IF(OR(W41<=0,V41>Financiamento_EV!$C$7),0,W41*Financiamento_EV!$C$9) -> 0 | Y41: =MAX(0,W41+X41) -> 73166.209 | Z41: =IF(Y41<=0,0,Y41*Financiamento_EV!$C$6) -> 1243.8256 | AA41: =IF(Y41<=0,0,IF(Financiamento_EV!$C$6=0,Y41/(Financiamento_EV!$C$7-V41+1),Y41*Financiamento_EV!$C$6/(1-(1+Financiamento_EV!$C$6)^(-(Financiamento_EV!$C$7-V41+1))))) -> 2451.511 | AB41: =MAX(0,MIN(Y41,AA41-Z41)) -> 1207.6854 | AC41: =IF(Y41<=0,0,MIN(IF(ISNUMBER(INDEX(Financiamento_EV!$I$17:$I$136,V41)),MAX(0,INDEX(Financiamento_EV!$I$17:$I$136,V41)),IF(V41>=Financiamento_EV!$C$11,Financiamento_EV!$C$10,0)),MAX(0,Y41-AB41))) -> 0 | AD41: =IF(OR(Y41<=0,V41<Financiamento_EV!$C$11),0,MIN(MAX(0,Financiamento_EV!$F$5-AA41),MAX(0,Y41-AB41-AC41))) -> 9.094947e-13 | AE41: =IF(Y41<=0,0,AA41+AC41+AD41) -> 2451.511 | AF41: =MAX(0,Y41-AB41-AC41-AD41) -> 71958.524 | AG41: =AC41+AD41 -> 9.094947e-13 | AI41: =A41 -> 7 | AJ41: =H41 -> 71958.524 | AK41: =S41 -> 71958.524 | AL41: =AF41 -> 71958.524 | AM41: =A41 -> 7 | AN41: =I41 -> 2451.511 | AO41: =T41 -> 2451.511 | AP41: =AE41 -> 2451.511
A42: =A41+1 -> 8 | B42: =H41 -> 71958.524 | C42: =IF(OR(B42<=0,A42>Financiamento_EV!$C$7),0,B42*Financiamento_EV!$C$9) -> 0 | D42: =MAX(0,B42+C42) -> 71958.524 | E42: =IF(D42<=0,0,D42*Financiamento_EV!$C$6) -> 1223.2949 | F42: =IF(D42<=0,0,IF(Financiamento_EV!$C$6=0,D42/(Financiamento_EV!$C$7-A42+1),D42*Financiamento_EV!$C$6/(1-(1+Financiamento_EV!$C$6)^(-(Financiamento_EV!$C$7-A42+1))))) -> 2451.511 | G42: =MAX(0,MIN(D42,F42-E42)) -> 1228.216 | H42: =MAX(0,D42-G42) -> 70730.308 | I42: =IF(D42<=0,0,F42) -> 2451.511 | K42: =K41+1 -> 8 | L42: =S41 -> 71958.524 | M42: =IF(OR(L42<=0,K42>Financiamento_EV!$C$7),0,L42*Financiamento_EV!$C$9) -> 0 | N42: =MAX(0,L42+M42) -> 71958.524 | O42: =IF(N42<=0,0,N42*Financiamento_EV!$C$6) -> 1223.2949 | P42: =IF(N42<=0,0,IF(Financiamento_EV!$C$6=0,N42/(Financiamento_EV!$C$7-K42+1),N42*Financiamento_EV!$C$6/(1-(1+Financiamento_EV!$C$6)^(-(Financiamento_EV!$C$7-K42+1))))) -> 2451.511 | Q42: =MAX(0,MIN(N42,P42-O42)) -> 1228.216 | R42: =IF(N42<=0,0,MIN(IF(ISNUMBER(INDEX(Financiamento_EV!$I$17:$I$136,K42)),MAX(0,INDEX(Financiamento_EV!$I$17:$I$136,K42)),IF(K42>=Financiamento_EV!$C$11,Financiamento_EV!$C$10,0)),MAX(0,N42-Q42))) -> 0 | S42: =MAX(0,N42-Q42-R42) -> 70730.308 | T42: =IF(N42<=0,0,P42+R42) -> 2451.511 | V42: =V41+1 -> 8 | W42: =AF41 -> 71958.524 | X42: =IF(OR(W42<=0,V42>Financiamento_EV!$C$7),0,W42*Financiamento_EV!$C$9) -> 0 | Y42: =MAX(0,W42+X42) -> 71958.524 | Z42: =IF(Y42<=0,0,Y42*Financiamento_EV!$C$6) -> 1223.2949 | AA42: =IF(Y42<=0,0,IF(Financiamento_EV!$C$6=0,Y42/(Financiamento_EV!$C$7-V42+1),Y42*Financiamento_EV!$C$6/(1-(1+Financiamento_EV!$C$6)^(-(Financiamento_EV!$C$7-V42+1))))) -> 2451.511 | AB42: =MAX(0,MIN(Y42,AA42-Z42)) -> 1228.216 | AC42: =IF(Y42<=0,0,MIN(IF(ISNUMBER(INDEX(Financiamento_EV!$I$17:$I$136,V42)),MAX(0,INDEX(Financiamento_EV!$I$17:$I$136,V42)),IF(V42>=Financiamento_EV!$C$11,Financiamento_EV!$C$10,0)),MAX(0,Y42-AB42))) -> 0 | AD42: =IF(OR(Y42<=0,V42<Financiamento_EV!$C$11),0,MIN(MAX(0,Financiamento_EV!$F$5-AA42),MAX(0,Y42-AB42-AC42))) -> 9.094947e-13 | AE42: =IF(Y42<=0,0,AA42+AC42+AD42) -> 2451.511 | AF42: =MAX(0,Y42-AB42-AC42-AD42) -> 70730.308 | AG42: =AC42+AD42 -> 9.094947e-13 | AI42: =A42 -> 8 | AJ42: =H42 -> 70730.308 | AK42: =S42 -> 70730.308 | AL42: =AF42 -> 70730.308 | AM42: =A42 -> 8 | AN42: =I42 -> 2451.511 | AO42: =T42 -> 2451.511 | AP42: =AE42 -> 2451.511
A43: =A42+1 -> 9 | B43: =H42 -> 70730.308 | C43: =IF(OR(B43<=0,A43>Financiamento_EV!$C$7),0,B43*Financiamento_EV!$C$9) -> 0 | D43: =MAX(0,B43+C43) -> 70730.308 | E43: =IF(D43<=0,0,D43*Financiamento_EV!$C$6) -> 1202.4152 | F43: =IF(D43<=0,0,IF(Financiamento_EV!$C$6=0,D43/(Financiamento_EV!$C$7-A43+1),D43*Financiamento_EV!$C$6/(1-(1+Financiamento_EV!$C$6)^(-(Financiamento_EV!$C$7-A43+1))))) -> 2451.511 | G43: =MAX(0,MIN(D43,F43-E43)) -> 1249.0957 | H43: =MAX(0,D43-G43) -> 69481.212 | I43: =IF(D43<=0,0,F43) -> 2451.511 | K43: =K42+1 -> 9 | L43: =S42 -> 70730.308 | M43: =IF(OR(L43<=0,K43>Financiamento_EV!$C$7),0,L43*Financiamento_EV!$C$9) -> 0 | N43: =MAX(0,L43+M43) -> 70730.308 | O43: =IF(N43<=0,0,N43*Financiamento_EV!$C$6) -> 1202.4152 | P43: =IF(N43<=0,0,IF(Financiamento_EV!$C$6=0,N43/(Financiamento_EV!$C$7-K43+1),N43*Financiamento_EV!$C$6/(1-(1+Financiamento_EV!$C$6)^(-(Financiamento_EV!$C$7-K43+1))))) -> 2451.511 | Q43: =MAX(0,MIN(N43,P43-O43)) -> 1249.0957 | R43: =IF(N43<=0,0,MIN(IF(ISNUMBER(INDEX(Financiamento_EV!$I$17:$I$136,K43)),MAX(0,INDEX(Financiamento_EV!$I$17:$I$136,K43)),IF(K43>=Financiamento_EV!$C$11,Financiamento_EV!$C$10,0)),MAX(0,N43-Q43))) -> 0 | S43: =MAX(0,N43-Q43-R43) -> 69481.212 | T43: =IF(N43<=0,0,P43+R43) -> 2451.511 | V43: =V42+1 -> 9 | W43: =AF42 -> 70730.308 | X43: =IF(OR(W43<=0,V43>Financiamento_EV!$C$7),0,W43*Financiamento_EV!$C$9) -> 0 | Y43: =MAX(0,W43+X43) -> 70730.308 | Z43: =IF(Y43<=0,0,Y43*Financiamento_EV!$C$6) -> 1202.4152 | AA43: =IF(Y43<=0,0,IF(Financiamento_EV!$C$6=0,Y43/(Financiamento_EV!$C$7-V43+1),Y43*Financiamento_EV!$C$6/(1-(1+Financiamento_EV!$C$6)^(-(Financiamento_EV!$C$7-V43+1))))) -> 2451.511 | AB43: =MAX(0,MIN(Y43,AA43-Z43)) -> 1249.0957 | AC43: =IF(Y43<=0,0,MIN(IF(ISNUMBER(INDEX(Financiamento_EV!$I$17:$I$136,V43)),MAX(0,INDEX(Financiamento_EV!$I$17:$I$136,V43)),IF(V43>=Financiamento_EV!$C$11,Financiamento_EV!$C$10,0)),MAX(0,Y43-AB43))) -> 0 | AD43: =IF(OR(Y43<=0,V43<Financiamento_EV!$C$11),0,MIN(MAX(0,Financiamento_EV!$F$5-AA43),MAX(0,Y43-AB43-AC43))) -> 1.3642421e-12 | AE43: =IF(Y43<=0,0,AA43+AC43+AD43) -> 2451.511 | AF43: =MAX(0,Y43-AB43-AC43-AD43) -> 69481.212 | AG43: =AC43+AD43 -> 1.3642421e-12 | AI43: =A43 -> 9 | AJ43: =H43 -> 69481.212 | AK43: =S43 -> 69481.212 | AL43: =AF43 -> 69481.212 | AM43: =A43 -> 9 | AN43: =I43 -> 2451.511 | AO43: =T43 -> 2451.511 | AP43: =AE43 -> 2451.511
A44: =A43+1 -> 10 | B44: =H43 -> 69481.212 | C44: =IF(OR(B44<=0,A44>Financiamento_EV!$C$7),0,B44*Financiamento_EV!$C$9) -> 0 | D44: =MAX(0,B44+C44) -> 69481.212 | E44: =IF(D44<=0,0,D44*Financiamento_EV!$C$6) -> 1181.1806 | F44: =IF(D44<=0,0,IF(Financiamento_EV!$C$6=0,D44/(Financiamento_EV!$C$7-A44+1),D44*Financiamento_EV!$C$6/(1-(1+Financiamento_EV!$C$6)^(-(Financiamento_EV!$C$7-A44+1))))) -> 2451.511 | G44: =MAX(0,MIN(D44,F44-E44)) -> 1270.3303 | H44: =MAX(0,D44-G44) -> 68210.882 | I44: =IF(D44<=0,0,F44) -> 2451.511 | K44: =K43+1 -> 10 | L44: =S43 -> 69481.212 | M44: =IF(OR(L44<=0,K44>Financiamento_EV!$C$7),0,L44*Financiamento_EV!$C$9) -> 0 | N44: =MAX(0,L44+M44) -> 69481.212 | O44: =IF(N44<=0,0,N44*Financiamento_EV!$C$6) -> 1181.1806 | P44: =IF(N44<=0,0,IF(Financiamento_EV!$C$6=0,N44/(Financiamento_EV!$C$7-K44+1),N44*Financiamento_EV!$C$6/(1-(1+Financiamento_EV!$C$6)^(-(Financiamento_EV!$C$7-K44+1))))) -> 2451.511 | Q44: =MAX(0,MIN(N44,P44-O44)) -> 1270.3303 | R44: =IF(N44<=0,0,MIN(IF(ISNUMBER(INDEX(Financiamento_EV!$I$17:$I$136,K44)),MAX(0,INDEX(Financiamento_EV!$I$17:$I$136,K44)),IF(K44>=Financiamento_EV!$C$11,Financiamento_EV!$C$10,0)),MAX(0,N44-Q44))) -> 0 | S44: =MAX(0,N44-Q44-R44) -> 68210.882 | T44: =IF(N44<=0,0,P44+R44) -> 2451.511 | V44: =V43+1 -> 10 | W44: =AF43 -> 69481.212 | X44: =IF(OR(W44<=0,V44>Financiamento_EV!$C$7),0,W44*Financiamento_EV!$C$9) -> 0 | Y44: =MAX(0,W44+X44) -> 69481.212 | Z44: =IF(Y44<=0,0,Y44*Financiamento_EV!$C$6) -> 1181.1806 | AA44: =IF(Y44<=0,0,IF(Financiamento_EV!$C$6=0,Y44/(Financiamento_EV!$C$7-V44+1),Y44*Financiamento_EV!$C$6/(1-(1+Financiamento_EV!$C$6)^(-(Financiamento_EV!$C$7-V44+1))))) -> 2451.511 | AB44: =MAX(0,MIN(Y44,AA44-Z44)) -> 1270.3303 | AC44: =IF(Y44<=0,0,MIN(IF(ISNUMBER(INDEX(Financiamento_EV!$I$17:$I$136,V44)),MAX(0,INDEX(Financiamento_EV!$I$17:$I$136,V44)),IF(V44>=Financiamento_EV!$C$11,Financiamento_EV!$C$10,0)),MAX(0,Y44-AB44))) -> 0 | AD44: =IF(OR(Y44<=0,V44<Financiamento_EV!$C$11),0,MIN(MAX(0,Financiamento_EV!$F$5-AA44),MAX(0,Y44-AB44-AC44))) -> 1.3642421e-12 | AE44: =IF(Y44<=0,0,AA44+AC44+AD44) -> 2451.511 | AF44: =MAX(0,Y44-AB44-AC44-AD44) -> 68210.882 | AG44: =AC44+AD44 -> 1.3642421e-12 | AI44: =A44 -> 10 | AJ44: =H44 -> 68210.882 | AK44: =S44 -> 68210.882 | AL44: =AF44 -> 68210.882 | AM44: =A44 -> 10 | AN44: =I44 -> 2451.511 | AO44: =T44 -> 2451.511 | AP44: =AE44 -> 2451.511
A45: =A44+1 -> 11 | B45: =H44 -> 68210.882 | C45: =IF(OR(B45<=0,A45>Financiamento_EV!$C$7),0,B45*Financiamento_EV!$C$9) -> 0 | D45: =MAX(0,B45+C45) -> 68210.882 | E45: =IF(D45<=0,0,D45*Financiamento_EV!$C$6) -> 1159.585 | F45: =IF(D45<=0,0,IF(Financiamento_EV!$C$6=0,D45/(Financiamento_EV!$C$7-A45+1),D45*Financiamento_EV!$C$6/(1-(1+Financiamento_EV!$C$6)^(-(Financiamento_EV!$C$7-A45+1))))) -> 2451.511 | G45: =MAX(0,MIN(D45,F45-E45)) -> 1291.926 | H45: =MAX(0,D45-G45) -> 66918.956 | I45: =IF(D45<=0,0,F45) -> 2451.511 | K45: =K44+1 -> 11 | L45: =S44 -> 68210.882 | M45: =IF(OR(L45<=0,K45>Financiamento_EV!$C$7),0,L45*Financiamento_EV!$C$9) -> 0 | N45: =MAX(0,L45+M45) -> 68210.882 | O45: =IF(N45<=0,0,N45*Financiamento_EV!$C$6) -> 1159.585 | P45: =IF(N45<=0,0,IF(Financiamento_EV!$C$6=0,N45/(Financiamento_EV!$C$7-K45+1),N45*Financiamento_EV!$C$6/(1-(1+Financiamento_EV!$C$6)^(-(Financiamento_EV!$C$7-K45+1))))) -> 2451.511 | Q45: =MAX(0,MIN(N45,P45-O45)) -> 1291.926 | R45: =IF(N45<=0,0,MIN(IF(ISNUMBER(INDEX(Financiamento_EV!$I$17:$I$136,K45)),MAX(0,INDEX(Financiamento_EV!$I$17:$I$136,K45)),IF(K45>=Financiamento_EV!$C$11,Financiamento_EV!$C$10,0)),MAX(0,N45-Q45))) -> 0 | S45: =MAX(0,N45-Q45-R45) -> 66918.956 | T45: =IF(N45<=0,0,P45+R45) -> 2451.511 | V45: =V44+1 -> 11 | W45: =AF44 -> 68210.882 | X45: =IF(OR(W45<=0,V45>Financiamento_EV!$C$7),0,W45*Financiamento_EV!$C$9) -> 0 | Y45: =MAX(0,W45+X45) -> 68210.882 | Z45: =IF(Y45<=0,0,Y45*Financiamento_EV!$C$6) -> 1159.585 | AA45: =IF(Y45<=0,0,IF(Financiamento_EV!$C$6=0,Y45/(Financiamento_EV!$C$7-V45+1),Y45*Financiamento_EV!$C$6/(1-(1+Financiamento_EV!$C$6)^(-(Financiamento_EV!$C$7-V45+1))))) -> 2451.511 | AB45: =MAX(0,MIN(Y45,AA45-Z45)) -> 1291.926 | AC45: =IF(Y45<=0,0,MIN(IF(ISNUMBER(INDEX(Financiamento_EV!$I$17:$I$136,V45)),MAX(0,INDEX(Financiamento_EV!$I$17:$I$136,V45)),IF(V45>=Financiamento_EV!$C$11,Financiamento_EV!$C$10,0)),MAX(0,Y45-AB45))) -> 0 | AD45: =IF(OR(Y45<=0,V45<Financiamento_EV!$C$11),0,MIN(MAX(0,Financiamento_EV!$F$5-AA45),MAX(0,Y45-AB45-AC45))) -> 2.2737368e-12 | AE45: =IF(Y45<=0,0,AA45+AC45+AD45) -> 2451.511 | AF45: =MAX(0,Y45-AB45-AC45-AD45) -> 66918.956 | AG45: =AC45+AD45 -> 2.2737368e-12 | AI45: =A45 -> 11 | AJ45: =H45 -> 66918.956 | AK45: =S45 -> 66918.956 | AL45: =AF45 -> 66918.956 | AM45: =A45 -> 11 | AN45: =I45 -> 2451.511 | AO45: =T45 -> 2451.511 | AP45: =AE45 -> 2451.511
A46: =A45+1 -> 12 | B46: =H45 -> 66918.956 | C46: =IF(OR(B46<=0,A46>Financiamento_EV!$C$7),0,B46*Financiamento_EV!$C$9) -> 0 | D46: =MAX(0,B46+C46) -> 66918.956 | E46: =IF(D46<=0,0,D46*Financiamento_EV!$C$6) -> 1137.6222 | F46: =IF(D46<=0,0,IF(Financiamento_EV!$C$6=0,D46/(Financiamento_EV!$C$7-A46+1),D46*Financiamento_EV!$C$6/(1-(1+Financiamento_EV!$C$6)^(-(Financiamento_EV!$C$7-A46+1))))) -> 2451.511 | G46: =MAX(0,MIN(D46,F46-E46)) -> 1313.8887 | H46: =MAX(0,D46-G46) -> 65605.067 | I46: =IF(D46<=0,0,F46) -> 2451.511 | K46: =K45+1 -> 12 | L46: =S45 -> 66918.956 | M46: =IF(OR(L46<=0,K46>Financiamento_EV!$C$7),0,L46*Financiamento_EV!$C$9) -> 0 | N46: =MAX(0,L46+M46) -> 66918.956 | O46: =IF(N46<=0,0,N46*Financiamento_EV!$C$6) -> 1137.6222 | P46: =IF(N46<=0,0,IF(Financiamento_EV!$C$6=0,N46/(Financiamento_EV!$C$7-K46+1),N46*Financiamento_EV!$C$6/(1-(1+Financiamento_EV!$C$6)^(-(Financiamento_EV!$C$7-K46+1))))) -> 2451.511 | Q46: =MAX(0,MIN(N46,P46-O46)) -> 1313.8887 | R46: =IF(N46<=0,0,MIN(IF(ISNUMBER(INDEX(Financiamento_EV!$I$17:$I$136,K46)),MAX(0,INDEX(Financiamento_EV!$I$17:$I$136,K46)),IF(K46>=Financiamento_EV!$C$11,Financiamento_EV!$C$10,0)),MAX(0,N46-Q46))) -> 0 | S46: =MAX(0,N46-Q46-R46) -> 65605.067 | T46: =IF(N46<=0,0,P46+R46) -> 2451.511 | V46: =V45+1 -> 12 | W46: =AF45 -> 66918.956 | X46: =IF(OR(W46<=0,V46>Financiamento_EV!$C$7),0,W46*Financiamento_EV!$C$9) -> 0 | Y46: =MAX(0,W46+X46) -> 66918.956 | Z46: =IF(Y46<=0,0,Y46*Financiamento_EV!$C$6) -> 1137.6222 | AA46: =IF(Y46<=0,0,IF(Financiamento_EV!$C$6=0,Y46/(Financiamento_EV!$C$7-V46+1),Y46*Financiamento_EV!$C$6/(1-(1+Financiamento_EV!$C$6)^(-(Financiamento_EV!$C$7-V46+1))))) -> 2451.511 | AB46: =MAX(0,MIN(Y46,AA46-Z46)) -> 1313.8887 | AC46: =IF(Y46<=0,0,MIN(IF(ISNUMBER(INDEX(Financiamento_EV!$I$17:$I$136,V46)),MAX(0,INDEX(Financiamento_EV!$I$17:$I$136,V46)),IF(V46>=Financiamento_EV!$C$11,Financiamento_EV!$C$10,0)),MAX(0,Y46-AB46))) -> 0 | AD46: =IF(OR(Y46<=0,V46<Financiamento_EV!$C$11),0,MIN(MAX(0,Financiamento_EV!$F$5-AA46),MAX(0,Y46-AB46-AC46))) -> 1.8189894e-12 | AE46: =IF(Y46<=0,0,AA46+AC46+AD46) -> 2451.511 | AF46: =MAX(0,Y46-AB46-AC46-AD46) -> 65605.067 | AG46: =AC46+AD46 -> 1.8189894e-12 | AI46: =A46 -> 12 | AJ46: =H46 -> 65605.067 | AK46: =S46 -> 65605.067 | AL46: =AF46 -> 65605.067 | AM46: =A46 -> 12 | AN46: =I46 -> 2451.511 | AO46: =T46 -> 2451.511 | AP46: =AE46 -> 2451.511
A47: =A46+1 -> 13 | B47: =H46 -> 65605.067 | C47: =IF(OR(B47<=0,A47>Financiamento_EV!$C$7),0,B47*Financiamento_EV!$C$9) -> 0 | D47: =MAX(0,B47+C47) -> 65605.067 | E47: =IF(D47<=0,0,D47*Financiamento_EV!$C$6) -> 1115.2861 | F47: =IF(D47<=0,0,IF(Financiamento_EV!$C$6=0,D47/(Financiamento_EV!$C$7-A47+1),D47*Financiamento_EV!$C$6/(1-(1+Financiamento_EV!$C$6)^(-(Financiamento_EV!$C$7-A47+1))))) -> 2451.511 | G47: =MAX(0,MIN(D47,F47-E47)) -> 1336.2248 | H47: =MAX(0,D47-G47) -> 64268.842 | I47: =IF(D47<=0,0,F47) -> 2451.511 | K47: =K46+1 -> 13 | L47: =S46 -> 65605.067 | M47: =IF(OR(L47<=0,K47>Financiamento_EV!$C$7),0,L47*Financiamento_EV!$C$9) -> 0 | N47: =MAX(0,L47+M47) -> 65605.067 | O47: =IF(N47<=0,0,N47*Financiamento_EV!$C$6) -> 1115.2861 | P47: =IF(N47<=0,0,IF(Financiamento_EV!$C$6=0,N47/(Financiamento_EV!$C$7-K47+1),N47*Financiamento_EV!$C$6/(1-(1+Financiamento_EV!$C$6)^(-(Financiamento_EV!$C$7-K47+1))))) -> 2451.511 | Q47: =MAX(0,MIN(N47,P47-O47)) -> 1336.2248 | R47: =IF(N47<=0,0,MIN(IF(ISNUMBER(INDEX(Financiamento_EV!$I$17:$I$136,K47)),MAX(0,INDEX(Financiamento_EV!$I$17:$I$136,K47)),IF(K47>=Financiamento_EV!$C$11,Financiamento_EV!$C$10,0)),MAX(0,N47-Q47))) -> 0 | S47: =MAX(0,N47-Q47-R47) -> 64268.842 | T47: =IF(N47<=0,0,P47+R47) -> 2451.511 | V47: =V46+1 -> 13 | W47: =AF46 -> 65605.067 | X47: =IF(OR(W47<=0,V47>Financiamento_EV!$C$7),0,W47*Financiamento_EV!$C$9) -> 0 | Y47: =MAX(0,W47+X47) -> 65605.067 | Z47: =IF(Y47<=0,0,Y47*Financiamento_EV!$C$6) -> 1115.2861 | AA47: =IF(Y47<=0,0,IF(Financiamento_EV!$C$6=0,Y47/(Financiamento_EV!$C$7-V47+1),Y47*Financiamento_EV!$C$6/(1-(1+Financiamento_EV!$C$6)^(-(Financiamento_EV!$C$7-V47+1))))) -> 2451.511 | AB47: =MAX(0,MIN(Y47,AA47-Z47)) -> 1336.2248 | AC47: =IF(Y47<=0,0,MIN(IF(ISNUMBER(INDEX(Financiamento_EV!$I$17:$I$136,V47)),MAX(0,INDEX(Financiamento_EV!$I$17:$I$136,V47)),IF(V47>=Financiamento_EV!$C$11,Financiamento_EV!$C$10,0)),MAX(0,Y47-AB47))) -> 0 | AD47: =IF(OR(Y47<=0,V47<Financiamento_EV!$C$11),0,MIN(MAX(0,Financiamento_EV!$F$5-AA47),MAX(0,Y47-AB47-AC47))) -> 2.7284841e-12 | AE47: =IF(Y47<=0,0,AA47+AC47+AD47) -> 2451.511 | AF47: =MAX(0,Y47-AB47-AC47-AD47) -> 64268.842 | AG47: =AC47+AD47 -> 2.7284841e-12 | AI47: =A47 -> 13 | AJ47: =H47 -> 64268.842 | AK47: =S47 -> 64268.842 | AL47: =AF47 -> 64268.842 | AM47: =A47 -> 13 | AN47: =I47 -> 2451.511 | AO47: =T47 -> 2451.511 | AP47: =AE47 -> 2451.511
... A94: =A93+1 -> 60 | B94: =H93 -> 0 | C94: =IF(OR(B94<=0,A94>Financiamento_EV!$C$7),0,B94*Financiamento_EV!$C$9) -> 0 | D94: =MAX(0,B94+C94) -> 0 | E94: =IF(D94<=0,0,D94*Financiamento_EV!$C$6) -> 0 | F94: =IF(D94<=0,0,IF(Financiamento_EV!$C$6=0,D94/(Financiamento_EV!$C$7-A94+1),D94*Financiamento_EV!$C$6/(1-(1+Financiamento_EV!$C$6)^(-(Financiamento_EV!$C$7-A94+1))))) -> 0 | G94: =MAX(0,MIN(D94,F94-E94)) -> 0 | H94: =MAX(0,D94-G94) -> 0 | I94: =IF(D94<=0,0,F94) -> 0 | K94: =K93+1 -> 60 | L94: =S93 -> 0 | M94: =IF(OR(L94<=0,K94>Financiamento_EV!$C$7),0,L94*Financiamento_EV!$C$9) -> 0 | N94: =MAX(0,L94+M94) -> 0 | O94: =IF(N94<=0,0,N94*Financiamento_EV!$C$6) -> 0 | P94: =IF(N94<=0,0,IF(Financiamento_EV!$C$6=0,N94/(Financiamento_EV!$C$7-K94+1),N94*Financiamento_EV!$C$6/(1-(1+Financiamento_EV!$C$6)^(-(Financiamento_EV!$C$7-K94+1))))) -> 0 | Q94: =MAX(0,MIN(N94,P94-O94)) -> 0 | R94: =IF(N94<=0,0,MIN(IF(ISNUMBER(INDEX(Financiamento_EV!$I$17:$I$136,K94)),MAX(0,INDEX(Financiamento_EV!$I$17:$I$136,K94)),IF(K94>=Financiamento_EV!$C$11,Financiamento_EV!$C$10,0)),MAX(0,N94-Q94))) -> 0 | S94: =MAX(0,N94-Q94-R94) -> 0 | T94: =IF(N94<=0,0,P94+R94) -> 0 | V94: =V93+1 -> 60 | W94: =AF93 -> 0 | X94: =IF(OR(W94<=0,V94>Financiamento_EV!$C$7),0,W94*Financiamento_EV!$C$9) -> 0 | Y94: =MAX(0,W94+X94) -> 0 | Z94: =IF(Y94<=0,0,Y94*Financiamento_EV!$C$6) -> 0 | AA94: =IF(Y94<=0,0,IF(Financiamento_EV!$C$6=0,Y94/(Financiamento_EV!$C$7-V94+1),Y94*Financiamento_EV!$C$6/(1-(1+Financiamento_EV!$C$6)^(-(Financiamento_EV!$C$7-V94+1))))) -> 0 | AB94: =MAX(0,MIN(Y94,AA94-Z94)) -> 0 | AC94: =IF(Y94<=0,0,MIN(IF(ISNUMBER(INDEX(Financiamento_EV!$I$17:$I$136,V94)),MAX(0,INDEX(Financiamento_EV!$I$17:$I$136,V94)),IF(V94>=Financiamento_EV!$C$11,Financiamento_EV!$C$10,0)),MAX(0,Y94-AB94))) -> 0 | AD94: =IF(OR(Y94<=0,V94<Financiamento_EV!$C$11),0,MIN(MAX(0,Financiamento_EV!$F$5-AA94),MAX(0,Y94-AB94-AC94))) -> 0 | AE94: =IF(Y94<=0,0,AA94+AC94+AD94) -> 0 | AF94: =MAX(0,Y94-AB94-AC94-AD94) -> 0 | AG94: =AC94+AD94 -> 0 | AI94: =A94 -> 60 | AJ94: =H94 -> 0 | AK94: =S94 -> 0 | AL94: =AF94 -> 0 | AM94: =A94 -> 60 | AN94: =I94 -> 0 | AO94: =T94 -> 0 | AP94: =AE94 -> 0
A95: =A94+1 -> 61 | B95: =H94 -> 0 | C95: =IF(OR(B95<=0,A95>Financiamento_EV!$C$7),0,B95*Financiamento_EV!$C$9) -> 0 | D95: =MAX(0,B95+C95) -> 0 | E95: =IF(D95<=0,0,D95*Financiamento_EV!$C$6) -> 0 | F95: =IF(D95<=0,0,IF(Financiamento_EV!$C$6=0,D95/(Financiamento_EV!$C$7-A95+1),D95*Financiamento_EV!$C$6/(1-(1+Financiamento_EV!$C$6)^(-(Financiamento_EV!$C$7-A95+1))))) -> 0 | G95: =MAX(0,MIN(D95,F95-E95)) -> 0 | H95: =MAX(0,D95-G95) -> 0 | I95: =IF(D95<=0,0,F95) -> 0 | K95: =K94+1 -> 61 | L95: =S94 -> 0 | M95: =IF(OR(L95<=0,K95>Financiamento_EV!$C$7),0,L95*Financiamento_EV!$C$9) -> 0 | N95: =MAX(0,L95+M95) -> 0 | O95: =IF(N95<=0,0,N95*Financiamento_EV!$C$6) -> 0 | P95: =IF(N95<=0,0,IF(Financiamento_EV!$C$6=0,N95/(Financiamento_EV!$C$7-K95+1),N95*Financiamento_EV!$C$6/(1-(1+Financiamento_EV!$C$6)^(-(Financiamento_EV!$C$7-K95+1))))) -> 0 | Q95: =MAX(0,MIN(N95,P95-O95)) -> 0 | R95: =IF(N95<=0,0,MIN(IF(ISNUMBER(INDEX(Financiamento_EV!$I$17:$I$136,K95)),MAX(0,INDEX(Financiamento_EV!$I$17:$I$136,K95)),IF(K95>=Financiamento_EV!$C$11,Financiamento_EV!$C$10,0)),MAX(0,N95-Q95))) -> 0 | S95: =MAX(0,N95-Q95-R95) -> 0 | T95: =IF(N95<=0,0,P95+R95) -> 0 | V95: =V94+1 -> 61 | W95: =AF94 -> 0 | X95: =IF(OR(W95<=0,V95>Financiamento_EV!$C$7),0,W95*Financiamento_EV!$C$9) -> 0 | Y95: =MAX(0,W95+X95) -> 0 | Z95: =IF(Y95<=0,0,Y95*Financiamento_EV!$C$6) -> 0 | AA95: =IF(Y95<=0,0,IF(Financiamento_EV!$C$6=0,Y95/(Financiamento_EV!$C$7-V95+1),Y95*Financiamento_EV!$C$6/(1-(1+Financiamento_EV!$C$6)^(-(Financiamento_EV!$C$7-V95+1))))) -> 0 | AB95: =MAX(0,MIN(Y95,AA95-Z95)) -> 0 | AC95: =IF(Y95<=0,0,MIN(IF(ISNUMBER(INDEX(Financiamento_EV!$I$17:$I$136,V95)),MAX(0,INDEX(Financiamento_EV!$I$17:$I$136,V95)),IF(V95>=Financiamento_EV!$C$11,Financiamento_EV!$C$10,0)),MAX(0,Y95-AB95))) -> 0 | AD95: =IF(OR(Y95<=0,V95<Financiamento_EV!$C$11),0,MIN(MAX(0,Financiamento_EV!$F$5-AA95),MAX(0,Y95-AB95-AC95))) -> 0 | AE95: =IF(Y95<=0,0,AA95+AC95+AD95) -> 0 | AF95: =MAX(0,Y95-AB95-AC95-AD95) -> 0 | AG95: =AC95+AD95 -> 0
A96: =A95+1 -> 62 | B96: =H95 -> 0 | C96: =IF(OR(B96<=0,A96>Financiamento_EV!$C$7),0,B96*Financiamento_EV!$C$9) -> 0 | D96: =MAX(0,B96+C96) -> 0 | E96: =IF(D96<=0,0,D96*Financiamento_EV!$C$6) -> 0 | F96: =IF(D96<=0,0,IF(Financiamento_EV!$C$6=0,D96/(Financiamento_EV!$C$7-A96+1),D96*Financiamento_EV!$C$6/(1-(1+Financiamento_EV!$C$6)^(-(Financiamento_EV!$C$7-A96+1))))) -> 0 | G96: =MAX(0,MIN(D96,F96-E96)) -> 0 | H96: =MAX(0,D96-G96) -> 0 | I96: =IF(D96<=0,0,F96) -> 0 | K96: =K95+1 -> 62 | L96: =S95 -> 0 | M96: =IF(OR(L96<=0,K96>Financiamento_EV!$C$7),0,L96*Financiamento_EV!$C$9) -> 0 | N96: =MAX(0,L96+M96) -> 0 | O96: =IF(N96<=0,0,N96*Financiamento_EV!$C$6) -> 0 | P96: =IF(N96<=0,0,IF(Financiamento_EV!$C$6=0,N96/(Financiamento_EV!$C$7-K96+1),N96*Financiamento_EV!$C$6/(1-(1+Financiamento_EV!$C$6)^(-(Financiamento_EV!$C$7-K96+1))))) -> 0 | Q96: =MAX(0,MIN(N96,P96-O96)) -> 0 | R96: =IF(N96<=0,0,MIN(IF(ISNUMBER(INDEX(Financiamento_EV!$I$17:$I$136,K96)),MAX(0,INDEX(Financiamento_EV!$I$17:$I$136,K96)),IF(K96>=Financiamento_EV!$C$11,Financiamento_EV!$C$10,0)),MAX(0,N96-Q96))) -> 0 | S96: =MAX(0,N96-Q96-R96) -> 0 | T96: =IF(N96<=0,0,P96+R96) -> 0 | V96: =V95+1 -> 62 | W96: =AF95 -> 0 | X96: =IF(OR(W96<=0,V96>Financiamento_EV!$C$7),0,W96*Financiamento_EV!$C$9) -> 0 | Y96: =MAX(0,W96+X96) -> 0 | Z96: =IF(Y96<=0,0,Y96*Financiamento_EV!$C$6) -> 0 | AA96: =IF(Y96<=0,0,IF(Financiamento_EV!$C$6=0,Y96/(Financiamento_EV!$C$7-V96+1),Y96*Financiamento_EV!$C$6/(1-(1+Financiamento_EV!$C$6)^(-(Financiamento_EV!$C$7-V96+1))))) -> 0 | AB96: =MAX(0,MIN(Y96,AA96-Z96)) -> 0 | AC96: =IF(Y96<=0,0,MIN(IF(ISNUMBER(INDEX(Financiamento_EV!$I$17:$I$136,V96)),MAX(0,INDEX(Financiamento_EV!$I$17:$I$136,V96)),IF(V96>=Financiamento_EV!$C$11,Financiamento_EV!$C$10,0)),MAX(0,Y96-AB96))) -> 0 | AD96: =IF(OR(Y96<=0,V96<Financiamento_EV!$C$11),0,MIN(MAX(0,Financiamento_EV!$F$5-AA96),MAX(0,Y96-AB96-AC96))) -> 0 | AE96: =IF(Y96<=0,0,AA96+AC96+AD96) -> 0 | AF96: =MAX(0,Y96-AB96-AC96-AD96) -> 0 | AG96: =AC96+AD96 -> 0
A97: =A96+1 -> 63 | B97: =H96 -> 0 | C97: =IF(OR(B97<=0,A97>Financiamento_EV!$C$7),0,B97*Financiamento_EV!$C$9) -> 0 | D97: =MAX(0,B97+C97) -> 0 | E97: =IF(D97<=0,0,D97*Financiamento_EV!$C$6) -> 0 | F97: =IF(D97<=0,0,IF(Financiamento_EV!$C$6=0,D97/(Financiamento_EV!$C$7-A97+1),D97*Financiamento_EV!$C$6/(1-(1+Financiamento_EV!$C$6)^(-(Financiamento_EV!$C$7-A97+1))))) -> 0 | G97: =MAX(0,MIN(D97,F97-E97)) -> 0 | H97: =MAX(0,D97-G97) -> 0 | I97: =IF(D97<=0,0,F97) -> 0 | K97: =K96+1 -> 63 | L97: =S96 -> 0 | M97: =IF(OR(L97<=0,K97>Financiamento_EV!$C$7),0,L97*Financiamento_EV!$C$9) -> 0 | N97: =MAX(0,L97+M97) -> 0 | O97: =IF(N97<=0,0,N97*Financiamento_EV!$C$6) -> 0 | P97: =IF(N97<=0,0,IF(Financiamento_EV!$C$6=0,N97/(Financiamento_EV!$C$7-K97+1),N97*Financiamento_EV!$C$6/(1-(1+Financiamento_EV!$C$6)^(-(Financiamento_EV!$C$7-K97+1))))) -> 0 | Q97: =MAX(0,MIN(N97,P97-O97)) -> 0 | R97: =IF(N97<=0,0,MIN(IF(ISNUMBER(INDEX(Financiamento_EV!$I$17:$I$136,K97)),MAX(0,INDEX(Financiamento_EV!$I$17:$I$136,K97)),IF(K97>=Financiamento_EV!$C$11,Financiamento_EV!$C$10,0)),MAX(0,N97-Q97))) -> 0 | S97: =MAX(0,N97-Q97-R97) -> 0 | T97: =IF(N97<=0,0,P97+R97) -> 0 | V97: =V96+1 -> 63 | W97: =AF96 -> 0 | X97: =IF(OR(W97<=0,V97>Financiamento_EV!$C$7),0,W97*Financiamento_EV!$C$9) -> 0 | Y97: =MAX(0,W97+X97) -> 0 | Z97: =IF(Y97<=0,0,Y97*Financiamento_EV!$C$6) -> 0 | AA97: =IF(Y97<=0,0,IF(Financiamento_EV!$C$6=0,Y97/(Financiamento_EV!$C$7-V97+1),Y97*Financiamento_EV!$C$6/(1-(1+Financiamento_EV!$C$6)^(-(Financiamento_EV!$C$7-V97+1))))) -> 0 | AB97: =MAX(0,MIN(Y97,AA97-Z97)) -> 0 | AC97: =IF(Y97<=0,0,MIN(IF(ISNUMBER(INDEX(Financiamento_EV!$I$17:$I$136,V97)),MAX(0,INDEX(Financiamento_EV!$I$17:$I$136,V97)),IF(V97>=Financiamento_EV!$C$11,Financiamento_EV!$C$10,0)),MAX(0,Y97-AB97))) -> 0 | AD97: =IF(OR(Y97<=0,V97<Financiamento_EV!$C$11),0,MIN(MAX(0,Financiamento_EV!$F$5-AA97),MAX(0,Y97-AB97-AC97))) -> 0 | AE97: =IF(Y97<=0,0,AA97+AC97+AD97) -> 0 | AF97: =MAX(0,Y97-AB97-AC97-AD97) -> 0 | AG97: =AC97+AD97 -> 0
A98: =A97+1 -> 64 | B98: =H97 -> 0 | C98: =IF(OR(B98<=0,A98>Financiamento_EV!$C$7),0,B98*Financiamento_EV!$C$9) -> 0 | D98: =MAX(0,B98+C98) -> 0 | E98: =IF(D98<=0,0,D98*Financiamento_EV!$C$6) -> 0 | F98: =IF(D98<=0,0,IF(Financiamento_EV!$C$6=0,D98/(Financiamento_EV!$C$7-A98+1),D98*Financiamento_EV!$C$6/(1-(1+Financiamento_EV!$C$6)^(-(Financiamento_EV!$C$7-A98+1))))) -> 0 | G98: =MAX(0,MIN(D98,F98-E98)) -> 0 | H98: =MAX(0,D98-G98) -> 0 | I98: =IF(D98<=0,0,F98) -> 0 | K98: =K97+1 -> 64 | L98: =S97 -> 0 | M98: =IF(OR(L98<=0,K98>Financiamento_EV!$C$7),0,L98*Financiamento_EV!$C$9) -> 0 | N98: =MAX(0,L98+M98) -> 0 | O98: =IF(N98<=0,0,N98*Financiamento_EV!$C$6) -> 0 | P98: =IF(N98<=0,0,IF(Financiamento_EV!$C$6=0,N98/(Financiamento_EV!$C$7-K98+1),N98*Financiamento_EV!$C$6/(1-(1+Financiamento_EV!$C$6)^(-(Financiamento_EV!$C$7-K98+1))))) -> 0 | Q98: =MAX(0,MIN(N98,P98-O98)) -> 0 | R98: =IF(N98<=0,0,MIN(IF(ISNUMBER(INDEX(Financiamento_EV!$I$17:$I$136,K98)),MAX(0,INDEX(Financiamento_EV!$I$17:$I$136,K98)),IF(K98>=Financiamento_EV!$C$11,Financiamento_EV!$C$10,0)),MAX(0,N98-Q98))) -> 0 | S98: =MAX(0,N98-Q98-R98) -> 0 | T98: =IF(N98<=0,0,P98+R98) -> 0 | V98: =V97+1 -> 64 | W98: =AF97 -> 0 | X98: =IF(OR(W98<=0,V98>Financiamento_EV!$C$7),0,W98*Financiamento_EV!$C$9) -> 0 | Y98: =MAX(0,W98+X98) -> 0 | Z98: =IF(Y98<=0,0,Y98*Financiamento_EV!$C$6) -> 0 | AA98: =IF(Y98<=0,0,IF(Financiamento_EV!$C$6=0,Y98/(Financiamento_EV!$C$7-V98+1),Y98*Financiamento_EV!$C$6/(1-(1+Financiamento_EV!$C$6)^(-(Financiamento_EV!$C$7-V98+1))))) -> 0 | AB98: =MAX(0,MIN(Y98,AA98-Z98)) -> 0 | AC98: =IF(Y98<=0,0,MIN(IF(ISNUMBER(INDEX(Financiamento_EV!$I$17:$I$136,V98)),MAX(0,INDEX(Financiamento_EV!$I$17:$I$136,V98)),IF(V98>=Financiamento_EV!$C$11,Financiamento_EV!$C$10,0)),MAX(0,Y98-AB98))) -> 0 | AD98: =IF(OR(Y98<=0,V98<Financiamento_EV!$C$11),0,MIN(MAX(0,Financiamento_EV!$F$5-AA98),MAX(0,Y98-AB98-AC98))) -> 0 | AE98: =IF(Y98<=0,0,AA98+AC98+AD98) -> 0 | AF98: =MAX(0,Y98-AB98-AC98-AD98) -> 0 | AG98: =AC98+AD98 -> 0
A99: =A98+1 -> 65 | B99: =H98 -> 0 | C99: =IF(OR(B99<=0,A99>Financiamento_EV!$C$7),0,B99*Financiamento_EV!$C$9) -> 0 | D99: =MAX(0,B99+C99) -> 0 | E99: =IF(D99<=0,0,D99*Financiamento_EV!$C$6) -> 0 | F99: =IF(D99<=0,0,IF(Financiamento_EV!$C$6=0,D99/(Financiamento_EV!$C$7-A99+1),D99*Financiamento_EV!$C$6/(1-(1+Financiamento_EV!$C$6)^(-(Financiamento_EV!$C$7-A99+1))))) -> 0 | G99: =MAX(0,MIN(D99,F99-E99)) -> 0 | H99: =MAX(0,D99-G99) -> 0 | I99: =IF(D99<=0,0,F99) -> 0 | K99: =K98+1 -> 65 | L99: =S98 -> 0 | M99: =IF(OR(L99<=0,K99>Financiamento_EV!$C$7),0,L99*Financiamento_EV!$C$9) -> 0 | N99: =MAX(0,L99+M99) -> 0 | O99: =IF(N99<=0,0,N99*Financiamento_EV!$C$6) -> 0 | P99: =IF(N99<=0,0,IF(Financiamento_EV!$C$6=0,N99/(Financiamento_EV!$C$7-K99+1),N99*Financiamento_EV!$C$6/(1-(1+Financiamento_EV!$C$6)^(-(Financiamento_EV!$C$7-K99+1))))) -> 0 | Q99: =MAX(0,MIN(N99,P99-O99)) -> 0 | R99: =IF(N99<=0,0,MIN(IF(ISNUMBER(INDEX(Financiamento_EV!$I$17:$I$136,K99)),MAX(0,INDEX(Financiamento_EV!$I$17:$I$136,K99)),IF(K99>=Financiamento_EV!$C$11,Financiamento_EV!$C$10,0)),MAX(0,N99-Q99))) -> 0 | S99: =MAX(0,N99-Q99-R99) -> 0 | T99: =IF(N99<=0,0,P99+R99) -> 0 | V99: =V98+1 -> 65 | W99: =AF98 -> 0 | X99: =IF(OR(W99<=0,V99>Financiamento_EV!$C$7),0,W99*Financiamento_EV!$C$9) -> 0 | Y99: =MAX(0,W99+X99) -> 0 | Z99: =IF(Y99<=0,0,Y99*Financiamento_EV!$C$6) -> 0 | AA99: =IF(Y99<=0,0,IF(Financiamento_EV!$C$6=0,Y99/(Financiamento_EV!$C$7-V99+1),Y99*Financiamento_EV!$C$6/(1-(1+Financiamento_EV!$C$6)^(-(Financiamento_EV!$C$7-V99+1))))) -> 0 | AB99: =MAX(0,MIN(Y99,AA99-Z99)) -> 0 | AC99: =IF(Y99<=0,0,MIN(IF(ISNUMBER(INDEX(Financiamento_EV!$I$17:$I$136,V99)),MAX(0,INDEX(Financiamento_EV!$I$17:$I$136,V99)),IF(V99>=Financiamento_EV!$C$11,Financiamento_EV!$C$10,0)),MAX(0,Y99-AB99))) -> 0 | AD99: =IF(OR(Y99<=0,V99<Financiamento_EV!$C$11),0,MIN(MAX(0,Financiamento_EV!$F$5-AA99),MAX(0,Y99-AB99-AC99))) -> 0 | AE99: =IF(Y99<=0,0,AA99+AC99+AD99) -> 0 | AF99: =MAX(0,Y99-AB99-AC99-AD99) -> 0 | AG99: =AC99+AD99 -> 0
A100: =A99+1 -> 66 | B100: =H99 -> 0 | C100: =IF(OR(B100<=0,A100>Financiamento_EV!$C$7),0,B100*Financiamento_EV!$C$9) -> 0 | D100: =MAX(0,B100+C100) -> 0 | E100: =IF(D100<=0,0,D100*Financiamento_EV!$C$6) -> 0 | F100: =IF(D100<=0,0,IF(Financiamento_EV!$C$6=0,D100/(Financiamento_EV!$C$7-A100+1),D100*Financiamento_EV!$C$6/(1-(1+Financiamento_EV!$C$6)^(-(Financiamento_EV!$C$7-A100+1))))) -> 0 | G100: =MAX(0,MIN(D100,F100-E100)) -> 0 | H100: =MAX(0,D100-G100) -> 0 | I100: =IF(D100<=0,0,F100) -> 0 | K100: =K99+1 -> 66 | L100: =S99 -> 0 | M100: =IF(OR(L100<=0,K100>Financiamento_EV!$C$7),0,L100*Financiamento_EV!$C$9) -> 0 | N100: =MAX(0,L100+M100) -> 0 | O100: =IF(N100<=0,0,N100*Financiamento_EV!$C$6) -> 0 | P100: =IF(N100<=0,0,IF(Financiamento_EV!$C$6=0,N100/(Financiamento_EV!$C$7-K100+1),N100*Financiamento_EV!$C$6/(1-(1+Financiamento_EV!$C$6)^(-(Financiamento_EV!$C$7-K100+1))))) -> 0 | Q100: =MAX(0,MIN(N100,P100-O100)) -> 0 | R100: =IF(N100<=0,0,MIN(IF(ISNUMBER(INDEX(Financiamento_EV!$I$17:$I$136,K100)),MAX(0,INDEX(Financiamento_EV!$I$17:$I$136,K100)),IF(K100>=Financiamento_EV!$C$11,Financiamento_EV!$C$10,0)),MAX(0,N100-Q100))) -> 0 | S100: =MAX(0,N100-Q100-R100) -> 0 | T100: =IF(N100<=0,0,P100+R100) -> 0 | V100: =V99+1 -> 66 | W100: =AF99 -> 0 | X100: =IF(OR(W100<=0,V100>Financiamento_EV!$C$7),0,W100*Financiamento_EV!$C$9) -> 0 | Y100: =MAX(0,W100+X100) -> 0 | Z100: =IF(Y100<=0,0,Y100*Financiamento_EV!$C$6) -> 0 | AA100: =IF(Y100<=0,0,IF(Financiamento_EV!$C$6=0,Y100/(Financiamento_EV!$C$7-V100+1),Y100*Financiamento_EV!$C$6/(1-(1+Financiamento_EV!$C$6)^(-(Financiamento_EV!$C$7-V100+1))))) -> 0 | AB100: =MAX(0,MIN(Y100,AA100-Z100)) -> 0 | AC100: =IF(Y100<=0,0,MIN(IF(ISNUMBER(INDEX(Financiamento_EV!$I$17:$I$136,V100)),MAX(0,INDEX(Financiamento_EV!$I$17:$I$136,V100)),IF(V100>=Financiamento_EV!$C$11,Financiamento_EV!$C$10,0)),MAX(0,Y100-AB100))) -> 0 | AD100: =IF(OR(Y100<=0,V100<Financiamento_EV!$C$11),0,MIN(MAX(0,Financiamento_EV!$F$5-AA100),MAX(0,Y100-AB100-AC100))) -> 0 | AE100: =IF(Y100<=0,0,AA100+AC100+AD100) -> 0 | AF100: =MAX(0,Y100-AB100-AC100-AD100) -> 0 | AG100: =AC100+AD100 -> 0
A101: =A100+1 -> 67 | B101: =H100 -> 0 | C101: =IF(OR(B101<=0,A101>Financiamento_EV!$C$7),0,B101*Financiamento_EV!$C$9) -> 0 | D101: =MAX(0,B101+C101) -> 0 | E101: =IF(D101<=0,0,D101*Financiamento_EV!$C$6) -> 0 | F101: =IF(D101<=0,0,IF(Financiamento_EV!$C$6=0,D101/(Financiamento_EV!$C$7-A101+1),D101*Financiamento_EV!$C$6/(1-(1+Financiamento_EV!$C$6)^(-(Financiamento_EV!$C$7-A101+1))))) -> 0 | G101: =MAX(0,MIN(D101,F101-E101)) -> 0 | H101: =MAX(0,D101-G101) -> 0 | I101: =IF(D101<=0,0,F101) -> 0 | K101: =K100+1 -> 67 | L101: =S100 -> 0 | M101: =IF(OR(L101<=0,K101>Financiamento_EV!$C$7),0,L101*Financiamento_EV!$C$9) -> 0 | N101: =MAX(0,L101+M101) -> 0 | O101: =IF(N101<=0,0,N101*Financiamento_EV!$C$6) -> 0 | P101: =IF(N101<=0,0,IF(Financiamento_EV!$C$6=0,N101/(Financiamento_EV!$C$7-K101+1),N101*Financiamento_EV!$C$6/(1-(1+Financiamento_EV!$C$6)^(-(Financiamento_EV!$C$7-K101+1))))) -> 0 | Q101: =MAX(0,MIN(N101,P101-O101)) -> 0 | R101: =IF(N101<=0,0,MIN(IF(ISNUMBER(INDEX(Financiamento_EV!$I$17:$I$136,K101)),MAX(0,INDEX(Financiamento_EV!$I$17:$I$136,K101)),IF(K101>=Financiamento_EV!$C$11,Financiamento_EV!$C$10,0)),MAX(0,N101-Q101))) -> 0 | S101: =MAX(0,N101-Q101-R101) -> 0 | T101: =IF(N101<=0,0,P101+R101) -> 0 | V101: =V100+1 -> 67 | W101: =AF100 -> 0 | X101: =IF(OR(W101<=0,V101>Financiamento_EV!$C$7),0,W101*Financiamento_EV!$C$9) -> 0 | Y101: =MAX(0,W101+X101) -> 0 | Z101: =IF(Y101<=0,0,Y101*Financiamento_EV!$C$6) -> 0 | AA101: =IF(Y101<=0,0,IF(Financiamento_EV!$C$6=0,Y101/(Financiamento_EV!$C$7-V101+1),Y101*Financiamento_EV!$C$6/(1-(1+Financiamento_EV!$C$6)^(-(Financiamento_EV!$C$7-V101+1))))) -> 0 | AB101: =MAX(0,MIN(Y101,AA101-Z101)) -> 0 | AC101: =IF(Y101<=0,0,MIN(IF(ISNUMBER(INDEX(Financiamento_EV!$I$17:$I$136,V101)),MAX(0,INDEX(Financiamento_EV!$I$17:$I$136,V101)),IF(V101>=Financiamento_EV!$C$11,Financiamento_EV!$C$10,0)),MAX(0,Y101-AB101))) -> 0 | AD101: =IF(OR(Y101<=0,V101<Financiamento_EV!$C$11),0,MIN(MAX(0,Financiamento_EV!$F$5-AA101),MAX(0,Y101-AB101-AC101))) -> 0 | AE101: =IF(Y101<=0,0,AA101+AC101+AD101) -> 0 | AF101: =MAX(0,Y101-AB101-AC101-AD101) -> 0 | AG101: =AC101+AD101 -> 0
A102: =A101+1 -> 68 | B102: =H101 -> 0 | C102: =IF(OR(B102<=0,A102>Financiamento_EV!$C$7),0,B102*Financiamento_EV!$C$9) -> 0 | D102: =MAX(0,B102+C102) -> 0 | E102: =IF(D102<=0,0,D102*Financiamento_EV!$C$6) -> 0 | F102: =IF(D102<=0,0,IF(Financiamento_EV!$C$6=0,D102/(Financiamento_EV!$C$7-A102+1),D102*Financiamento_EV!$C$6/(1-(1+Financiamento_EV!$C$6)^(-(Financiamento_EV!$C$7-A102+1))))) -> 0 | G102: =MAX(0,MIN(D102,F102-E102)) -> 0 | H102: =MAX(0,D102-G102) -> 0 | I102: =IF(D102<=0,0,F102) -> 0 | K102: =K101+1 -> 68 | L102: =S101 -> 0 | M102: =IF(OR(L102<=0,K102>Financiamento_EV!$C$7),0,L102*Financiamento_EV!$C$9) -> 0 | N102: =MAX(0,L102+M102) -> 0 | O102: =IF(N102<=0,0,N102*Financiamento_EV!$C$6) -> 0 | P102: =IF(N102<=0,0,IF(Financiamento_EV!$C$6=0,N102/(Financiamento_EV!$C$7-K102+1),N102*Financiamento_EV!$C$6/(1-(1+Financiamento_EV!$C$6)^(-(Financiamento_EV!$C$7-K102+1))))) -> 0 | Q102: =MAX(0,MIN(N102,P102-O102)) -> 0 | R102: =IF(N102<=0,0,MIN(IF(ISNUMBER(INDEX(Financiamento_EV!$I$17:$I$136,K102)),MAX(0,INDEX(Financiamento_EV!$I$17:$I$136,K102)),IF(K102>=Financiamento_EV!$C$11,Financiamento_EV!$C$10,0)),MAX(0,N102-Q102))) -> 0 | S102: =MAX(0,N102-Q102-R102) -> 0 | T102: =IF(N102<=0,0,P102+R102) -> 0 | V102: =V101+1 -> 68 | W102: =AF101 -> 0 | X102: =IF(OR(W102<=0,V102>Financiamento_EV!$C$7),0,W102*Financiamento_EV!$C$9) -> 0 | Y102: =MAX(0,W102+X102) -> 0 | Z102: =IF(Y102<=0,0,Y102*Financiamento_EV!$C$6) -> 0 | AA102: =IF(Y102<=0,0,IF(Financiamento_EV!$C$6=0,Y102/(Financiamento_EV!$C$7-V102+1),Y102*Financiamento_EV!$C$6/(1-(1+Financiamento_EV!$C$6)^(-(Financiamento_EV!$C$7-V102+1))))) -> 0 | AB102: =MAX(0,MIN(Y102,AA102-Z102)) -> 0 | AC102: =IF(Y102<=0,0,MIN(IF(ISNUMBER(INDEX(Financiamento_EV!$I$17:$I$136,V102)),MAX(0,INDEX(Financiamento_EV!$I$17:$I$136,V102)),IF(V102>=Financiamento_EV!$C$11,Financiamento_EV!$C$10,0)),MAX(0,Y102-AB102))) -> 0 | AD102: =IF(OR(Y102<=0,V102<Financiamento_EV!$C$11),0,MIN(MAX(0,Financiamento_EV!$F$5-AA102),MAX(0,Y102-AB102-AC102))) -> 0 | AE102: =IF(Y102<=0,0,AA102+AC102+AD102) -> 0 | AF102: =MAX(0,Y102-AB102-AC102-AD102) -> 0 | AG102: =AC102+AD102 -> 0
A103: =A102+1 -> 69 | B103: =H102 -> 0 | C103: =IF(OR(B103<=0,A103>Financiamento_EV!$C$7),0,B103*Financiamento_EV!$C$9) -> 0 | D103: =MAX(0,B103+C103) -> 0 | E103: =IF(D103<=0,0,D103*Financiamento_EV!$C$6) -> 0 | F103: =IF(D103<=0,0,IF(Financiamento_EV!$C$6=0,D103/(Financiamento_EV!$C$7-A103+1),D103*Financiamento_EV!$C$6/(1-(1+Financiamento_EV!$C$6)^(-(Financiamento_EV!$C$7-A103+1))))) -> 0 | G103: =MAX(0,MIN(D103,F103-E103)) -> 0 | H103: =MAX(0,D103-G103) -> 0 | I103: =IF(D103<=0,0,F103) -> 0 | K103: =K102+1 -> 69 | L103: =S102 -> 0 | M103: =IF(OR(L103<=0,K103>Financiamento_EV!$C$7),0,L103*Financiamento_EV!$C$9) -> 0 | N103: =MAX(0,L103+M103) -> 0 | O103: =IF(N103<=0,0,N103*Financiamento_EV!$C$6) -> 0 | P103: =IF(N103<=0,0,IF(Financiamento_EV!$C$6=0,N103/(Financiamento_EV!$C$7-K103+1),N103*Financiamento_EV!$C$6/(1-(1+Financiamento_EV!$C$6)^(-(Financiamento_EV!$C$7-K103+1))))) -> 0 | Q103: =MAX(0,MIN(N103,P103-O103)) -> 0 | R103: =IF(N103<=0,0,MIN(IF(ISNUMBER(INDEX(Financiamento_EV!$I$17:$I$136,K103)),MAX(0,INDEX(Financiamento_EV!$I$17:$I$136,K103)),IF(K103>=Financiamento_EV!$C$11,Financiamento_EV!$C$10,0)),MAX(0,N103-Q103))) -> 0 | S103: =MAX(0,N103-Q103-R103) -> 0 | T103: =IF(N103<=0,0,P103+R103) -> 0 | V103: =V102+1 -> 69 | W103: =AF102 -> 0 | X103: =IF(OR(W103<=0,V103>Financiamento_EV!$C$7),0,W103*Financiamento_EV!$C$9) -> 0 | Y103: =MAX(0,W103+X103) -> 0 | Z103: =IF(Y103<=0,0,Y103*Financiamento_EV!$C$6) -> 0 | AA103: =IF(Y103<=0,0,IF(Financiamento_EV!$C$6=0,Y103/(Financiamento_EV!$C$7-V103+1),Y103*Financiamento_EV!$C$6/(1-(1+Financiamento_EV!$C$6)^(-(Financiamento_EV!$C$7-V103+1))))) -> 0 | AB103: =MAX(0,MIN(Y103,AA103-Z103)) -> 0 | AC103: =IF(Y103<=0,0,MIN(IF(ISNUMBER(INDEX(Financiamento_EV!$I$17:$I$136,V103)),MAX(0,INDEX(Financiamento_EV!$I$17:$I$136,V103)),IF(V103>=Financiamento_EV!$C$11,Financiamento_EV!$C$10,0)),MAX(0,Y103-AB103))) -> 0 | AD103: =IF(OR(Y103<=0,V103<Financiamento_EV!$C$11),0,MIN(MAX(0,Financiamento_EV!$F$5-AA103),MAX(0,Y103-AB103-AC103))) -> 0 | AE103: =IF(Y103<=0,0,AA103+AC103+AD103) -> 0 | AF103: =MAX(0,Y103-AB103-AC103-AD103) -> 0 | AG103: =AC103+AD103 -> 0
A104: =A103+1 -> 70 | B104: =H103 -> 0 | C104: =IF(OR(B104<=0,A104>Financiamento_EV!$C$7),0,B104*Financiamento_EV!$C$9) -> 0 | D104: =MAX(0,B104+C104) -> 0 | E104: =IF(D104<=0,0,D104*Financiamento_EV!$C$6) -> 0 | F104: =IF(D104<=0,0,IF(Financiamento_EV!$C$6=0,D104/(Financiamento_EV!$C$7-A104+1),D104*Financiamento_EV!$C$6/(1-(1+Financiamento_EV!$C$6)^(-(Financiamento_EV!$C$7-A104+1))))) -> 0 | G104: =MAX(0,MIN(D104,F104-E104)) -> 0 | H104: =MAX(0,D104-G104) -> 0 | I104: =IF(D104<=0,0,F104) -> 0 | K104: =K103+1 -> 70 | L104: =S103 -> 0 | M104: =IF(OR(L104<=0,K104>Financiamento_EV!$C$7),0,L104*Financiamento_EV!$C$9) -> 0 | N104: =MAX(0,L104+M104) -> 0 | O104: =IF(N104<=0,0,N104*Financiamento_EV!$C$6) -> 0 | P104: =IF(N104<=0,0,IF(Financiamento_EV!$C$6=0,N104/(Financiamento_EV!$C$7-K104+1),N104*Financiamento_EV!$C$6/(1-(1+Financiamento_EV!$C$6)^(-(Financiamento_EV!$C$7-K104+1))))) -> 0 | Q104: =MAX(0,MIN(N104,P104-O104)) -> 0 | R104: =IF(N104<=0,0,MIN(IF(ISNUMBER(INDEX(Financiamento_EV!$I$17:$I$136,K104)),MAX(0,INDEX(Financiamento_EV!$I$17:$I$136,K104)),IF(K104>=Financiamento_EV!$C$11,Financiamento_EV!$C$10,0)),MAX(0,N104-Q104))) -> 0 | S104: =MAX(0,N104-Q104-R104) -> 0 | T104: =IF(N104<=0,0,P104+R104) -> 0 | V104: =V103+1 -> 70 | W104: =AF103 -> 0 | X104: =IF(OR(W104<=0,V104>Financiamento_EV!$C$7),0,W104*Financiamento_EV!$C$9) -> 0 | Y104: =MAX(0,W104+X104) -> 0 | Z104: =IF(Y104<=0,0,Y104*Financiamento_EV!$C$6) -> 0 | AA104: =IF(Y104<=0,0,IF(Financiamento_EV!$C$6=0,Y104/(Financiamento_EV!$C$7-V104+1),Y104*Financiamento_EV!$C$6/(1-(1+Financiamento_EV!$C$6)^(-(Financiamento_EV!$C$7-V104+1))))) -> 0 | AB104: =MAX(0,MIN(Y104,AA104-Z104)) -> 0 | AC104: =IF(Y104<=0,0,MIN(IF(ISNUMBER(INDEX(Financiamento_EV!$I$17:$I$136,V104)),MAX(0,INDEX(Financiamento_EV!$I$17:$I$136,V104)),IF(V104>=Financiamento_EV!$C$11,Financiamento_EV!$C$10,0)),MAX(0,Y104-AB104))) -> 0 | AD104: =IF(OR(Y104<=0,V104<Financiamento_EV!$C$11),0,MIN(MAX(0,Financiamento_EV!$F$5-AA104),MAX(0,Y104-AB104-AC104))) -> 0 | AE104: =IF(Y104<=0,0,AA104+AC104+AD104) -> 0 | AF104: =MAX(0,Y104-AB104-AC104-AD104) -> 0 | AG104: =AC104+AD104 -> 0
A105: =A104+1 -> 71 | B105: =H104 -> 0 | C105: =IF(OR(B105<=0,A105>Financiamento_EV!$C$7),0,B105*Financiamento_EV!$C$9) -> 0 | D105: =MAX(0,B105+C105) -> 0 | E105: =IF(D105<=0,0,D105*Financiamento_EV!$C$6) -> 0 | F105: =IF(D105<=0,0,IF(Financiamento_EV!$C$6=0,D105/(Financiamento_EV!$C$7-A105+1),D105*Financiamento_EV!$C$6/(1-(1+Financiamento_EV!$C$6)^(-(Financiamento_EV!$C$7-A105+1))))) -> 0 | G105: =MAX(0,MIN(D105,F105-E105)) -> 0 | H105: =MAX(0,D105-G105) -> 0 | I105: =IF(D105<=0,0,F105) -> 0 | K105: =K104+1 -> 71 | L105: =S104 -> 0 | M105: =IF(OR(L105<=0,K105>Financiamento_EV!$C$7),0,L105*Financiamento_EV!$C$9) -> 0 | N105: =MAX(0,L105+M105) -> 0 | O105: =IF(N105<=0,0,N105*Financiamento_EV!$C$6) -> 0 | P105: =IF(N105<=0,0,IF(Financiamento_EV!$C$6=0,N105/(Financiamento_EV!$C$7-K105+1),N105*Financiamento_EV!$C$6/(1-(1+Financiamento_EV!$C$6)^(-(Financiamento_EV!$C$7-K105+1))))) -> 0 | Q105: =MAX(0,MIN(N105,P105-O105)) -> 0 | R105: =IF(N105<=0,0,MIN(IF(ISNUMBER(INDEX(Financiamento_EV!$I$17:$I$136,K105)),MAX(0,INDEX(Financiamento_EV!$I$17:$I$136,K105)),IF(K105>=Financiamento_EV!$C$11,Financiamento_EV!$C$10,0)),MAX(0,N105-Q105))) -> 0 | S105: =MAX(0,N105-Q105-R105) -> 0 | T105: =IF(N105<=0,0,P105+R105) -> 0 | V105: =V104+1 -> 71 | W105: =AF104 -> 0 | X105: =IF(OR(W105<=0,V105>Financiamento_EV!$C$7),0,W105*Financiamento_EV!$C$9) -> 0 | Y105: =MAX(0,W105+X105) -> 0 | Z105: =IF(Y105<=0,0,Y105*Financiamento_EV!$C$6) -> 0 | AA105: =IF(Y105<=0,0,IF(Financiamento_EV!$C$6=0,Y105/(Financiamento_EV!$C$7-V105+1),Y105*Financiamento_EV!$C$6/(1-(1+Financiamento_EV!$C$6)^(-(Financiamento_EV!$C$7-V105+1))))) -> 0 | AB105: =MAX(0,MIN(Y105,AA105-Z105)) -> 0 | AC105: =IF(Y105<=0,0,MIN(IF(ISNUMBER(INDEX(Financiamento_EV!$I$17:$I$136,V105)),MAX(0,INDEX(Financiamento_EV!$I$17:$I$136,V105)),IF(V105>=Financiamento_EV!$C$11,Financiamento_EV!$C$10,0)),MAX(0,Y105-AB105))) -> 0 | AD105: =IF(OR(Y105<=0,V105<Financiamento_EV!$C$11),0,MIN(MAX(0,Financiamento_EV!$F$5-AA105),MAX(0,Y105-AB105-AC105))) -> 0 | AE105: =IF(Y105<=0,0,AA105+AC105+AD105) -> 0 | AF105: =MAX(0,Y105-AB105-AC105-AD105) -> 0 | AG105: =AC105+AD105 -> 0
A106: =A105+1 -> 72 | B106: =H105 -> 0 | C106: =IF(OR(B106<=0,A106>Financiamento_EV!$C$7),0,B106*Financiamento_EV!$C$9) -> 0 | D106: =MAX(0,B106+C106) -> 0 | E106: =IF(D106<=0,0,D106*Financiamento_EV!$C$6) -> 0 | F106: =IF(D106<=0,0,IF(Financiamento_EV!$C$6=0,D106/(Financiamento_EV!$C$7-A106+1),D106*Financiamento_EV!$C$6/(1-(1+Financiamento_EV!$C$6)^(-(Financiamento_EV!$C$7-A106+1))))) -> 0 | G106: =MAX(0,MIN(D106,F106-E106)) -> 0 | H106: =MAX(0,D106-G106) -> 0 | I106: =IF(D106<=0,0,F106) -> 0 | K106: =K105+1 -> 72 | L106: =S105 -> 0 | M106: =IF(OR(L106<=0,K106>Financiamento_EV!$C$7),0,L106*Financiamento_EV!$C$9) -> 0 | N106: =MAX(0,L106+M106) -> 0 | O106: =IF(N106<=0,0,N106*Financiamento_EV!$C$6) -> 0 | P106: =IF(N106<=0,0,IF(Financiamento_EV!$C$6=0,N106/(Financiamento_EV!$C$7-K106+1),N106*Financiamento_EV!$C$6/(1-(1+Financiamento_EV!$C$6)^(-(Financiamento_EV!$C$7-K106+1))))) -> 0 | Q106: =MAX(0,MIN(N106,P106-O106)) -> 0 | R106: =IF(N106<=0,0,MIN(IF(ISNUMBER(INDEX(Financiamento_EV!$I$17:$I$136,K106)),MAX(0,INDEX(Financiamento_EV!$I$17:$I$136,K106)),IF(K106>=Financiamento_EV!$C$11,Financiamento_EV!$C$10,0)),MAX(0,N106-Q106))) -> 0 | S106: =MAX(0,N106-Q106-R106) -> 0 | T106: =IF(N106<=0,0,P106+R106) -> 0 | V106: =V105+1 -> 72 | W106: =AF105 -> 0 | X106: =IF(OR(W106<=0,V106>Financiamento_EV!$C$7),0,W106*Financiamento_EV!$C$9) -> 0 | Y106: =MAX(0,W106+X106) -> 0 | Z106: =IF(Y106<=0,0,Y106*Financiamento_EV!$C$6) -> 0 | AA106: =IF(Y106<=0,0,IF(Financiamento_EV!$C$6=0,Y106/(Financiamento_EV!$C$7-V106+1),Y106*Financiamento_EV!$C$6/(1-(1+Financiamento_EV!$C$6)^(-(Financiamento_EV!$C$7-V106+1))))) -> 0 | AB106: =MAX(0,MIN(Y106,AA106-Z106)) -> 0 | AC106: =IF(Y106<=0,0,MIN(IF(ISNUMBER(INDEX(Financiamento_EV!$I$17:$I$136,V106)),MAX(0,INDEX(Financiamento_EV!$I$17:$I$136,V106)),IF(V106>=Financiamento_EV!$C$11,Financiamento_EV!$C$10,0)),MAX(0,Y106-AB106))) -> 0 | AD106: =IF(OR(Y106<=0,V106<Financiamento_EV!$C$11),0,MIN(MAX(0,Financiamento_EV!$F$5-AA106),MAX(0,Y106-AB106-AC106))) -> 0 | AE106: =IF(Y106<=0,0,AA106+AC106+AD106) -> 0 | AF106: =MAX(0,Y106-AB106-AC106-AD106) -> 0 | AG106: =AC106+AD106 -> 0
... A154: =A153+1 -> 120 | B154: =H153 -> 0 | C154: =IF(OR(B154<=0,A154>Financiamento_EV!$C$7),0,B154*Financiamento_EV!$C$9) -> 0 | D154: =MAX(0,B154+C154) -> 0 | E154: =IF(D154<=0,0,D154*Financiamento_EV!$C$6) -> 0 | F154: =IF(D154<=0,0,IF(Financiamento_EV!$C$6=0,D154/(Financiamento_EV!$C$7-A154+1),D154*Financiamento_EV!$C$6/(1-(1+Financiamento_EV!$C$6)^(-(Financiamento_EV!$C$7-A154+1))))) -> 0 | G154: =MAX(0,MIN(D154,F154-E154)) -> 0 | H154: =MAX(0,D154-G154) -> 0 | I154: =IF(D154<=0,0,F154) -> 0 | K154: =K153+1 -> 120 | L154: =S153 -> 0 | M154: =IF(OR(L154<=0,K154>Financiamento_EV!$C$7),0,L154*Financiamento_EV!$C$9) -> 0 | N154: =MAX(0,L154+M154) -> 0 | O154: =IF(N154<=0,0,N154*Financiamento_EV!$C$6) -> 0 | P154: =IF(N154<=0,0,IF(Financiamento_EV!$C$6=0,N154/(Financiamento_EV!$C$7-K154+1),N154*Financiamento_EV!$C$6/(1-(1+Financiamento_EV!$C$6)^(-(Financiamento_EV!$C$7-K154+1))))) -> 0 | Q154: =MAX(0,MIN(N154,P154-O154)) -> 0 | R154: =IF(N154<=0,0,MIN(IF(ISNUMBER(INDEX(Financiamento_EV!$I$17:$I$136,K154)),MAX(0,INDEX(Financiamento_EV!$I$17:$I$136,K154)),IF(K154>=Financiamento_EV!$C$11,Financiamento_EV!$C$10,0)),MAX(0,N154-Q154))) -> 0 | S154: =MAX(0,N154-Q154-R154) -> 0 | T154: =IF(N154<=0,0,P154+R154) -> 0 | V154: =V153+1 -> 120 | W154: =AF153 -> 0 | X154: =IF(OR(W154<=0,V154>Financiamento_EV!$C$7),0,W154*Financiamento_EV!$C$9) -> 0 | Y154: =MAX(0,W154+X154) -> 0 | Z154: =IF(Y154<=0,0,Y154*Financiamento_EV!$C$6) -> 0 | AA154: =IF(Y154<=0,0,IF(Financiamento_EV!$C$6=0,Y154/(Financiamento_EV!$C$7-V154+1),Y154*Financiamento_EV!$C$6/(1-(1+Financiamento_EV!$C$6)^(-(Financiamento_EV!$C$7-V154+1))))) -> 0 | AB154: =MAX(0,MIN(Y154,AA154-Z154)) -> 0 | AC154: =IF(Y154<=0,0,MIN(IF(ISNUMBER(INDEX(Financiamento_EV!$I$17:$I$136,V154)),MAX(0,INDEX(Financiamento_EV!$I$17:$I$136,V154)),IF(V154>=Financiamento_EV!$C$11,Financiamento_EV!$C$10,0)),MAX(0,Y154-AB154))) -> 0 | AD154: =IF(OR(Y154<=0,V154<Financiamento_EV!$C$11),0,MIN(MAX(0,Financiamento_EV!$F$5-AA154),MAX(0,Y154-AB154-AC154))) -> 0 | AE154: =IF(Y154<=0,0,AA154+AC154+AD154) -> 0 | AF154: =MAX(0,Y154-AB154-AC154-AD154) -> 0 | AG154: =AC154+AD154 -> 0

Sheet Fluxo_EV
A1: Fluxo mensal — quanto o carro elétrico realmente acrescenta ao seu caixa
A2: A parcela líquida da troca é o desembolso mensal do EV (financiamento + operação) menos o TCO de caixa do Tiida. Positivo = gasto adicional; negativo = economia.
A4: Mês 1 | B4: =IF(N11="","",N11) -> 1530.6036 | C4: Média até quitação | D4: =IFERROR(SUMIF(F11:F130,">0",N11:N130)/COUNTIF(F11:F130,">0"),"") -> 1530.6036 | E4: Depois da quitação | F4: =IF(Comparador_EV!J16="","",Comparador_EV!J16-Dashboard!H12) -> -920.90733 | G4: Acumulado até quitação | H4: =IFERROR(SUMIF(F11:F130,">0",N11:N130),"") -> 73468.974 | I4: Prazo efetivo | J4: =Financiamento_EV!F6 -> 48 | K4: Quitação | L4: =Financiamento_EV!F7 -> 47696
A8: PREVISÃO MENSAL
A9: Mês | B9: Data | C9: Parcela contratual | D9: Aporte base | E9: Reinvestimento | F9: Pagamento financiamento | G9: Energia EV | H9: Manutenção EV | I9: Seguro EV | J9: IPVA + lic. | K9: TCO operacional EV | L9: Desembolso total EV | M9: TCO Tiida | N9: PARCELA LÍQUIDA DA TROCA | O9: Saldo devedor | P9: Delta acumulado | R9: Mês | S9: Desembolso EV | T9: Tiida | U9: Parcela líquida
R10: =A11 -> 1 | S10: =L11 -> 3835.1536 | T10: =M11 -> 2304.55 | U10: =N11 -> 1530.6036
A11: 1 | B11: =INDEX(Financiamento_EV!$B$17:$B$136,A11) -> 46266 | C11: =INDEX(Financiamento_EV!$G$17:$G$136,A11) -> 2451.511 | D11: =INDEX(Financiamento_EV!$L$17:$L$136,A11) -> 0 | E11: =INDEX(Financiamento_EV!$M$17:$M$136,A11) -> 0 | F11: =INDEX(Financiamento_EV!$N$17:$N$136,A11) -> 2451.511 | G11: =IF(Comparador_EV!$J$8="","",Comparador_EV!$J$8/12) -> 471.636 | H11: =IF(Comparador_EV!$J$12="","",Comparador_EV!$J$12/12) -> 64.166667 | I11: =IF(Comparador_EV!$J$9="","",Comparador_EV!$J$9/12) -> 466.66667 | J11: =IF(OR(Comparador_EV!$J$10="",Comparador_EV!$J$11=""),"",(Comparador_EV!$J$10+Comparador_EV!$J$11)/12) -> 381.17333 | K11: =IF(COUNT(G11:J11)<4,"",SUM(G11:J11)) -> 1383.6427 | L11: =IF(K11="","",F11+K11) -> 3835.1536 | M11: =Dashboard!$H$12 -> 2304.55 | N11: =IF(OR(L11="",M11=""),"",L11-M11) -> 1530.6036 | O11: =INDEX(Financiamento_EV!$O$17:$O$136,A11) -> 78908.489 | P11: =N11 -> 1530.6036 | R11: =A12 -> 2 | S11: =L12 -> 3835.1536 | T11: =M12 -> 2304.55 | U11: =N12 -> 1530.6036
A12: 2 | B12: =INDEX(Financiamento_EV!$B$17:$B$136,A12) -> 46296 | C12: =INDEX(Financiamento_EV!$G$17:$G$136,A12) -> 2451.511 | D12: =INDEX(Financiamento_EV!$L$17:$L$136,A12) -> 0 | E12: =INDEX(Financiamento_EV!$M$17:$M$136,A12) -> 0 | F12: =INDEX(Financiamento_EV!$N$17:$N$136,A12) -> 2451.511 | G12: =IF(Comparador_EV!$J$8="","",Comparador_EV!$J$8/12) -> 471.636 | H12: =IF(Comparador_EV!$J$12="","",Comparador_EV!$J$12/12) -> 64.166667 | I12: =IF(Comparador_EV!$J$9="","",Comparador_EV!$J$9/12) -> 466.66667 | J12: =IF(OR(Comparador_EV!$J$10="",Comparador_EV!$J$11=""),"",(Comparador_EV!$J$10+Comparador_EV!$J$11)/12) -> 381.17333 | K12: =IF(COUNT(G12:J12)<4,"",SUM(G12:J12)) -> 1383.6427 | L12: =IF(K12="","",F12+K12) -> 3835.1536 | M12: =Dashboard!$H$12 -> 2304.55 | N12: =IF(OR(L12="",M12=""),"",L12-M12) -> 1530.6036 | O12: =INDEX(Financiamento_EV!$O$17:$O$136,A12) -> 77798.422 | P12: =P11+N12 -> 3061.2072 | R12: =A13 -> 3 | S12: =L13 -> 3835.1536 | T12: =M13 -> 2304.55 | U12: =N13 -> 1530.6036
A13: 3 | B13: =INDEX(Financiamento_EV!$B$17:$B$136,A13) -> 46327 | C13: =INDEX(Financiamento_EV!$G$17:$G$136,A13) -> 2451.511 | D13: =INDEX(Financiamento_EV!$L$17:$L$136,A13) -> 0 | E13: =INDEX(Financiamento_EV!$M$17:$M$136,A13) -> 9.094947e-13 | F13: =INDEX(Financiamento_EV!$N$17:$N$136,A13) -> 2451.511 | G13: =IF(Comparador_EV!$J$8="","",Comparador_EV!$J$8/12) -> 471.636 | H13: =IF(Comparador_EV!$J$12="","",Comparador_EV!$J$12/12) -> 64.166667 | I13: =IF(Comparador_EV!$J$9="","",Comparador_EV!$J$9/12) -> 466.66667 | J13: =IF(OR(Comparador_EV!$J$10="",Comparador_EV!$J$11=""),"",(Comparador_EV!$J$10+Comparador_EV!$J$11)/12) -> 381.17333 | K13: =IF(COUNT(G13:J13)<4,"",SUM(G13:J13)) -> 1383.6427 | L13: =IF(K13="","",F13+K13) -> 3835.1536 | M13: =Dashboard!$H$12 -> 2304.55 | N13: =IF(OR(L13="",M13=""),"",L13-M13) -> 1530.6036 | O13: =INDEX(Financiamento_EV!$O$17:$O$136,A13) -> 76669.485 | P13: =P12+N13 -> 4591.8109 | R13: =A14 -> 4 | S13: =L14 -> 3835.1536 | T13: =M14 -> 2304.55 | U13: =N14 -> 1530.6036
A14: 4 | B14: =INDEX(Financiamento_EV!$B$17:$B$136,A14) -> 46357 | C14: =INDEX(Financiamento_EV!$G$17:$G$136,A14) -> 2451.511 | D14: =INDEX(Financiamento_EV!$L$17:$L$136,A14) -> 0 | E14: =INDEX(Financiamento_EV!$M$17:$M$136,A14) -> 4.5474735e-13 | F14: =INDEX(Financiamento_EV!$N$17:$N$136,A14) -> 2451.511 | G14: =IF(Comparador_EV!$J$8="","",Comparador_EV!$J$8/12) -> 471.636 | H14: =IF(Comparador_EV!$J$12="","",Comparador_EV!$J$12/12) -> 64.166667 | I14: =IF(Comparador_EV!$J$9="","",Comparador_EV!$J$9/12) -> 466.66667 | J14: =IF(OR(Comparador_EV!$J$10="",Comparador_EV!$J$11=""),"",(Comparador_EV!$J$10+Comparador_EV!$J$11)/12) -> 381.17333 | K14: =IF(COUNT(G14:J14)<4,"",SUM(G14:J14)) -> 1383.6427 | L14: =IF(K14="","",F14+K14) -> 3835.1536 | M14: =Dashboard!$H$12 -> 2304.55 | N14: =IF(OR(L14="",M14=""),"",L14-M14) -> 1530.6036 | O14: =INDEX(Financiamento_EV!$O$17:$O$136,A14) -> 75521.355 | P14: =P13+N14 -> 6122.4145 | R14: =A15 -> 5 | S14: =L15 -> 3835.1536 | T14: =M15 -> 2304.55 | U14: =N15 -> 1530.6036
A15: 5 | B15: =INDEX(Financiamento_EV!$B$17:$B$136,A15) -> 46388 | C15: =INDEX(Financiamento_EV!$G$17:$G$136,A15) -> 2451.511 | D15: =INDEX(Financiamento_EV!$L$17:$L$136,A15) -> 0 | E15: =INDEX(Financiamento_EV!$M$17:$M$136,A15) -> 9.094947e-13 | F15: =INDEX(Financiamento_EV!$N$17:$N$136,A15) -> 2451.511 | G15: =IF(Comparador_EV!$J$8="","",Comparador_EV!$J$8/12) -> 471.636 | H15: =IF(Comparador_EV!$J$12="","",Comparador_EV!$J$12/12) -> 64.166667 | I15: =IF(Comparador_EV!$J$9="","",Comparador_EV!$J$9/12) -> 466.66667 | J15: =IF(OR(Comparador_EV!$J$10="",Comparador_EV!$J$11=""),"",(Comparador_EV!$J$10+Comparador_EV!$J$11)/12) -> 381.17333 | K15: =IF(COUNT(G15:J15)<4,"",SUM(G15:J15)) -> 1383.6427 | L15: =IF(K15="","",F15+K15) -> 3835.1536 | M15: =Dashboard!$H$12 -> 2304.55 | N15: =IF(OR(L15="",M15=""),"",L15-M15) -> 1530.6036 | O15: =INDEX(Financiamento_EV!$O$17:$O$136,A15) -> 74353.707 | P15: =P14+N15 -> 7653.0181 | R15: =A16 -> 6 | S15: =L16 -> 3835.1536 | T15: =M16 -> 2304.55 | U15: =N16 -> 1530.6036
A16: 6 | B16: =INDEX(Financiamento_EV!$B$17:$B$136,A16) -> 46419 | C16: =INDEX(Financiamento_EV!$G$17:$G$136,A16) -> 2451.511 | D16: =INDEX(Financiamento_EV!$L$17:$L$136,A16) -> 0 | E16: =INDEX(Financiamento_EV!$M$17:$M$136,A16) -> 9.094947e-13 | F16: =INDEX(Financiamento_EV!$N$17:$N$136,A16) -> 2451.511 | G16: =IF(Comparador_EV!$J$8="","",Comparador_EV!$J$8/12) -> 471.636 | H16: =IF(Comparador_EV!$J$12="","",Comparador_EV!$J$12/12) -> 64.166667 | I16: =IF(Comparador_EV!$J$9="","",Comparador_EV!$J$9/12) -> 466.66667 | J16: =IF(OR(Comparador_EV!$J$10="",Comparador_EV!$J$11=""),"",(Comparador_EV!$J$10+Comparador_EV!$J$11)/12) -> 381.17333 | K16: =IF(COUNT(G16:J16)<4,"",SUM(G16:J16)) -> 1383.6427 | L16: =IF(K16="","",F16+K16) -> 3835.1536 | M16: =Dashboard!$H$12 -> 2304.55 | N16: =IF(OR(L16="",M16=""),"",L16-M16) -> 1530.6036 | O16: =INDEX(Financiamento_EV!$O$17:$O$136,A16) -> 73166.209 | P16: =P15+N16 -> 9183.6217 | R16: =A17 -> 7 | S16: =L17 -> 3835.1536 | T16: =M17 -> 2304.55 | U16: =N17 -> 1530.6036
A17: 7 | B17: =INDEX(Financiamento_EV!$B$17:$B$136,A17) -> 46447 | C17: =INDEX(Financiamento_EV!$G$17:$G$136,A17) -> 2451.511 | D17: =INDEX(Financiamento_EV!$L$17:$L$136,A17) -> 0 | E17: =INDEX(Financiamento_EV!$M$17:$M$136,A17) -> 9.094947e-13 | F17: =INDEX(Financiamento_EV!$N$17:$N$136,A17) -> 2451.511 | G17: =IF(Comparador_EV!$J$8="","",Comparador_EV!$J$8/12) -> 471.636 | H17: =IF(Comparador_EV!$J$12="","",Comparador_EV!$J$12/12) -> 64.166667 | I17: =IF(Comparador_EV!$J$9="","",Comparador_EV!$J$9/12) -> 466.66667 | J17: =IF(OR(Comparador_EV!$J$10="",Comparador_EV!$J$11=""),"",(Comparador_EV!$J$10+Comparador_EV!$J$11)/12) -> 381.17333 | K17: =IF(COUNT(G17:J17)<4,"",SUM(G17:J17)) -> 1383.6427 | L17: =IF(K17="","",F17+K17) -> 3835.1536 | M17: =Dashboard!$H$12 -> 2304.55 | N17: =IF(OR(L17="",M17=""),"",L17-M17) -> 1530.6036 | O17: =INDEX(Financiamento_EV!$O$17:$O$136,A17) -> 71958.524 | P17: =P16+N17 -> 10714.225 | R17: =A18 -> 8 | S17: =L18 -> 3835.1536 | T17: =M18 -> 2304.55 | U17: =N18 -> 1530.6036
A18: 8 | B18: =INDEX(Financiamento_EV!$B$17:$B$136,A18) -> 46478 | C18: =INDEX(Financiamento_EV!$G$17:$G$136,A18) -> 2451.511 | D18: =INDEX(Financiamento_EV!$L$17:$L$136,A18) -> 0 | E18: =INDEX(Financiamento_EV!$M$17:$M$136,A18) -> 9.094947e-13 | F18: =INDEX(Financiamento_EV!$N$17:$N$136,A18) -> 2451.511 | G18: =IF(Comparador_EV!$J$8="","",Comparador_EV!$J$8/12) -> 471.636 | H18: =IF(Comparador_EV!$J$12="","",Comparador_EV!$J$12/12) -> 64.166667 | I18: =IF(Comparador_EV!$J$9="","",Comparador_EV!$J$9/12) -> 466.66667 | J18: =IF(OR(Comparador_EV!$J$10="",Comparador_EV!$J$11=""),"",(Comparador_EV!$J$10+Comparador_EV!$J$11)/12) -> 381.17333 | K18: =IF(COUNT(G18:J18)<4,"",SUM(G18:J18)) -> 1383.6427 | L18: =IF(K18="","",F18+K18) -> 3835.1536 | M18: =Dashboard!$H$12 -> 2304.55 | N18: =IF(OR(L18="",M18=""),"",L18-M18) -> 1530.6036 | O18: =INDEX(Financiamento_EV!$O$17:$O$136,A18) -> 70730.308 | P18: =P17+N18 -> 12244.829 | R18: =A19 -> 9 | S18: =L19 -> 3835.1536 | T18: =M19 -> 2304.55 | U18: =N19 -> 1530.6036
A19: 9 | B19: =INDEX(Financiamento_EV!$B$17:$B$136,A19) -> 46508 | C19: =INDEX(Financiamento_EV!$G$17:$G$136,A19) -> 2451.511 | D19: =INDEX(Financiamento_EV!$L$17:$L$136,A19) -> 0 | E19: =INDEX(Financiamento_EV!$M$17:$M$136,A19) -> 1.3642421e-12 | F19: =INDEX(Financiamento_EV!$N$17:$N$136,A19) -> 2451.511 | G19: =IF(Comparador_EV!$J$8="","",Comparador_EV!$J$8/12) -> 471.636 | H19: =IF(Comparador_EV!$J$12="","",Comparador_EV!$J$12/12) -> 64.166667 | I19: =IF(Comparador_EV!$J$9="","",Comparador_EV!$J$9/12) -> 466.66667 | J19: =IF(OR(Comparador_EV!$J$10="",Comparador_EV!$J$11=""),"",(Comparador_EV!$J$10+Comparador_EV!$J$11)/12) -> 381.17333 | K19: =IF(COUNT(G19:J19)<4,"",SUM(G19:J19)) -> 1383.6427 | L19: =IF(K19="","",F19+K19) -> 3835.1536 | M19: =Dashboard!$H$12 -> 2304.55 | N19: =IF(OR(L19="",M19=""),"",L19-M19) -> 1530.6036 | O19: =INDEX(Financiamento_EV!$O$17:$O$136,A19) -> 69481.212 | P19: =P18+N19 -> 13775.433 | R19: =A20 -> 10 | S19: =L20 -> 3835.1536 | T19: =M20 -> 2304.55 | U19: =N20 -> 1530.6036
A20: 10 | B20: =INDEX(Financiamento_EV!$B$17:$B$136,A20) -> 46539 | C20: =INDEX(Financiamento_EV!$G$17:$G$136,A20) -> 2451.511 | D20: =INDEX(Financiamento_EV!$L$17:$L$136,A20) -> 0 | E20: =INDEX(Financiamento_EV!$M$17:$M$136,A20) -> 1.3642421e-12 | F20: =INDEX(Financiamento_EV!$N$17:$N$136,A20) -> 2451.511 | G20: =IF(Comparador_EV!$J$8="","",Comparador_EV!$J$8/12) -> 471.636 | H20: =IF(Comparador_EV!$J$12="","",Comparador_EV!$J$12/12) -> 64.166667 | I20: =IF(Comparador_EV!$J$9="","",Comparador_EV!$J$9/12) -> 466.66667 | J20: =IF(OR(Comparador_EV!$J$10="",Comparador_EV!$J$11=""),"",(Comparador_EV!$J$10+Comparador_EV!$J$11)/12) -> 381.17333 | K20: =IF(COUNT(G20:J20)<4,"",SUM(G20:J20)) -> 1383.6427 | L20: =IF(K20="","",F20+K20) -> 3835.1536 | M20: =Dashboard!$H$12 -> 2304.55 | N20: =IF(OR(L20="",M20=""),"",L20-M20) -> 1530.6036 | O20: =INDEX(Financiamento_EV!$O$17:$O$136,A20) -> 68210.882 | P20: =P19+N20 -> 15306.036 | R20: =A21 -> 11 | S20: =L21 -> 3835.1536 | T20: =M21 -> 2304.55 | U20: =N21 -> 1530.6036
A21: 11 | B21: =INDEX(Financiamento_EV!$B$17:$B$136,A21) -> 46569 | C21: =INDEX(Financiamento_EV!$G$17:$G$136,A21) -> 2451.511 | D21: =INDEX(Financiamento_EV!$L$17:$L$136,A21) -> 0 | E21: =INDEX(Financiamento_EV!$M$17:$M$136,A21) -> 2.2737368e-12 | F21: =INDEX(Financiamento_EV!$N$17:$N$136,A21) -> 2451.511 | G21: =IF(Comparador_EV!$J$8="","",Comparador_EV!$J$8/12) -> 471.636 | H21: =IF(Comparador_EV!$J$12="","",Comparador_EV!$J$12/12) -> 64.166667 | I21: =IF(Comparador_EV!$J$9="","",Comparador_EV!$J$9/12) -> 466.66667 | J21: =IF(OR(Comparador_EV!$J$10="",Comparador_EV!$J$11=""),"",(Comparador_EV!$J$10+Comparador_EV!$J$11)/12) -> 381.17333 | K21: =IF(COUNT(G21:J21)<4,"",SUM(G21:J21)) -> 1383.6427 | L21: =IF(K21="","",F21+K21) -> 3835.1536 | M21: =Dashboard!$H$12 -> 2304.55 | N21: =IF(OR(L21="",M21=""),"",L21-M21) -> 1530.6036 | O21: =INDEX(Financiamento_EV!$O$17:$O$136,A21) -> 66918.956 | P21: =P20+N21 -> 16836.64 | R21: =A22 -> 12 | S21: =L22 -> 3835.1536 | T21: =M22 -> 2304.55 | U21: =N22 -> 1530.6036
A22: 12 | B22: =INDEX(Financiamento_EV!$B$17:$B$136,A22) -> 46600 | C22: =INDEX(Financiamento_EV!$G$17:$G$136,A22) -> 2451.511 | D22: =INDEX(Financiamento_EV!$L$17:$L$136,A22) -> 0 | E22: =INDEX(Financiamento_EV!$M$17:$M$136,A22) -> 1.8189894e-12 | F22: =INDEX(Financiamento_EV!$N$17:$N$136,A22) -> 2451.511 | G22: =IF(Comparador_EV!$J$8="","",Comparador_EV!$J$8/12) -> 471.636 | H22: =IF(Comparador_EV!$J$12="","",Comparador_EV!$J$12/12) -> 64.166667 | I22: =IF(Comparador_EV!$J$9="","",Comparador_EV!$J$9/12) -> 466.66667 | J22: =IF(OR(Comparador_EV!$J$10="",Comparador_EV!$J$11=""),"",(Comparador_EV!$J$10+Comparador_EV!$J$11)/12) -> 381.17333 | K22: =IF(COUNT(G22:J22)<4,"",SUM(G22:J22)) -> 1383.6427 | L22: =IF(K22="","",F22+K22) -> 3835.1536 | M22: =Dashboard!$H$12 -> 2304.55 | N22: =IF(OR(L22="",M22=""),"",L22-M22) -> 1530.6036 | O22: =INDEX(Financiamento_EV!$O$17:$O$136,A22) -> 65605.067 | P22: =P21+N22 -> 18367.243 | R22: =A23 -> 13 | S22: =L23 -> 3835.1536 | T22: =M23 -> 2304.55 | U22: =N23 -> 1530.6036
A23: 13 | B23: =INDEX(Financiamento_EV!$B$17:$B$136,A23) -> 46631 | C23: =INDEX(Financiamento_EV!$G$17:$G$136,A23) -> 2451.511 | D23: =INDEX(Financiamento_EV!$L$17:$L$136,A23) -> 0 | E23: =INDEX(Financiamento_EV!$M$17:$M$136,A23) -> 2.7284841e-12 | F23: =INDEX(Financiamento_EV!$N$17:$N$136,A23) -> 2451.511 | G23: =IF(Comparador_EV!$J$8="","",Comparador_EV!$J$8/12) -> 471.636 | H23: =IF(Comparador_EV!$J$12="","",Comparador_EV!$J$12/12) -> 64.166667 | I23: =IF(Comparador_EV!$J$9="","",Comparador_EV!$J$9/12) -> 466.66667 | J23: =IF(OR(Comparador_EV!$J$10="",Comparador_EV!$J$11=""),"",(Comparador_EV!$J$10+Comparador_EV!$J$11)/12) -> 381.17333 | K23: =IF(COUNT(G23:J23)<4,"",SUM(G23:J23)) -> 1383.6427 | L23: =IF(K23="","",F23+K23) -> 3835.1536 | M23: =Dashboard!$H$12 -> 2304.55 | N23: =IF(OR(L23="",M23=""),"",L23-M23) -> 1530.6036 | O23: =INDEX(Financiamento_EV!$O$17:$O$136,A23) -> 64268.842 | P23: =P22+N23 -> 19897.847 | R23: =A24 -> 14 | S23: =L24 -> 3835.1536 | T23: =M24 -> 2304.55 | U23: =N24 -> 1530.6036
... A69: 59 | B69: =INDEX(Financiamento_EV!$B$17:$B$136,A69) -> 48030 | C69: =INDEX(Financiamento_EV!$G$17:$G$136,A69) -> 0 | D69: =INDEX(Financiamento_EV!$L$17:$L$136,A69) -> 0 | E69: =INDEX(Financiamento_EV!$M$17:$M$136,A69) -> 0 | F69: =INDEX(Financiamento_EV!$N$17:$N$136,A69) -> 0 | G69: =IF(Comparador_EV!$J$8="","",Comparador_EV!$J$8/12) -> 471.636 | H69: =IF(Comparador_EV!$J$12="","",Comparador_EV!$J$12/12) -> 64.166667 | I69: =IF(Comparador_EV!$J$9="","",Comparador_EV!$J$9/12) -> 466.66667 | J69: =IF(OR(Comparador_EV!$J$10="",Comparador_EV!$J$11=""),"",(Comparador_EV!$J$10+Comparador_EV!$J$11)/12) -> 381.17333 | K69: =IF(COUNT(G69:J69)<4,"",SUM(G69:J69)) -> 1383.6427 | L69: =IF(K69="","",F69+K69) -> 1383.6427 | M69: =Dashboard!$H$12 -> 2304.55 | N69: =IF(OR(L69="",M69=""),"",L69-M69) -> -920.90733 | O69: =INDEX(Financiamento_EV!$O$17:$O$136,A69) -> 0 | P69: =P68+N69 -> 63338.993 | R69: =A70 -> 60 | S69: =L70 -> 1383.6427 | T69: =M70 -> 2304.55 | U69: =N70 -> -920.90733
A70: 60 | B70: =INDEX(Financiamento_EV!$B$17:$B$136,A70) -> 48061 | C70: =INDEX(Financiamento_EV!$G$17:$G$136,A70) -> 0 | D70: =INDEX(Financiamento_EV!$L$17:$L$136,A70) -> 0 | E70: =INDEX(Financiamento_EV!$M$17:$M$136,A70) -> 0 | F70: =INDEX(Financiamento_EV!$N$17:$N$136,A70) -> 0 | G70: =IF(Comparador_EV!$J$8="","",Comparador_EV!$J$8/12) -> 471.636 | H70: =IF(Comparador_EV!$J$12="","",Comparador_EV!$J$12/12) -> 64.166667 | I70: =IF(Comparador_EV!$J$9="","",Comparador_EV!$J$9/12) -> 466.66667 | J70: =IF(OR(Comparador_EV!$J$10="",Comparador_EV!$J$11=""),"",(Comparador_EV!$J$10+Comparador_EV!$J$11)/12) -> 381.17333 | K70: =IF(COUNT(G70:J70)<4,"",SUM(G70:J70)) -> 1383.6427 | L70: =IF(K70="","",F70+K70) -> 1383.6427 | M70: =Dashboard!$H$12 -> 2304.55 | N70: =IF(OR(L70="",M70=""),"",L70-M70) -> -920.90733 | O70: =INDEX(Financiamento_EV!$O$17:$O$136,A70) -> 0 | P70: =P69+N70 -> 62418.086
A71: 61 | B71: =INDEX(Financiamento_EV!$B$17:$B$136,A71) -> 48092 | C71: =INDEX(Financiamento_EV!$G$17:$G$136,A71) -> 0 | D71: =INDEX(Financiamento_EV!$L$17:$L$136,A71) -> 0 | E71: =INDEX(Financiamento_EV!$M$17:$M$136,A71) -> 0 | F71: =INDEX(Financiamento_EV!$N$17:$N$136,A71) -> 0 | G71: =IF(Comparador_EV!$J$8="","",Comparador_EV!$J$8/12) -> 471.636 | H71: =IF(Comparador_EV!$J$12="","",Comparador_EV!$J$12/12) -> 64.166667 | I71: =IF(Comparador_EV!$J$9="","",Comparador_EV!$J$9/12) -> 466.66667 | J71: =IF(OR(Comparador_EV!$J$10="",Comparador_EV!$J$11=""),"",(Comparador_EV!$J$10+Comparador_EV!$J$11)/12) -> 381.17333 | K71: =IF(COUNT(G71:J71)<4,"",SUM(G71:J71)) -> 1383.6427 | L71: =IF(K71="","",F71+K71) -> 1383.6427 | M71: =Dashboard!$H$12 -> 2304.55 | N71: =IF(OR(L71="",M71=""),"",L71-M71) -> -920.90733 | O71: =INDEX(Financiamento_EV!$O$17:$O$136,A71) -> 0 | P71: =P70+N71 -> 61497.178
A72: 62 | B72: =INDEX(Financiamento_EV!$B$17:$B$136,A72) -> 48122 | C72: =INDEX(Financiamento_EV!$G$17:$G$136,A72) -> 0 | D72: =INDEX(Financiamento_EV!$L$17:$L$136,A72) -> 0 | E72: =INDEX(Financiamento_EV!$M$17:$M$136,A72) -> 0 | F72: =INDEX(Financiamento_EV!$N$17:$N$136,A72) -> 0 | G72: =IF(Comparador_EV!$J$8="","",Comparador_EV!$J$8/12) -> 471.636 | H72: =IF(Comparador_EV!$J$12="","",Comparador_EV!$J$12/12) -> 64.166667 | I72: =IF(Comparador_EV!$J$9="","",Comparador_EV!$J$9/12) -> 466.66667 | J72: =IF(OR(Comparador_EV!$J$10="",Comparador_EV!$J$11=""),"",(Comparador_EV!$J$10+Comparador_EV!$J$11)/12) -> 381.17333 | K72: =IF(COUNT(G72:J72)<4,"",SUM(G72:J72)) -> 1383.6427 | L72: =IF(K72="","",F72+K72) -> 1383.6427 | M72: =Dashboard!$H$12 -> 2304.55 | N72: =IF(OR(L72="",M72=""),"",L72-M72) -> -920.90733 | O72: =INDEX(Financiamento_EV!$O$17:$O$136,A72) -> 0 | P72: =P71+N72 -> 60576.271
A73: 63 | B73: =INDEX(Financiamento_EV!$B$17:$B$136,A73) -> 48153 | C73: =INDEX(Financiamento_EV!$G$17:$G$136,A73) -> 0 | D73: =INDEX(Financiamento_EV!$L$17:$L$136,A73) -> 0 | E73: =INDEX(Financiamento_EV!$M$17:$M$136,A73) -> 0 | F73: =INDEX(Financiamento_EV!$N$17:$N$136,A73) -> 0 | G73: =IF(Comparador_EV!$J$8="","",Comparador_EV!$J$8/12) -> 471.636 | H73: =IF(Comparador_EV!$J$12="","",Comparador_EV!$J$12/12) -> 64.166667 | I73: =IF(Comparador_EV!$J$9="","",Comparador_EV!$J$9/12) -> 466.66667 | J73: =IF(OR(Comparador_EV!$J$10="",Comparador_EV!$J$11=""),"",(Comparador_EV!$J$10+Comparador_EV!$J$11)/12) -> 381.17333 | K73: =IF(COUNT(G73:J73)<4,"",SUM(G73:J73)) -> 1383.6427 | L73: =IF(K73="","",F73+K73) -> 1383.6427 | M73: =Dashboard!$H$12 -> 2304.55 | N73: =IF(OR(L73="",M73=""),"",L73-M73) -> -920.90733 | O73: =INDEX(Financiamento_EV!$O$17:$O$136,A73) -> 0 | P73: =P72+N73 -> 59655.364
A74: 64 | B74: =INDEX(Financiamento_EV!$B$17:$B$136,A74) -> 48183 | C74: =INDEX(Financiamento_EV!$G$17:$G$136,A74) -> 0 | D74: =INDEX(Financiamento_EV!$L$17:$L$136,A74) -> 0 | E74: =INDEX(Financiamento_EV!$M$17:$M$136,A74) -> 0 | F74: =INDEX(Financiamento_EV!$N$17:$N$136,A74) -> 0 | G74: =IF(Comparador_EV!$J$8="","",Comparador_EV!$J$8/12) -> 471.636 | H74: =IF(Comparador_EV!$J$12="","",Comparador_EV!$J$12/12) -> 64.166667 | I74: =IF(Comparador_EV!$J$9="","",Comparador_EV!$J$9/12) -> 466.66667 | J74: =IF(OR(Comparador_EV!$J$10="",Comparador_EV!$J$11=""),"",(Comparador_EV!$J$10+Comparador_EV!$J$11)/12) -> 381.17333 | K74: =IF(COUNT(G74:J74)<4,"",SUM(G74:J74)) -> 1383.6427 | L74: =IF(K74="","",F74+K74) -> 1383.6427 | M74: =Dashboard!$H$12 -> 2304.55 | N74: =IF(OR(L74="",M74=""),"",L74-M74) -> -920.90733 | O74: =INDEX(Financiamento_EV!$O$17:$O$136,A74) -> 0 | P74: =P73+N74 -> 58734.456
A75: 65 | B75: =INDEX(Financiamento_EV!$B$17:$B$136,A75) -> 48214 | C75: =INDEX(Financiamento_EV!$G$17:$G$136,A75) -> 0 | D75: =INDEX(Financiamento_EV!$L$17:$L$136,A75) -> 0 | E75: =INDEX(Financiamento_EV!$M$17:$M$136,A75) -> 0 | F75: =INDEX(Financiamento_EV!$N$17:$N$136,A75) -> 0 | G75: =IF(Comparador_EV!$J$8="","",Comparador_EV!$J$8/12) -> 471.636 | H75: =IF(Comparador_EV!$J$12="","",Comparador_EV!$J$12/12) -> 64.166667 | I75: =IF(Comparador_EV!$J$9="","",Comparador_EV!$J$9/12) -> 466.66667 | J75: =IF(OR(Comparador_EV!$J$10="",Comparador_EV!$J$11=""),"",(Comparador_EV!$J$10+Comparador_EV!$J$11)/12) -> 381.17333 | K75: =IF(COUNT(G75:J75)<4,"",SUM(G75:J75)) -> 1383.6427 | L75: =IF(K75="","",F75+K75) -> 1383.6427 | M75: =Dashboard!$H$12 -> 2304.55 | N75: =IF(OR(L75="",M75=""),"",L75-M75) -> -920.90733 | O75: =INDEX(Financiamento_EV!$O$17:$O$136,A75) -> 0 | P75: =P74+N75 -> 57813.549
A76: 66 | B76: =INDEX(Financiamento_EV!$B$17:$B$136,A76) -> 48245 | C76: =INDEX(Financiamento_EV!$G$17:$G$136,A76) -> 0 | D76: =INDEX(Financiamento_EV!$L$17:$L$136,A76) -> 0 | E76: =INDEX(Financiamento_EV!$M$17:$M$136,A76) -> 0 | F76: =INDEX(Financiamento_EV!$N$17:$N$136,A76) -> 0 | G76: =IF(Comparador_EV!$J$8="","",Comparador_EV!$J$8/12) -> 471.636 | H76: =IF(Comparador_EV!$J$12="","",Comparador_EV!$J$12/12) -> 64.166667 | I76: =IF(Comparador_EV!$J$9="","",Comparador_EV!$J$9/12) -> 466.66667 | J76: =IF(OR(Comparador_EV!$J$10="",Comparador_EV!$J$11=""),"",(Comparador_EV!$J$10+Comparador_EV!$J$11)/12) -> 381.17333 | K76: =IF(COUNT(G76:J76)<4,"",SUM(G76:J76)) -> 1383.6427 | L76: =IF(K76="","",F76+K76) -> 1383.6427 | M76: =Dashboard!$H$12 -> 2304.55 | N76: =IF(OR(L76="",M76=""),"",L76-M76) -> -920.90733 | O76: =INDEX(Financiamento_EV!$O$17:$O$136,A76) -> 0 | P76: =P75+N76 -> 56892.642
A77: 67 | B77: =INDEX(Financiamento_EV!$B$17:$B$136,A77) -> 48274 | C77: =INDEX(Financiamento_EV!$G$17:$G$136,A77) -> 0 | D77: =INDEX(Financiamento_EV!$L$17:$L$136,A77) -> 0 | E77: =INDEX(Financiamento_EV!$M$17:$M$136,A77) -> 0 | F77: =INDEX(Financiamento_EV!$N$17:$N$136,A77) -> 0 | G77: =IF(Comparador_EV!$J$8="","",Comparador_EV!$J$8/12) -> 471.636 | H77: =IF(Comparador_EV!$J$12="","",Comparador_EV!$J$12/12) -> 64.166667 | I77: =IF(Comparador_EV!$J$9="","",Comparador_EV!$J$9/12) -> 466.66667 | J77: =IF(OR(Comparador_EV!$J$10="",Comparador_EV!$J$11=""),"",(Comparador_EV!$J$10+Comparador_EV!$J$11)/12) -> 381.17333 | K77: =IF(COUNT(G77:J77)<4,"",SUM(G77:J77)) -> 1383.6427 | L77: =IF(K77="","",F77+K77) -> 1383.6427 | M77: =Dashboard!$H$12 -> 2304.55 | N77: =IF(OR(L77="",M77=""),"",L77-M77) -> -920.90733 | O77: =INDEX(Financiamento_EV!$O$17:$O$136,A77) -> 0 | P77: =P76+N77 -> 55971.734
A78: 68 | B78: =INDEX(Financiamento_EV!$B$17:$B$136,A78) -> 48305 | C78: =INDEX(Financiamento_EV!$G$17:$G$136,A78) -> 0 | D78: =INDEX(Financiamento_EV!$L$17:$L$136,A78) -> 0 | E78: =INDEX(Financiamento_EV!$M$17:$M$136,A78) -> 0 | F78: =INDEX(Financiamento_EV!$N$17:$N$136,A78) -> 0 | G78: =IF(Comparador_EV!$J$8="","",Comparador_EV!$J$8/12) -> 471.636 | H78: =IF(Comparador_EV!$J$12="","",Comparador_EV!$J$12/12) -> 64.166667 | I78: =IF(Comparador_EV!$J$9="","",Comparador_EV!$J$9/12) -> 466.66667 | J78: =IF(OR(Comparador_EV!$J$10="",Comparador_EV!$J$11=""),"",(Comparador_EV!$J$10+Comparador_EV!$J$11)/12) -> 381.17333 | K78: =IF(COUNT(G78:J78)<4,"",SUM(G78:J78)) -> 1383.6427 | L78: =IF(K78="","",F78+K78) -> 1383.6427 | M78: =Dashboard!$H$12 -> 2304.55 | N78: =IF(OR(L78="",M78=""),"",L78-M78) -> -920.90733 | O78: =INDEX(Financiamento_EV!$O$17:$O$136,A78) -> 0 | P78: =P77+N78 -> 55050.827
A79: 69 | B79: =INDEX(Financiamento_EV!$B$17:$B$136,A79) -> 48335 | C79: =INDEX(Financiamento_EV!$G$17:$G$136,A79) -> 0 | D79: =INDEX(Financiamento_EV!$L$17:$L$136,A79) -> 0 | E79: =INDEX(Financiamento_EV!$M$17:$M$136,A79) -> 0 | F79: =INDEX(Financiamento_EV!$N$17:$N$136,A79) -> 0 | G79: =IF(Comparador_EV!$J$8="","",Comparador_EV!$J$8/12) -> 471.636 | H79: =IF(Comparador_EV!$J$12="","",Comparador_EV!$J$12/12) -> 64.166667 | I79: =IF(Comparador_EV!$J$9="","",Comparador_EV!$J$9/12) -> 466.66667 | J79: =IF(OR(Comparador_EV!$J$10="",Comparador_EV!$J$11=""),"",(Comparador_EV!$J$10+Comparador_EV!$J$11)/12) -> 381.17333 | K79: =IF(COUNT(G79:J79)<4,"",SUM(G79:J79)) -> 1383.6427 | L79: =IF(K79="","",F79+K79) -> 1383.6427 | M79: =Dashboard!$H$12 -> 2304.55 | N79: =IF(OR(L79="",M79=""),"",L79-M79) -> -920.90733 | O79: =INDEX(Financiamento_EV!$O$17:$O$136,A79) -> 0 | P79: =P78+N79 -> 54129.92
A80: 70 | B80: =INDEX(Financiamento_EV!$B$17:$B$136,A80) -> 48366 | C80: =INDEX(Financiamento_EV!$G$17:$G$136,A80) -> 0 | D80: =INDEX(Financiamento_EV!$L$17:$L$136,A80) -> 0 | E80: =INDEX(Financiamento_EV!$M$17:$M$136,A80) -> 0 | F80: =INDEX(Financiamento_EV!$N$17:$N$136,A80) -> 0 | G80: =IF(Comparador_EV!$J$8="","",Comparador_EV!$J$8/12) -> 471.636 | H80: =IF(Comparador_EV!$J$12="","",Comparador_EV!$J$12/12) -> 64.166667 | I80: =IF(Comparador_EV!$J$9="","",Comparador_EV!$J$9/12) -> 466.66667 | J80: =IF(OR(Comparador_EV!$J$10="",Comparador_EV!$J$11=""),"",(Comparador_EV!$J$10+Comparador_EV!$J$11)/12) -> 381.17333 | K80: =IF(COUNT(G80:J80)<4,"",SUM(G80:J80)) -> 1383.6427 | L80: =IF(K80="","",F80+K80) -> 1383.6427 | M80: =Dashboard!$H$12 -> 2304.55 | N80: =IF(OR(L80="",M80=""),"",L80-M80) -> -920.90733 | O80: =INDEX(Financiamento_EV!$O$17:$O$136,A80) -> 0 | P80: =P79+N80 -> 53209.012
A81: 71 | B81: =INDEX(Financiamento_EV!$B$17:$B$136,A81) -> 48396 | C81: =INDEX(Financiamento_EV!$G$17:$G$136,A81) -> 0 | D81: =INDEX(Financiamento_EV!$L$17:$L$136,A81) -> 0 | E81: =INDEX(Financiamento_EV!$M$17:$M$136,A81) -> 0 | F81: =INDEX(Financiamento_EV!$N$17:$N$136,A81) -> 0 | G81: =IF(Comparador_EV!$J$8="","",Comparador_EV!$J$8/12) -> 471.636 | H81: =IF(Comparador_EV!$J$12="","",Comparador_EV!$J$12/12) -> 64.166667 | I81: =IF(Comparador_EV!$J$9="","",Comparador_EV!$J$9/12) -> 466.66667 | J81: =IF(OR(Comparador_EV!$J$10="",Comparador_EV!$J$11=""),"",(Comparador_EV!$J$10+Comparador_EV!$J$11)/12) -> 381.17333 | K81: =IF(COUNT(G81:J81)<4,"",SUM(G81:J81)) -> 1383.6427 | L81: =IF(K81="","",F81+K81) -> 1383.6427 | M81: =Dashboard!$H$12 -> 2304.55 | N81: =IF(OR(L81="",M81=""),"",L81-M81) -> -920.90733 | O81: =INDEX(Financiamento_EV!$O$17:$O$136,A81) -> 0 | P81: =P80+N81 -> 52288.105
... A130: 120 | B130: =INDEX(Financiamento_EV!$B$17:$B$136,A130) -> 49888 | C130: =INDEX(Financiamento_EV!$G$17:$G$136,A130) -> 0 | D130: =INDEX(Financiamento_EV!$L$17:$L$136,A130) -> 0 | E130: =INDEX(Financiamento_EV!$M$17:$M$136,A130) -> 0 | F130: =INDEX(Financiamento_EV!$N$17:$N$136,A130) -> 0 | G130: =IF(Comparador_EV!$J$8="","",Comparador_EV!$J$8/12) -> 471.636 | H130: =IF(Comparador_EV!$J$12="","",Comparador_EV!$J$12/12) -> 64.166667 | I130: =IF(Comparador_EV!$J$9="","",Comparador_EV!$J$9/12) -> 466.66667 | J130: =IF(OR(Comparador_EV!$J$10="",Comparador_EV!$J$11=""),"",(Comparador_EV!$J$10+Comparador_EV!$J$11)/12) -> 381.17333 | K130: =IF(COUNT(G130:J130)<4,"",SUM(G130:J130)) -> 1383.6427 | L130: =IF(K130="","",F130+K130) -> 1383.6427 | M130: =Dashboard!$H$12 -> 2304.55 | N130: =IF(OR(L130="",M130=""),"",L130-M130) -> -920.90733 | O130: =INDEX(Financiamento_EV!$O$17:$O$136,A130) -> 0 | P130: =P129+N130 -> 7163.6457

Sheet Handoff_EV
A1: Handoff — baseline do Tiida para comparar carros elétricos
A3: Use o cenário CENTRAL como caso-base. Mantenha otimista e stress como sensibilidade. Compare separadamente fluxo de caixa mensal e custo econômico.
A5: Baseline atual
A6: Métrica | B6: Valor | C6: Unidade | D6: Status | E6: Como usar | F6: Observação
A7: Data-base | B7: 46278 | C7: data | D7: Atual | E7: Referência temporal | F7: Último lançamento Drivvo
A8: Rodagem anual | B8: 21438 | C8: km/ano | D8: Base | E8: Mesma rodagem no EV | F8: 13/09/25 → 13/09/26
A9: Combustível otimizado | B9: 10858.57 | C9: R$/ano | D9: Base | E9: Custo do Tiida para frente | F9: Etanol
A10: Seguro | B10: 3516.24 | C10: R$/ano | D10: Atual | E10: Comparar com cotação EV | F10: R$ 293,02/mês
A11: IPVA | B11: 1404.88 | C11: R$/ano | D11: Estimativa | E11: Comparar com EV | F11: Trocar pelo pago quando disponível
A12: Licenciamento | B12: 174.08 | C12: R$/ano | D12: 2026 | E12: Comparar
A13: Manutenção otimista | B13: 8739.46 | C13: R$/ano | D13: Sensibilidade | E13: Piso
A14: Manutenção CENTRAL | B14: 11700.83 | C14: R$/ano | D14: PRINCIPAL | E14: Caso-base | F14: Histórico longo por km
A15: Manutenção stress | B15: 15295.73 | C15: R$/ano | D15: Sensibilidade | E15: Teto | F15: Ritmo recente
A16: TCO caixa CENTRAL | B16: 27654.6 | C16: R$/ano | D16: PRINCIPAL | E16: Base contra EV
A17: TCO caixa CENTRAL / mês | B17: 2304.55 | C17: R$/mês | D17: PRINCIPAL | E17: Base contra parcela
A18: TCO econômico CENTRAL / mês | B18: 2397.16 | C18: R$/mês | D18: PRINCIPAL | E18: Base econômica | F18: Inclui depreciação
A20: Texto pronto para copiar para o chat de comparação
A21: Baseline atualizada do meu Nissan Tiida SL 1.8 manual 2011/2012: rodo cerca de 21,438 km/ano. Para frente, considere etanol a R$ 3.89/L, consumo de referência de 7.68 km/L e combustível projetado de ~R$ 10,859/ano. Seguro: R$ 3,516/ano; IPVA estimado: R$ 1,405/ano; licenciamento: R$ 174/ano. O histórico de manutenção agora soma R$ 48,321 registrados entre 137.762 e 226.295 km (~R$ 0.546/km). A manutenção anual central é ~R$ 11,701; cenário otimista ~R$ 8,739; stress ~R$ 15,296. O TCO de caixa CENTRAL do Tiida é ~R$ 27,655/ano ou R$ 2,305/mês; o TCO econômico, incluindo depreciação de 3% a.a., é ~R$ 2,397/mês. Para cada EV, compare energia, manutenção, seguro, IPVA/licenciamento, depreciação, preço, entrada, CET e parcela. Quero ver (1) delta mensal de caixa incluindo parcela; (2) economia operacional antes da parcela; e (3) delta econômico anual, tratando juros/CET e depreciação como custo econômico.
A33: Modelo integrado: use Comparador_EV como cockpit. Financiamento_EV detalha a amortização do cenário ativo; Cenarios_Fin compara as três estratégias; Fluxo_EV mostra a parcela líquida mês a mês.

Sheet Premissas
A1: Premissas e fontes — TCO Tiida
A3: Premissa | B3: Valor | C3: Unidade | D3: Tipo | E3: Fonte / observação
A4: Odômetro inicial (13/09/2025) | B4: 204860 | C4: km | D4: Histórico | E4: Drivvo; leitura comparável de 12 meses
A5: Odômetro final (13/09/2026) | B5: 226298 | C5: km | D5: Histórico | E5: Drivvo; último abastecimento disponível
A6: Dias entre leituras | B6: 365 | C6: dias | D6: Cálculo | E6: Período exato de 12 meses
A7: Quilometragem anual | B7: =B5-B4 -> 21438 | C7: km/ano | D7: Cálculo | E7: Odômetro final - inicial
A8: Seguro mensal atual | B8: 293.02 | C8: R$/mês | D8: Input usuário | E8: Valor informado pelo usuário
A9: Seguro anual atual | B9: =B8*12 -> 3516.24 | C9: R$/ano | D9: Cálculo | E9: Seguro mensal × 12
A10: FIPE Tiida SL manual — jan/2026 | B10: 35122 | C10: R$ | D10: Referência | E10: Mantida da versão anterior do modelo
A11: FIPE Tiida SL manual — set/2026 | B11: 37044 | C11: R$ | D11: Referência | E11: Mantida da versão anterior do modelo
A12: Alíquota IPVA SP — carro passeio | B12: 0.04 | C12: % | D12: Referência | E12: Mantida da versão anterior do modelo
A13: IPVA anual estimado | B13: =B10*B12 -> 1404.88 | C13: R$/ano | D13: Cálculo | E13: FIPE jan/2026 × alíquota; trocar pelo valor pago quando disponível
A14: Licenciamento SP 2026 | B14: 174.08 | C14: R$/ano | D14: Referência | E14: Mantido da versão anterior
A15: Etanol — preço atual usado | B15: 3.89 | C15: R$/L | D15: Drivvo | E15: Último abastecimento: 13/09/2026
A16: Gasolina — preço atual usado | B16: 6.29 | C16: R$/L | D16: Drivvo | E16: Último abastecimento: 13/09/2026
A17: Consumo etanol — referência | B17: 7.68 | C17: km/L | D17: Histórico | E17: Ciclos puros analisados; premissa mantida
A18: Consumo gasolina — referência | B18: 9.53 | C18: km/L | D18: Histórico | E18: Ciclos puros analisados; premissa mantida
A19: Amortização das corretivas | B19: 3 | C19: anos | D19: Premissa editável | E19: Usada somente no cenário otimista
A20: Depreciação anual Tiida | B20: 0.03 | C20: % a.a. | D20: Premissa editável | E20: Cenário econômico; editar conforme hipótese
A21: Data-base do Drivvo | B21: 46278 | C21: data | D21: Histórico | E21: Último lançamento usado nesta atualização

Sheet Historico_Mensal
A1: Histórico mensal — out/2025 a set/2026
A2: Setembro/2026 é parcial até 13/09. O Dashboard usa uma janela móvel exata de 12 meses para o histórico principal.
A4: Mês | B4: Combustível | C4: Serviços | D4: Seguro | E4: IPVA prov. | F4: Licenc. prov. | G4: TCO de caixa
A5: out/2025 | B5: 1209.161 | C5: 3693 | D5: 293.02 | E5: 117.07333 | F5: 14.506667 | G5: =SUM(B5:F5) -> 5326.761
A6: nov/2025 | B6: 1199.344 | C6: 0 | D6: 293.02 | E6: 117.07333 | F6: 14.506667 | G6: =SUM(B6:F6) -> 1623.944
A7: dez/2025 | B7: 1067.661 | C7: 0 | D7: 293.02 | E7: 117.07333 | F7: 14.506667 | G7: =SUM(B7:F7) -> 1492.261
A8: jan/2026 | B8: 919.53 | C8: 0 | D8: 293.02 | E8: 117.07333 | F8: 14.506667 | G8: =SUM(B8:F8) -> 1344.13
A9: fev/2026 | B9: 981 | C9: 0 | D9: 293.02 | E9: 117.07333 | F9: 14.506667 | G9: =SUM(B9:F9) -> 1405.6
A10: mar/2026 | B10: 1239.23 | C10: 6980 | D10: 293.02 | E10: 117.07333 | F10: 14.506667 | G10: =SUM(B10:F10) -> 8643.83
A11: abr/2026 | B11: 910.647 | C11: 0 | D11: 293.02 | E11: 117.07333 | F11: 14.506667 | G11: =SUM(B11:F11) -> 1335.247
A12: mai/2026 | B12: 1592.506 | C12: 300 | D12: 293.02 | E12: 117.07333 | F12: 14.506667 | G12: =SUM(B12:F12) -> 2317.106
A13: jun/2026 | B13: 938.198 | C13: 4089.6 | D13: 293.02 | E13: 117.07333 | F13: 14.506667 | G13: =SUM(B13:F13) -> 5452.398
A14: jul/2026 | B14: 751.474 | C14: 1431 | D14: 293.02 | E14: 117.07333 | F14: 14.506667 | G14: =SUM(B14:F14) -> 2607.074
A15: ago/2026 | B15: 1443.786 | C15: 0 | D15: 293.02 | E15: 117.07333 | F15: 14.506667 | G15: =SUM(B15:F15) -> 1868.386
A16: set/2026 | B16: 539.287 | C16: 1288.86 | D16: 293.02 | E16: 117.07333 | F16: 14.506667 | G16: =SUM(B16:F16) -> 2252.747
A18: TOTAL DO PERÍODO EXIBIDO | B18: =SUM(B5:B16) -> 12791.824 | C18: =SUM(C5:C16) -> 17782.46 | D18: =SUM(D5:D16) -> 3516.24 | E18: =SUM(E5:E16) -> 1404.88 | F18: =SUM(F5:F16) -> 174.08 | G18: =SUM(G5:G16) -> 35669.484

Sheet Servicos_12m
A1: Serviços — 12 meses móveis até 13/09/2026
A3: Data | B3: Odômetro | C3: Serviço | D3: Categoria TCO | E3: Valor | F3: Local | G3: Observação | H3: Evento
A4: 45931.744 | B4: 206212 | C4: Filtro de Ar | D4: Preventiva / desgaste | E4: 70 | F4: HML Motors | H4: 01/10/2025 • 206.212 km
A5: 45931.744 | B5: 206212 | C5: Filtro de Combustível | D5: Preventiva / desgaste | E5: 38 | F5: HML Motors | H5: 01/10/2025 • 206.212 km
A6: 45931.744 | B6: 206212 | C6: Filtro de cabine | D6: Preventiva / desgaste | E6: 45 | F6: HML Motors | H6: 01/10/2025 • 206.212 km
A7: 45931.744 | B7: 206212 | C7: Filtro de Óleo | D7: Preventiva / desgaste | E7: 40 | F7: HML Motors | H7: 01/10/2025 • 206.212 km
A8: 45931.744 | B8: 206212 | C8: Mão de obra | D8: Preventiva / desgaste | E8: 110 | F8: HML Motors | H8: 01/10/2025 • 206.212 km
A9: 45931.744 | B9: 206212 | C9: Troca de Óleo | D9: Preventiva / desgaste | E9: 200 | F9: HML Motors | H9: 01/10/2025 • 206.212 km
A10: 45943.484 | B10: 207152 | C10: Alinhamento de roda | D10: Preventiva / desgaste | E10: 100 | F10: Aguiar Pneus | H10: 13/10/2025 • 207.152 km
A11: 45960.105 | B11: 208315 | C11: Bucha do eixo traseiro | D11: Corretiva / recuperação | E11: 190 | F11: W12 Car Service | H11: 30/10/2025 • 208.315 km
A12: 45960.105 | B12: 208315 | C12: Coxim Hidráulico do Motor | D12: Corretiva / recuperação | E12: 390 | F12: W12 Car Service | H12: 30/10/2025 • 208.315 km
A13: 45960.105 | B13: 208315 | C13: Coxim inferior do motor | D13: Corretiva / recuperação | E13: 230 | F13: W12 Car Service | H13: 30/10/2025 • 208.315 km
A14: 45960.105 | B14: 208315 | C14: Kit coxim do amortecedor dianteiro | D14: Corretiva / recuperação | E14: 830 | F14: W12 Car Service | H14: 30/10/2025 • 208.315 km
A15: 45960.105 | B15: 208315 | C15: Limpeza dos drenos do teto solar | D15: Corretiva / recuperação | E15: 250 | F15: W12 Car Service | H15: 30/10/2025 • 208.315 km
... A59: 46222.957 | B59: 222470 | C59: Bateria | D59: Preventiva / desgaste | E59: 490 | F59: Baterias Automotivas Colmeia | H59: 19/07/2026 • 222.470 km
A60: 46278.698 | B60: 226295 | C60: Braço Axial | D60: Preventiva / desgaste | E60: 100 | F60: Auto Posto Fevereiro Ltda | G60: Troca de óleo 225000km | H60: 13/09/2026 • 226.295 km
A61: 46278.698 | B61: 226295 | C61: Coifa homocinetica direita | D61: Preventiva / desgaste | E61: 140 | F61: Auto Posto Fevereiro Ltda | G61: Troca de óleo 225000km | H61: 13/09/2026 • 226.295 km
A62: 46278.698 | B62: 226295 | C62: Filtro Inflow | D62: Preventiva / desgaste | E62: 279.35 | F62: Auto Posto Fevereiro Ltda | G62: Troca de óleo 225000km | H62: 13/09/2026 • 226.295 km
A63: 46278.698 | B63: 226295 | C63: Filtro de Combustível | D63: Preventiva / desgaste | E63: 24.99 | F63: Auto Posto Fevereiro Ltda | G63: Troca de óleo 225000km | H63: 13/09/2026 • 226.295 km
A64: 46278.698 | B64: 226295 | C64: Filtro de cabine | D64: Preventiva / desgaste | E64: 39.68 | F64: Auto Posto Fevereiro Ltda | G64: Troca de óleo 225000km | H64: 13/09/2026 • 226.295 km
A65: 46278.698 | B65: 226295 | C65: Filtro de Óleo | D65: Preventiva / desgaste | E65: 19.34 | F65: Auto Posto Fevereiro Ltda | G65: Troca de óleo 225000km | H65: 13/09/2026 • 226.295 km
A66: 46278.698 | B66: 226295 | C66: Mão de obra | D66: Preventiva / desgaste | E66: 460 | F66: Auto Posto Fevereiro Ltda | G66: Troca de óleo 225000km | H66: 13/09/2026 • 226.295 km
A67: 46278.698 | B67: 226295 | C67: Óleo 5W30 | D67: Preventiva / desgaste | E67: 225.5 | F67: Auto Posto Fevereiro Ltda | G67: Troca de óleo 225000km | H67: 13/09/2026 • 226.295 km

Sheet Abastecimentos_12m
A1: Abastecimentos — 12 meses móveis até 13/09/2026
A3: Data | B3: Odômetro | C3: Combustível | D3: Preço/L | E3: Valor | F3: Volume | G3: Tanque cheio | H3: Média registrada | I3: Posto | K3: Atualização
A4: 45919.876 | B4: 205371 | C4: Gas. Comum | D4: 5.89 | E4: 259.749 | F4: 44.1 | G4: Sim | H4: 12.073 | I4: Auto Posto Vergueirão(3 postos) | K4: O registro de 10/08/2026 está agora corretamente classificado como Etanol no novo Drivvo.
A5: 45923.943 | B5: 205813 | C5: Gas. Comum | D5: 5.89 | E5: 215.633 | F5: 36.61 | G5: Sim | H5: 10.883 | I5: Auto Posto Vergueirão(3 postos) | K5: Preço mais recente: etanol R$ 3.89/L; gasolina R$ 6.29/L.
A6: 45932.477 | B6: 206242 | C6: Gas. Comum | D6: 5.89 | E6: 232.19 | F6: 39.421 | G6: Sim | H6: 12.138 | I6: Auto Posto Vergueirão(3 postos) | K6: Relação de preços atual: 61.8%.
A7: 45936.95 | B7: 206728 | C7: Gas. Comum | D7: 5.89 | E7: 235.84 | F7: 40.041 | G7: Sim | H7: 11.367 | I7: Auto Posto Vergueirão(3 postos)
A8: 45941.485 | B8: 207042 | C8: Gas. Comum | D8: 5.89 | E8: 96.72 | F8: 16.421 | G8: Não | H8: 11.367 | I8: Auto Posto Vergueirão(3 postos)
A9: 45945.804 | B9: 207368 | C9: Gas. Comum | D9: 5.89 | E9: 234.9 | F9: 39.881 | G9: Sim | H9: 10.411 | I9: Auto Posto Vergueirão(3 postos)
A10: 45950.488 | B10: 207773 | C10: Gas. Comum | D10: 5.89 | E10: 100 | F10: 16.978 | G10: Não | H10: 10.411 | I10: Ipiranga na saída de Santos
A11: 45951.254 | B11: 207947 | C11: Gas. Comum | D11: 5.89 | E11: 67.711 | F11: 11.496 | G11: Não | H11: 10.411 | I11: Auto Posto Vergueirão(3 postos)
A12: 45952.479 | B12: 208072 | C12: Gas. Comum | D12: 5.89 | E12: 96.72 | F12: 16.421 | G12: Não | H12: 10.411 | I12: Auto Posto Vergueirão(3 postos)
A13: 45955.479 | B13: 208294 | C13: Gas. Comum | D13: 5.89 | E13: 145.08 | F13: 24.632 | G13: Não | H13: 10.411 | I13: Auto Posto Vergueirão(3 postos)
A14: 45965.509 | B14: 208500 | C14: Etanol | D14: 4.89 | E14: 48.9 | F14: 10 | G14: Não | H14: 10.411 | I14: Auto Posto Vergueirão(3 postos)
A15: 45965.777 | B15: 208588 | C15: Gas. Comum | D15: 5.99 | E15: 225.583 | F15: 37.66 | G15: Sim | H15: 10.165 | I15: Shell 4 pistas - Santos
A16: 45972.005 | B16: 208952 | C16: Gas. Comum | D16: 5.89 | E16: 210.921 | F16: 35.81 | G16: Sim | H16: 10.165 | I16: Auto Posto Vergueirão(3 postos)
A17: 45978.758 | B17: 209394 | C17: Gas. Comum | D17: 5.99 | E17: 260.46 | F17: 43.482 | G17: Sim | H17: 9.716 | I17: Shell Paulicéia
A18: 45986.484 | B18: 209777 | C18: Gas. Comum | D18: 5.89 | E18: 232.19 | F18: 39.421 | G18: Sim | H18: 12.776 | I18: Auto Posto Vergueirão(3 postos)
... A96: 46278.644 | B96: 226298 | C96: Etanol | D96: 3.89 | E96: 91.695 | F96: 23.572 | G96: Sim | H96: 0 | I96: Shell Paulicéia

Sheet Historico_Manutencao
A1: Histórico de manutenção do Tiida — 2021 a 2026
A3: Data | B3: Ano | C3: Odômetro | D3: OS / evento | E3: Valor registrado | F3: Período | G3: Fonte | H3: Observação | J3: Resumo anual registrado
A4: 44517 | B4: 2021 | C4: 137762 | D4: OS #5843 | E4: 1069 | F4: Pré-compra | G4: 11.2021 - ordem_servico_5843.pdf | H4: Falha de ignição / bobinas. | J4: Ano | K4: Pré-compra | L4: Sua posse | M4: Total registrado | N4: Observação
A5: 44655 | B5: 2022 | C5: 139982 | D5: OS #6535 | E5: 3818.2 | F5: Pré-compra | G5: 04.2022 - ordem_servico_6535.pdf | H5: Revisão, arrefecimento, coxim, buchas e freios. | J5: 2021 | K5: 1069 | L5: 0 | M5: =K5+L5 -> 1069 | N5: Parcial
A6: 44995 | B6: 2023 | C6: 149429 | D6: OS #8301 | E6: 3618.52 | F6: Pré-compra | G6: 03.2023 - ordem_servico_8301.pdf | H6: Revisão, óleo de câmbio e freios dianteiros. | J6: 2022 | K6: 3818.2 | L6: 0 | M6: =K6+L6 -> 3818.2
A7: 45189 | B7: 2023 | C7: 155929 | D7: OS #9418 | E7: 496.72 | F7: Pré-compra | G7: 09.2023 - Ordem de Serviço #9418.pdf | H7: Troca de óleo e filtros. | J7: 2023 | K7: 4115.24 | L7: 0 | M7: =K7+L7 -> 4115.24
A8: 45455 | B8: 2024 | C8: 173551 | D8: OS #11032 | E8: 6584 | F8: Pré-compra | G8: 06.2024 - Ordem de Serviço #11032.pdf | H8: Grande revisão; a OS não inclui peças fornecidas externamente. | J8: 2024 | K8: 12730.4 | L8: 0 | M8: =K8+L8 -> 12730.4
A9: 45581 | B9: 2024 | C9: 182517 | D9: OS #11813 | E9: 3908.4 | F9: Pré-compra | G9: 10.2024 - ordem_servico_11813.pdf | H9: Ignição/injeção e freios traseiros. | J9: 2025 | K9: 7227.9 | L9: 5271 | M9: =K9+L9 -> 12498.9
A10: 45596 | B10: 2024 | C10: 183706 | D10: OS #11913 | E10: 2238 | F10: Pré-compra | G10: 10.2024 - ordem_servico_11913.pdf | H10: Bomba de combustível / tanque. | J10: 2026 | K10: 0 | L10: 14089.46 | M10: =K10+L10 -> 14089.46 | N10: Parcial até 13/09
A11: 45782 | B11: 2025 | C11: 197260 | D11: OS #12928 | E11: 4470.4 | F11: Pré-compra | G11: 05.2025 - ordem_servico_12928.pdf | H11: Revisão, junta da tampa, coxins e freios.
A12: 45803 | B12: 2025 | C12: 198895 | D12: OS #13052 | E12: 1364 | F12: Pré-compra | G12: 05.2025 - ordem_servico_13052.pdf | H12: Tensor da correia de acessórios. | J12: Métricas e cenários
A13: 45804 | B13: 2025 | C13: 198895 | D13: OS #13064 | E13: 1393.5 | F13: Pré-compra | G13: 05.2025 - ordem_servico_13064.pdf | H13: Velas e bobina de ignição. | J13: Métrica | K13: Valor | L13: Unidade | M13: Uso | N13: Nota
A14: 45812 | B14: 2025 | C14: 199160 | D14: Drivvo 04/06 | E14: 250 | F14: Sua posse | G14: Drivvo CSV | H14: Freios / retífica e mão de obra. | J14: Manutenção pré-compra registrada | K14: 28960.74 | L14: R$ | M14: Histórico | N14: 10 OS recebidas
A15: 45829 | B15: 2025 | C15: 199761 | D15: Drivvo 21/06 | E15: 680 | F15: Sua posse | G15: Drivvo CSV | H15: Cubo de roda traseiro + mão de obra. | J15: Manutenção na sua posse | K15: 19360.46 | L15: R$ | M15: Histórico | N15: Drivvo jun/2025–13/09/2026
A16: 45894 | B16: 2025 | C16: 202734 | D16: Drivvo 25/08 | E16: 648 | F16: Sua posse | G16: Drivvo CSV | H16: Freio traseiro / arrefecimento. | J16: Manutenção total registrada | K16: 48321.2 | L16: R$ | M16: Histórico | N16: Não corrigida por inflação
A17: 45931 | B17: 2025 | C17: 206212 | D17: Drivvo 01/10 | E17: 503 | F17: Sua posse | G17: Drivvo CSV | H17: Óleo, filtros e mão de obra. | J17: Quilometragem coberta | K17: 88533 | L17: km | M17: Histórico | N17: 137.762 → 226.295 km
A18: 45943 | B18: 2025 | C18: 207152 | D18: Drivvo 13/10 | E18: 100 | F18: Sua posse | G18: Drivvo CSV | H18: Alinhamento. | J18: Custo registrado por km | K18: 0.546 | L18: R$/km | M18: Baseline central | N18: Piso provável: há custos externos não comprovados
A19: 45960 | B19: 2025 | C19: 208315 | D19: Drivvo 30/10 | E19: 3090 | F19: Sua posse | G19: Drivvo CSV | H19: Buchas, coxins e kit do amortecedor dianteiro. | J19: Manutenção anual — otimista | K19: 8739.46 | L19: R$/ano | M19: Sensibilidade | N19: Preventiva 12m + corretivas/3
A20: 46084 | B20: 2026 | C20: 215846 | D20: Drivvo 03/03 | E20: 6980 | F20: Sua posse | G20: Drivvo CSV | H20: Grande corretiva: suspensão, radiador, fluidos e mão de obra. | J20: Manutenção anual — CENTRAL | K20: 11700.83 | L20: R$/ano | M20: Principal | N20: Histórico longo por km × uso atual
A21: 46154 | B21: 2026 | C21: 219458 | D21: Drivvo 12/05 | E21: 300 | F21: Sua posse | G21: Drivvo CSV | H21: Reset via scanner. | J21: Manutenção anual — central+ | K21: 12881.2 | L21: R$/ano | M21: Sensibilidade | N21: Inclui proxy das peças externas da OS 11032
A22: 46176 | B22: 2026 | C22: 220582 | D22: Drivvo 03/06 | E22: 1736.6 | F22: Sua posse | G22: Drivvo CSV | H22: Revisão, freios, óleo e arrefecimento. | J22: Manutenção anual — stress | K22: 15295.73 | L22: R$/ano | M22: Sensibilidade | N22: R$/km da sua posse recente
A23: 46189 | B23: 2026 | C23: 221241 | D23: Drivvo 16/06 | E23: 2353 | F23: Sua posse | G23: Drivvo CSV | H23: Cubos, mangueiras, junta e mão de obra. | J23: Proxy peças externas OS 11032 | K23: 4874.6 | L23: R$ referência | M23: Sensibilidade | N23: Não é gasto real comprovado
A24: 46204 | B24: 2026 | C24: 221817 | D24: Drivvo 01/07 | E24: 380 | F24: Sua posse | G24: Drivvo CSV | H24: Óleo do câmbio e limpeza. | J24: Serviços reais — 12m móveis | K24: 17782.46 | L24: R$/ano | M24: Histórico | N24: 14/09/2025–13/09/2026
A25: 46206 | B25: 2026 | C25: 221917 | D25: Drivvo 03/07 | E25: 561 | F25: Sua posse | G25: Drivvo CSV | H25: Para-barro / carroceria; incidente.
A26: 46222 | B26: 2026 | C26: 222470 | D26: Drivvo 19/07 | E26: 490 | F26: Sua posse | G26: Drivvo CSV | H26: Bateria Bosch. | J26: Leitura: o cenário CENTRAL continua sendo o caso-base para comparar um EV. Ele foi atualizado com a revisão de 13/09/2026 e com a rodagem anual atual de 21.438 km. O cenário otimista assume menor repetição de grandes corretivas; o stress mantém o ritmo recente.
A27: 46278 | B27: 2026 | C27: 226295 | D27: Drivvo 13/09 | E27: 1288.86 | F27: Sua posse | G27: Drivvo CSV | H27: Revisão 225 mil km: óleo, filtros, braço axial, coifa e mão de obra.
